Workbook
Name Baseline_Rate: Segment_Analysis!$F$4
Name FollowUp_Size: Lead_Scoring!$B$16
Name Hot_Cutoff: Lead_Scoring!$B$14
Name Profile_Inputs: Profile_Checker!$B$8:$B$15
Name Slicer_Education: #N/A
Name Slicer_Marital_Status: #N/A
Name Slicer_Region: #N/A
Name Takeaway_MinN: Pivot_Analysis!$F$4
Name Total_Buyers: Segment_Analysis!$D$4
Name Total_Customers: Segment_Analysis!$B$4
Name Warm_Cutoff: Lead_Scoring!$B$15

Sheet Dashboard
B1: Who Buys Bikes? Customer targeting dashboard | AA1: Chart data — do not edit
B3: 1,000 customers · purchase rate analysis · use the slicers to filter | AA3: % of Customers Targeted | AB3: Model | AC3: Random | AE3: Factor | AF3: Significant | AG3: Not significant
AA4: {=_xlfn.VSTACK(0,tbl_Gains[Decile]/ROWS(tbl_Gains[Decile]))} -> 0 | AB4: {=_xlfn.VSTACK(0,tbl_Gains[% of All Buyers Captured])} -> 0 | AC4: {=_xlfn.ANCHORARRAY(AA4)} -> 0 | AE4: {=_xlfn.LET(_xlpm.f,tbl_Significance[Factor],_xlpm.v,tbl_Significance[Cramér''s V],_xlpm.g,tbl_Significance[Significant?],_xlfn.SORTBY(_xlfn.HSTACK(_xlpm.f,IF(_xlpm.g="Yes",_xlpm.v,NA()),IF(_xlpm.g="No",_xlpm.v,NA())),_xlpm.v,1))} -> Home Owner | AF4: #N/A | AG4: 0.015153622
AA5: 0.1 | AB5: 0.16632017 | AC5: 0.1 | AE5: Gender | AF5: #N/A | AG5: 0.015178634
AA6: 0.2 | AB6: 0.3014553 | AC6: 0.2 | AE6: Occupation | AF6: #N/A | AG6: 0.089474532
AA7: 0.3 | AB7: 0.43866944 | AC7: 0.3 | AE7: Income Band | AF7: 0.10615007 | AG7: #N/A
AA8: 0.4 | AB8: 0.54677755 | AC8: 0.4 | AE8: Marital Status | AF8: 0.11151483 | AG8: #N/A
AA9: 0.5 | AB9: 0.65280665 | AC9: 0.5 | AE9: Region | AF9: 0.11727057 | AG9: #N/A
B10: Slicers filter the KPI cards and the four purchase-rate charts. Model charts show all customers. | AA10: 0.6 | AB10: 0.72557173 | AC10: 0.6 | AE10: Education | AF10: 0.15916245 | AG10: #N/A
B11: Customers | F11: Buyers | J11: Purchase rate | N11: Model · all customers | AA11: 0.7 | AB11: 0.80665281 | AC11: 0.7 | AE11: Children | AF11: 0.17903952 | AG11: #N/A
B12: =IFERROR(GETPIVOTDATA("Customers",Pivot_Analysis!$A$5),0) -> 1000 | F12: =IFERROR(GETPIVOTDATA("Buyers",Pivot_Analysis!$A$5),0) -> 481 | J12: =IFERROR(GETPIVOTDATA("Purchase Rate",Pivot_Analysis!$A$5),NA()) -> 0.481 | N12: =INDEX(tbl_TierSummary[Share of All Buyers],1) -> 0.43866944 | AA12: 0.8 | AB12: 0.91683992 | AC12: 0.8 | AE12: Commute Distance | AF12: 0.18577338 | AG12: #N/A
AA13: 0.9 | AB13: 0.96049896 | AC13: 0.9 | AE13: Age Band | AF13: 0.20549751 | AG13: #N/A
B14: ="of "&TEXT(Total_Customers,"#,##0")&" customers in total" -> of 1,000 customers in total | F14: =IFERROR(TEXT(F12/B12,"0.0%")&" of filtered customers bought","—") -> 48.1% of filtered customers bought | J14: =IFERROR(TEXT((J12-Baseline_Rate)*100,"+0.0;-0.0;0.0")&" pp vs "&TEXT(Baseline_Rate,"0.0%")&" overall","No customers in this filter") -> 0.0 pp vs 48.1% overall | N14: ="Hot tier's share of buyers (not filtered)" -> Hot tier's share of buyers (not filtered) | AA14: 1 | AB14: 1 | AC14: 1 | AE14: Car Ownership | AF14: 0.22331278 | AG14: #N/A
B15: =IF(B12<50,"⚠ Small group (n = "&TEXT(B12,"#,##0")&"). Read with caution.","") | AE15: Cars | AF15: 0.2257998 | AG15: #N/A
B16: Takeaways (these follow the slicers)
B17: {=IFERROR(_xlfn.LET(_xlpm.d,Pivot_Analysis!$A$12:$B$19,_xlpm.f,_xlfn._xlws.FILTER(_xlpm.d,ISNUMBER(INDEX(_xlpm.d,,2))),_xlpm.s,INDEX(_xlpm.f,,1),_xlpm.r,INDEX(_xlpm.f,,2),_xlpm.n,_xlfn.XLOOKUP(_xlpm.s,INDEX(Pivot_Analysis!$A$60:$B$67,,1),INDEX(Pivot_Analysis!$A$60:$B$67,,2),0),_xlpm.ok,_xlpm.n>=Takeaway_MinN,IF(SUM(--_xlpm.ok)=0,"• Best age band: not enough customers in any band to compare.",_xlfn.LET(_xlpm.rr,_xlfn._xlws.FILTER(_xlpm.r,_xlpm.ok),_xlpm.ss,_xlfn._xlws.FILTER(_xlpm.s,_xlpm.ok),_xlpm.nn,_xlfn._xlws.FILTER(_xlpm.n,_xlpm.ok),_xlpm.m,MAX(_xlpm.rr),"• Best age band: "&_xlfn.XLOOKUP(_xlpm.m,_xlpm.rr,_xlpm.ss)&" buys at "&TEXT(_xlpm.m,"0.0%")&" (n = "&TEXT(_xlfn.XLOOKUP(_xlpm.m,_xlpm.rr,_xlpm.nn),"#,##0")&")."))),"• Best age band: not enough customers in any band to compare.")} -> • Best age band: 31-40 buys at 61.1% (n = 316).
B18: =IFERROR(_xlfn.LET(_xlpm.na,IFERROR(GETPIVOTDATA("Customers",Pivot_Analysis!$A$79,"Car Ownership","0-1 Cars"),0),_xlpm.nb,IFERROR(GETPIVOTDATA("Customers",Pivot_Analysis!$A$79,"Car Ownership","2+ Cars"),0),IF(OR(_xlpm.na<Takeaway_MinN,_xlpm.nb<Takeaway_MinN),"• Car ownership gap: not enough customers in one group to compare.",_xlfn.LET(_xlpm.a,GETPIVOTDATA("Purchase Rate",Pivot_Analysis!$A$52,"Car Ownership","0-1 Cars"),_xlpm.b,GETPIVOTDATA("Purchase Rate",Pivot_Analysis!$A$52,"Car Ownership","2+ Cars"),"• Car ownership gap: 0-1 Cars buy at "&TEXT(_xlpm.a,"0.0%")&" vs "&TEXT(_xlpm.b,"0.0%")&" for 2+ Cars ("&TEXT((_xlpm.a-_xlpm.b)*100,"+0.0;-0.0;0.0")&" pp; n = "&TEXT(_xlpm.na,"#,##0")&" vs "&TEXT(_xlpm.nb,"#,##0")&")."))),"• Car ownership gap: not enough customers in one group to compare.") -> • Car ownership gap: 0-1 Cars buy at 58.9% vs 36.6% for 2+ Cars (+22.3 pp; n = 514 vs 486).
B19: {=IFERROR(_xlfn.LET(_xlpm.d,Pivot_Analysis!$A$22:$B$29,_xlpm.f,_xlfn._xlws.FILTER(_xlpm.d,ISNUMBER(INDEX(_xlpm.d,,2))),_xlpm.s,INDEX(_xlpm.f,,1),_xlpm.r,INDEX(_xlpm.f,,2),_xlpm.n,_xlfn.XLOOKUP(_xlpm.s,INDEX(Pivot_Analysis!$A$70:$B$77,,1),INDEX(Pivot_Analysis!$A$70:$B$77,,2),0),_xlpm.ok,_xlpm.n>=Takeaway_MinN,IF(SUM(--_xlpm.ok)=0,"• Lowest commute band: not enough customers in any band to compare.",_xlfn.LET(_xlpm.rr,_xlfn._xlws.FILTER(_xlpm.r,_xlpm.ok),_xlpm.ss,_xlfn._xlws.FILTER(_xlpm.s,_xlpm.ok),_xlpm.nn,_xlfn._xlws.FILTER(_xlpm.n,_xlpm.ok),_xlpm.m,MIN(_xlpm.rr),"• Lowest commute band: "&_xlfn.XLOOKUP(_xlpm.m,_xlpm.rr,_xlpm.ss)&" buys at only "&TEXT(_xlpm.m,"0.0%")&" (n = "&TEXT(_xlfn.XLOOKUP(_xlpm.m,_xlpm.rr,_xlpm.nn),"#,##0")&")."))),"• Lowest commute band: not enough customers in any band to compare.")} -> • Lowest commute band: 10+ Miles buys at only 29.7% (n = 111).
B72: Chart data for the model charts is in hidden columns AA–AI. See README_Brief › Technical notes.

Sheet README_Brief
A1: Who Buys Bikes? A Customer Targeting Analysis
A2: Purpose: project brief with the business question, approach and dataset, and a guide to every sheet in this workbook.
A4: Business question | B4: With a limited marketing budget, which customers should the retailer target to sell more bikes?
A5: Stakeholder | B5: Marketing Manager, bike retailer.
A6: Objective | B6: Find the groups most likely to buy, then score every customer so the best leads come first.
A7: Success metric | B7: Purchase rate = buyers ÷ customers (analysed by rate, not raw counts).
A8: Dataset | B8: Alex the Analyst's public Bike Buyers dataset. Raw: 1,026 rows × 13 fields, including 26 exact duplicate rows. After cleaning: 1,000 unique customers, 13 fields.
A9: Approach | B9: Clean → Segment by purchase rate → Test significance → Score leads → Dashboard → Recommendations.
A10: Tools | B10: Excel Tables, dynamic array formulas (LET, XLOOKUP, UNIQUE, FILTER, SORTBY), COUNTIFS, CHISQ.TEST, PivotTables, PivotCharts, slicers, GETPIVOTDATA, data validation, conditional formatting.
A11: Author | B11: Malachy Ugwu (github.com/Shikamaru-n)
A13: Sheet index
A14: Sheet | B14: Description
A15: Dashboard | B15: One-page summary: KPI cards, takeaways and four slicer-driven PivotCharts, plus two static model charts.
A16: README_Brief | B16: Project brief, approach, this sheet index and technical notes.
A17: Data_Dictionary | B17: Field definitions, data types, live unique-value counts and cleaning notes.
A18: Data_Quality_Log | B18: Log of every data issue found and the cleaning action taken, with live checks against Raw_Data.
A19: Clean_Data | B19: Clean dataset (tbl_Clean): 1,000 de-duplicated customers with decoded fields, plus 8 live formula columns (bands, sort keys, 1/0 purchase flag).
A20: Segment_Analysis | B20: Purchase rate and lift by every customer attribute and band, with a factor ranking by spread.
A21: Significance_Tests | B21: Chi-square tests (CHISQ.TEST) and Cramér's V showing which factors are significantly linked to purchasing.
A22: Lead_Scoring | B22: 0–100 propensity score, rank, decile and Hot/Warm/Cold tier for every customer, with tier summary and gains table.
A23: Profile_Checker | B23: Interactive dropdowns: pick a customer profile to see its estimated purchase rate, score, tier and matching customers.
A24: Pivot_Analysis | B24: Nine PivotTables. Six feed the Dashboard charts and KPI cards (KPIs, Age Band, Commute, Cars, Children, Car Ownership); three count segment sizes for the takeaways.
A25: Recommendations | B25: Seven actions for the Marketing Manager, each backed by a live number, plus limitations and next steps.
A26: Raw_Data | B26: Original source data (1,026 rows × 13 fields). Read-only and never modified.
A28: Technical notes
A29: # | B29: Where | C29: What | D29: Why
A30: 1 | B30: Dashboard, columns AA–AI (hidden) | C30: Chart data area for the two model charts: the gains table with "% of customers targeted", a random-targeting line and a 0% start point; Cramér's V split into "Significant" and "Not significant" columns, with #N/A where a factor doesn't belong. | D30: Ordinary charts must read from cells. Reshaping lets the gains curve compare the model with random targeting and lets bars be coloured by significance (#N/A draws no bar). Hidden to keep the dashboard clean; both charts are set to show data in hidden columns. Right-click the column headers → Unhide to inspect.
A31: 2 | B31: Clean_Data | C31: The 13 original columns are pasted values after de-duplication; the 8 derived columns are live formulas. | D31: An Excel Table can't hold a live UNIQUE() spill. Data_Quality_Log re-checks Clean_Data against Raw_Data with live formulas.
A32: 3 | B32: Pivot_Analysis | C32: Commute Distance order set manually (10+ Miles moved to the end). | D32: PivotTables sort text alphabetically, which would put 10+ before 2-5. A manual order persists on refresh.
A33: 4 | B33: Dashboard slicers | C33: Each slicer is connected to all 9 PivotTables via Report Connections. | D33: One click filters every PivotChart, KPI card and takeaway together.
A34: 5 | B34: Dashboard | C34: Slicers + PivotCharts for the filtered views; formula-based charts for the model results. | D34: Slicers can only drive PivotTables. Model results describe the whole customer base, so they stay fixed.
A35: 6 | B35: Profile_Checker | C35: Dropdowns (data validation) instead of slicers. | D35: The checker scores one hypothetical profile with formulas, which slicers can't drive.
A36: 7 | B36: Lead_Scoring | C36: Ties in Raw Score broken by lower ID; Decile = ROUNDUP(Rank × 10 / customers). | D36: Unique ranks give exactly 100 customers per decile.
A37: 8 | B37: Lead_Scoring | C37: Model uses 8 factors; excludes Cars (duplicates Car Ownership) and Occupation, Home Owner, Gender (not significant). | D37: Avoids double-counting and keeps only factors with statistical evidence (Significance_Tests).
A38: 9 | B38: Profile_Checker | C38: Scores outside the real customers' range are clamped to 0–100; likelihood uses the tier's actual purchase rate, not the decile's. | D38: Hypothetical profiles can be more extreme than any real customer; deciles 6 and 8 are uneven, tier rates are more stable.
A39: 10 | B39: Lead_Scoring / Profile_Checker | C39: Rates and scores are in-sample (built and evaluated on the same 1,000 customers). | D39: Results are indicative, not a validated forecast. See Recommendations.
A40: 11 | B40: Clean_Data and money cells | C40: Currency format [$$-en-US]#,##0. | D40: Prevents the en-NG locale displaying £.
A41: 12 | B41: Dashboard KPI cards | C41: Custom small-group warning: shows "⚠ Small group (n = X)" when filtered customers < 50. | D41: Percentages from small groups swing wildly (one customer can move the rate by 2+ pp); the threshold of 50 is a common rule of thumb, not an Excel feature.
... A43: 14 | B43: Pivot_Analysis E8:F12 | C43: Title cells for the 4 PivotCharts, linked to Baseline_Rate. | D43: PivotChart titles can only link to a cell, so these cells build "… (overall avg 48.1%)" and keep the average live.

Sheet Data_Dictionary
A1: Data dictionary
A2: Purpose: defines every Raw_Data field (type, meaning, examples and live unique-value count) and the cleaning it needs before analysis.
A4: Field | B4: Data Type | C4: Description | D4: Example Values | E4: Unique Values | F4: Notes/Cleaning Needed
A5: ID | B5: Whole number | C5: Unique customer identifier (primary key). | D5: 12496, 24107, 14177 | E5: =COUNTA(_xlfn.UNIQUE(_xlfn.XLOOKUP(tbl_Dictionary[[#This Row],[Field]],Raw_Data!$A$1:$M$1,Raw_Data!$A$2:$M$1027))) -> 1000 | F5: 26 exact duplicate rows (1,026 rows → 1,000 unique IDs). Remove duplicates in Clean_Data.
A6: Marital Status | B6: Text (code) | C6: Customer's marital status. | D6: M, S | E6: =COUNTA(_xlfn.UNIQUE(_xlfn.XLOOKUP(tbl_Dictionary[[#This Row],[Field]],Raw_Data!$A$1:$M$1,Raw_Data!$A$2:$M$1027))) -> 2 | F6: Recode M/S → Married/Single.
A7: Gender | B7: Text (code) | C7: Customer's gender. | D7: M, F | E7: =COUNTA(_xlfn.UNIQUE(_xlfn.XLOOKUP(tbl_Dictionary[[#This Row],[Field]],Raw_Data!$A$1:$M$1,Raw_Data!$A$2:$M$1027))) -> 2 | F7: Recode M/F → Male/Female.
A8: Income | B8: Number (US$) | C8: Annual household income in US dollars. | D8: $10,000 – $170,000 | E8: =COUNTA(_xlfn.UNIQUE(_xlfn.XLOOKUP(tbl_Dictionary[[#This Row],[Field]],Raw_Data!$A$1:$M$1,Raw_Data!$A$2:$M$1027))) -> 16 | F8: Recorded in $10,000 steps. Band into income groups for segmentation; display as [$$-en-US]#,##0.
A9: Children | B9: Whole number | C9: Number of children. | D9: 0 – 5 | E9: =COUNTA(_xlfn.UNIQUE(_xlfn.XLOOKUP(tbl_Dictionary[[#This Row],[Field]],Raw_Data!$A$1:$M$1,Raw_Data!$A$2:$M$1027))) -> 6 | F9: No cleaning needed.
A10: Education | B10: Text (category) | C10: Highest level of education completed. | D10: Partial High School, High School, Partial College, Bachelors, Graduate Degree | E10: =COUNTA(_xlfn.UNIQUE(_xlfn.XLOOKUP(tbl_Dictionary[[#This Row],[Field]],Raw_Data!$A$1:$M$1,Raw_Data!$A$2:$M$1027))) -> 5 | F10: Ordinal: needs an ordered sort (Partial High School → High School → Partial College → Bachelors → Graduate Degree), not alphabetical.
A11: Occupation | B11: Text (category) | C11: Occupation group. | D11: Manual, Skilled Manual, Clerical, Professional, Management | E11: =COUNTA(_xlfn.UNIQUE(_xlfn.XLOOKUP(tbl_Dictionary[[#This Row],[Field]],Raw_Data!$A$1:$M$1,Raw_Data!$A$2:$M$1027))) -> 5 | F11: No cleaning needed.
A12: Home Owner | B12: Text (Yes/No) | C12: Whether the customer owns their home. | D12: Yes, No | E12: =COUNTA(_xlfn.UNIQUE(_xlfn.XLOOKUP(tbl_Dictionary[[#This Row],[Field]],Raw_Data!$A$1:$M$1,Raw_Data!$A$2:$M$1027))) -> 2 | F12: No cleaning needed.
A13: Cars | B13: Whole number | C13: Number of cars owned. | D13: 0 – 4 | E13: =COUNTA(_xlfn.UNIQUE(_xlfn.XLOOKUP(tbl_Dictionary[[#This Row],[Field]],Raw_Data!$A$1:$M$1,Raw_Data!$A$2:$M$1027))) -> 5 | F13: No cleaning needed.
A14: Commute Distance | B14: Text (category) | C14: Distance from home to work. | D14: 0-1 Miles, 1-2 Miles, 2-5 Miles, 5-10 Miles, 10+ Miles | E14: =COUNTA(_xlfn.UNIQUE(_xlfn.XLOOKUP(tbl_Dictionary[[#This Row],[Field]],Raw_Data!$A$1:$M$1,Raw_Data!$A$2:$M$1027))) -> 5 | F14: Ordinal: needs a sort order (0-1, 1-2, 2-5, 5-10, 10+). Alphabetical sorting puts 10+ second.
A15: Region | B15: Text (category) | C15: Geographic region. | D15: Europe, North America, Pacific | E15: =COUNTA(_xlfn.UNIQUE(_xlfn.XLOOKUP(tbl_Dictionary[[#This Row],[Field]],Raw_Data!$A$1:$M$1,Raw_Data!$A$2:$M$1027))) -> 3 | F15: No cleaning needed.
A16: Age | B16: Whole number | C16: Customer's age in years. | D16: 25 – 89 | E16: =COUNTA(_xlfn.UNIQUE(_xlfn.XLOOKUP(tbl_Dictionary[[#This Row],[Field]],Raw_Data!$A$1:$M$1,Raw_Data!$A$2:$M$1027))) -> 53 | F16: Too many distinct values to segment directly. Band into age groups.
A17: Purchased Bike | B17: Text (Yes/No) | C17: Whether the customer bought a bike. | D17: Yes, No | E17: =COUNTA(_xlfn.UNIQUE(_xlfn.XLOOKUP(tbl_Dictionary[[#This Row],[Field]],Raw_Data!$A$1:$M$1,Raw_Data!$A$2:$M$1027))) -> 2 | F17: Target variable. Convert to a 1/0 flag in Clean_Data so purchase rate = AVERAGE(flag).
A19: Live data checks (against Raw_Data)
A20: Total rows | B20: =ROWS(Raw_Data!$A$2:$A$1027) -> 1026 | C20: Raw dataset size.
A21: Unique IDs | B21: =COUNTA(_xlfn.UNIQUE(Raw_Data!$A$2:$A$1027)) -> 1000 | C21: Unique customers after de-duplication.
A22: Exact duplicate rows | B22: =ROWS(Raw_Data!$A$2:$M$1027)-ROWS(_xlfn.UNIQUE(Raw_Data!$A$2:$M$1027)) -> 26 | C22: To be removed in Clean_Data.
A23: Blank cells (all 13 fields) | B23: =COUNTBLANK(Raw_Data!$A$2:$M$1027) -> 0 | C23: No blank values in any field, so no imputation is needed.

Sheet Data_Quality_Log
A1: Data quality log
A2: Purpose: audit trail of every data-quality check and cleaning action from Raw_Data to Clean_Data, with live validation checks.
A4: Step | B4: Check / Action | C4: Field(s) | D4: Rows Before | E4: Rows Affected | F4: Rows After | G4: Method | H4: Rationale
A5: 1 | B5: Row count check (Raw_Data) | C5: All 13 fields | D5: =ROWS(Raw_Data!$A$2:$A$1027) -> 1026 | E5: 0 | F5: =D5-E5 -> 1026 | G5: ROWS() on Raw_Data. | H5: Establish the baseline row count before any cleaning.
A6: 2 | B6: Blank value check (all 13 fields) | C6: All 13 fields | D6: =ROWS(Raw_Data!$A$2:$A$1027) -> 1026 | E6: =COUNTBLANK(Raw_Data!$A$2:$M$1027) -> 0 | F6: =ROWS(Raw_Data!$A$2:$A$1027) -> 1026 | G6: COUNTBLANK() across Raw_Data!A2:M1027 (Rows Affected = blank cells found). | H6: Blanks would bias purchase rates; none found, so no imputation or exclusion needed.
A7: 3 | B7: Exact duplicate removal | C7: All 13 fields | D7: =ROWS(Raw_Data!$A$2:$A$1027) -> 1026 | E7: =ROWS(Raw_Data!$A$2:$A$1027)-ROWS(_xlfn.UNIQUE(Raw_Data!$A$2:$M$1027)) -> 26 | F7: =ROWS(tbl_Clean[]) -> 1000 | G7: Copied Raw_Data to Clean_Data and removed rows identical across all 13 fields, keeping the first occurrence in original order. | H7: Duplicate customers would be double-counted and inflate segment counts and rates.
A8: 4 | B8: Duplicate ID check after removal | C8: ID | D8: =ROWS(tbl_Clean[ID]) -> 1000 | E8: =ROWS(tbl_Clean[ID])-ROWS(_xlfn.UNIQUE(tbl_Clean[ID])) -> 0 | F8: =D8-E8 -> 1000 | G8: ROWS() minus ROWS(UNIQUE()) on tbl_Clean[ID]. | H8: Confirms ID is a true primary key: one row per customer.
A9: 5 | B9: Range check: Age (25-89), Income ($10k-$170k), Children (0-5), Cars (0-4) | C9: Age, Income, Children, Cars | D9: =ROWS(tbl_Clean[]) -> 1000 | E9: {=SUM(COUNTIFS(tbl_Clean[Age],{"<25",">89"}),COUNTIFS(tbl_Clean[Income],{"<10000",">170000"}),COUNTIFS(tbl_Clean[Children],{"<0",">5"}),COUNTIFS(tbl_Clean[Cars],{"<0",">4"}))} -> 0 | F9: =D9-E9 -> 1000 | G9: COUNTIFS() for values outside each expected range (Rows Affected = out-of-range values). | H9: Catches impossible or mistyped values that would distort the bands.
A10: 6 | B10: Category consistency check (no typos / stray spaces in text fields) | C10: Marital Status, Gender, Education, Occupation, Home Owner, Commute Distance, Region, Purchased Bike | D10: =ROWS(tbl_Clean[]) -> 1000 | E10: {=SUMPRODUCT(--(LEN(tbl_Clean[[Marital Status]:[Purchased Bike]])<>LEN(TRIM(tbl_Clean[[Marital Status]:[Purchased Bike]]))))} -> 0 | F10: =D10-E10 -> 1000 | G10: LEN() vs LEN(TRIM()) for stray spaces (Rows Affected = cells with stray spaces). UNIQUE() level counts were reviewed against Data_Dictionary and showed no unexpected variants. | H10: Typos or trailing spaces would split one category into several and fragment segment rates.
A11: 7 | B11: Decode Marital Status and Gender | C11: Marital Status, Gender | D11: =ROWS(tbl_Clean[]) -> 1000 | E11: {=SUM(COUNTIFS(tbl_Clean[Marital Status],{"Married","Single"}))} -> 1000 | F11: =ROWS(tbl_Clean[]) -> 1000 | G11: Recoded in place in Clean_Data: M→Married, S→Single; M→Male, F→Female (Rows Affected = rows decoded). | H11: Readable labels for charts and slicers. It also removes the clash between M (Married) and M (Male).
A12: 8 | B12: Derived columns added: Age Band, Age Band Sort, Income Band, Income Band Sort, Car Ownership, Commute Sort, Education Sort, Purchased Flag | C12: Age, Income, Cars, Commute Distance, Education, Purchased Bike | D12: =ROWS(tbl_Clean[]) -> 1000 | E12: =ROWS(tbl_Clean[]) -> 1000 | F12: =ROWS(tbl_Clean[]) -> 1000 | G12: Live structured-reference formulas in tbl_Clean (IFS for bands, XMATCH for sort orders, IF for the 1/0 flag). | H12: Bands make continuous fields segmentable; sort keys give a logical (not alphabetical) order; the flag lets purchase rate = AVERAGE(flag).
B14: Validation checks
B15: Check | C15: Expected | D15: Actual | E15: Status
B16: Clean rows = 1,000 | C16: 1000 | D16: =ROWS(tbl_Clean[]) -> 1000 | E16: =IF(tbl_Validation[[#This Row],[Actual]]=tbl_Validation[[#This Row],[Expected]],"PASS","FAIL") -> PASS
B17: Unique IDs in tbl_Clean = 1,000 | C17: 1000 | D17: =ROWS(_xlfn.UNIQUE(tbl_Clean[ID])) -> 1000 | E17: =IF(tbl_Validation[[#This Row],[Actual]]=tbl_Validation[[#This Row],[Expected]],"PASS","FAIL") -> PASS
B18: Blank cells in tbl_Clean = 0 | C18: 0 | D18: =COUNTBLANK(tbl_Clean[]) -> 0 | E18: =IF(tbl_Validation[[#This Row],[Actual]]=tbl_Validation[[#This Row],[Expected]],"PASS","FAIL") -> PASS
B19: Raw unique rows = Clean rows | C19: =ROWS(_xlfn.UNIQUE(Raw_Data!$A$2:$M$1027)) -> 1000 | D19: =ROWS(tbl_Clean[]) -> 1000 | E19: =IF(tbl_Validation[[#This Row],[Actual]]=tbl_Validation[[#This Row],[Expected]],"PASS","FAIL") -> PASS
B20: Sum of Purchased Flag = count of "Yes" in tbl_Clean | C20: =COUNTIFS(tbl_Clean[Purchased Bike],"Yes") -> 481 | D20: =SUM(tbl_Clean[Purchased Flag]) -> 481 | E20: =IF(tbl_Validation[[#This Row],[Actual]]=tbl_Validation[[#This Row],[Expected]],"PASS","FAIL") -> PASS
B21: Only Married/Single and Male/Female in Marital Status and Gender (invalid values = 0) | C21: 0 | D21: {=2*ROWS(tbl_Clean[])-SUM(COUNTIFS(tbl_Clean[Marital Status],{"Married","Single"}))-SUM(COUNTIFS(tbl_Clean[Gender],{"Male","Female"}))} -> 0 | E21: =IF(tbl_Validation[[#This Row],[Actual]]=tbl_Validation[[#This Row],[Expected]],"PASS","FAIL") -> PASS
B22: Every row has a non-blank Age Band and Income Band (missing = 0) | C22: 0 | D22: =2*ROWS(tbl_Clean[])-COUNTIF(tbl_Clean[Age Band],"?*")-COUNTIF(tbl_Clean[Income Band],"?*") -> 0 | E22: =IF(tbl_Validation[[#This Row],[Actual]]=tbl_Validation[[#This Row],[Expected]],"PASS","FAIL") -> PASS
B24: Overall data quality: | C24: =IF(COUNTIF(tbl_Validation[Status],"FAIL")=0,"ALL CHECKS PASSED",COUNTIF(tbl_Validation[Status],"FAIL")&" CHECK(S) FAILED") -> ALL CHECKS PASSED

Sheet Clean_Data
A1: Clean data
A2: Purpose: analysis-ready dataset of 1,000 unique customers (26 exact duplicates removed), with codes decoded and live band, sort and flag columns.
A4: ID | B4: Marital Status | C4: Gender | D4: Income | E4: Children | F4: Education | G4: Occupation | H4: Home Owner | I4: Cars | J4: Commute Distance | K4: Region | L4: Age | M4: Purchased Bike | N4: Age Band | O4: Age Band Sort | P4: Income Band | Q4: Income Band Sort | R4: Car Ownership | S4: Commute Sort | T4: Education Sort | U4: Purchased Flag
A5: 12496 | B5: Married | C5: Female | D5: 40000 | E5: 1 | F5: Bachelors | G5: Skilled Manual | H5: Yes | I5: 0 | J5: 0-1 Miles | K5: Europe | L5: 42 | M5: No | N5: {=_xlfn.IFS(tbl_Clean[[#This Row],[Age]]<=30,"25-30",tbl_Clean[[#This Row],[Age]]<=40,"31-40",tbl_Clean[[#This Row],[Age]]<=50,"41-50",tbl_Clean[[#This Row],[Age]]<=60,"51-60",TRUE,"61+")} -> 41-50 | O5: =_xlfn.XMATCH(tbl_Clean[[#This Row],[Age Band]],{"25-30","31-40","41-50","51-60","61+"}) -> 3 | P5: {=_xlfn.IFS(tbl_Clean[[#This Row],[Income]]<=30000,"$10k-30k",tbl_Clean[[#This Row],[Income]]<=60000,"$40k-60k",tbl_Clean[[#This Row],[Income]]<=90000,"$70k-90k",TRUE,"$100k+")} -> $40k-60k | Q5: =_xlfn.XMATCH(tbl_Clean[[#This Row],[Income Band]],{"$10k-30k","$40k-60k","$70k-90k","$100k+"}) -> 2 | R5: =IF(tbl_Clean[[#This Row],[Cars]]<=1,"0-1 Cars","2+ Cars") -> 0-1 Cars | S5: =_xlfn.XMATCH(tbl_Clean[[#This Row],[Commute Distance]],{"0-1 Miles","1-2 Miles","2-5 Miles","5-10 Miles","10+ Miles"}) -> 1 | T5: =_xlfn.XMATCH(tbl_Clean[[#This Row],[Education]],{"Partial High School","High School","Partial College","Bachelors","Graduate Degree"}) -> 4 | U5: =IF(tbl_Clean[[#This Row],[Purchased Bike]]="Yes",1,0) -> 0
A6: 24107 | B6: Married | C6: Male | D6: 30000 | E6: 3 | F6: Partial College | G6: Clerical | H6: Yes | I6: 1 | J6: 0-1 Miles | K6: Europe | L6: 43 | M6: No | N6: {=_xlfn.IFS(tbl_Clean[[#This Row],[Age]]<=30,"25-30",tbl_Clean[[#This Row],[Age]]<=40,"31-40",tbl_Clean[[#This Row],[Age]]<=50,"41-50",tbl_Clean[[#This Row],[Age]]<=60,"51-60",TRUE,"61+")} -> 41-50 | O6: =_xlfn.XMATCH(tbl_Clean[[#This Row],[Age Band]],{"25-30","31-40","41-50","51-60","61+"}) -> 3 | P6: {=_xlfn.IFS(tbl_Clean[[#This Row],[Income]]<=30000,"$10k-30k",tbl_Clean[[#This Row],[Income]]<=60000,"$40k-60k",tbl_Clean[[#This Row],[Income]]<=90000,"$70k-90k",TRUE,"$100k+")} -> $10k-30k | Q6: =_xlfn.XMATCH(tbl_Clean[[#This Row],[Income Band]],{"$10k-30k","$40k-60k","$70k-90k","$100k+"}) -> 1 | R6: =IF(tbl_Clean[[#This Row],[Cars]]<=1,"0-1 Cars","2+ Cars") -> 0-1 Cars | S6: =_xlfn.XMATCH(tbl_Clean[[#This Row],[Commute Distance]],{"0-1 Miles","1-2 Miles","2-5 Miles","5-10 Miles","10+ Miles"}) -> 1 | T6: =_xlfn.XMATCH(tbl_Clean[[#This Row],[Education]],{"Partial High School","High School","Partial College","Bachelors","Graduate Degree"}) -> 3 | U6: =IF(tbl_Clean[[#This Row],[Purchased Bike]]="Yes",1,0) -> 0
A7: 14177 | B7: Married | C7: Male | D7: 80000 | E7: 5 | F7: Partial College | G7: Professional | H7: No | I7: 2 | J7: 2-5 Miles | K7: Europe | L7: 60 | M7: No | N7: {=_xlfn.IFS(tbl_Clean[[#This Row],[Age]]<=30,"25-30",tbl_Clean[[#This Row],[Age]]<=40,"31-40",tbl_Clean[[#This Row],[Age]]<=50,"41-50",tbl_Clean[[#This Row],[Age]]<=60,"51-60",TRUE,"61+")} -> 51-60 | O7: =_xlfn.XMATCH(tbl_Clean[[#This Row],[Age Band]],{"25-30","31-40","41-50","51-60","61+"}) -> 4 | P7: {=_xlfn.IFS(tbl_Clean[[#This Row],[Income]]<=30000,"$10k-30k",tbl_Clean[[#This Row],[Income]]<=60000,"$40k-60k",tbl_Clean[[#This Row],[Income]]<=90000,"$70k-90k",TRUE,"$100k+")} -> $70k-90k | Q7: =_xlfn.XMATCH(tbl_Clean[[#This Row],[Income Band]],{"$10k-30k","$40k-60k","$70k-90k","$100k+"}) -> 3 | R7: =IF(tbl_Clean[[#This Row],[Cars]]<=1,"0-1 Cars","2+ Cars") -> 2+ Cars | S7: =_xlfn.XMATCH(tbl_Clean[[#This Row],[Commute Distance]],{"0-1 Miles","1-2 Miles","2-5 Miles","5-10 Miles","10+ Miles"}) -> 3 | T7: =_xlfn.XMATCH(tbl_Clean[[#This Row],[Education]],{"Partial High School","High School","Partial College","Bachelors","Graduate Degree"}) -> 3 | U7: =IF(tbl_Clean[[#This Row],[Purchased Bike]]="Yes",1,0) -> 0
A8: 24381 | B8: Single | C8: Male | D8: 70000 | E8: 0 | F8: Bachelors | G8: Professional | H8: Yes | I8: 1 | J8: 5-10 Miles | K8: Pacific | L8: 41 | M8: Yes | N8: {=_xlfn.IFS(tbl_Clean[[#This Row],[Age]]<=30,"25-30",tbl_Clean[[#This Row],[Age]]<=40,"31-40",tbl_Clean[[#This Row],[Age]]<=50,"41-50",tbl_Clean[[#This Row],[Age]]<=60,"51-60",TRUE,"61+")} -> 41-50 | O8: =_xlfn.XMATCH(tbl_Clean[[#This Row],[Age Band]],{"25-30","31-40","41-50","51-60","61+"}) -> 3 | P8: {=_xlfn.IFS(tbl_Clean[[#This Row],[Income]]<=30000,"$10k-30k",tbl_Clean[[#This Row],[Income]]<=60000,"$40k-60k",tbl_Clean[[#This Row],[Income]]<=90000,"$70k-90k",TRUE,"$100k+")} -> $70k-90k | Q8: =_xlfn.XMATCH(tbl_Clean[[#This Row],[Income Band]],{"$10k-30k","$40k-60k","$70k-90k","$100k+"}) -> 3 | R8: =IF(tbl_Clean[[#This Row],[Cars]]<=1,"0-1 Cars","2+ Cars") -> 0-1 Cars | S8: =_xlfn.XMATCH(tbl_Clean[[#This Row],[Commute Distance]],{"0-1 Miles","1-2 Miles","2-5 Miles","5-10 Miles","10+ Miles"}) -> 4 | T8: =_xlfn.XMATCH(tbl_Clean[[#This Row],[Education]],{"Partial High School","High School","Partial College","Bachelors","Graduate Degree"}) -> 4 | U8: =IF(tbl_Clean[[#This Row],[Purchased Bike]]="Yes",1,0) -> 1
A9: 25597 | B9: Single | C9: Male | D9: 30000 | E9: 0 | F9: Bachelors | G9: Clerical | H9: No | I9: 0 | J9: 0-1 Miles | K9: Europe | L9: 36 | M9: Yes | N9: {=_xlfn.IFS(tbl_Clean[[#This Row],[Age]]<=30,"25-30",tbl_Clean[[#This Row],[Age]]<=40,"31-40",tbl_Clean[[#This Row],[Age]]<=50,"41-50",tbl_Clean[[#This Row],[Age]]<=60,"51-60",TRUE,"61+")} -> 31-40 | O9: =_xlfn.XMATCH(tbl_Clean[[#This Row],[Age Band]],{"25-30","31-40","41-50","51-60","61+"}) -> 2 | P9: {=_xlfn.IFS(tbl_Clean[[#This Row],[Income]]<=30000,"$10k-30k",tbl_Clean[[#This Row],[Income]]<=60000,"$40k-60k",tbl_Clean[[#This Row],[Income]]<=90000,"$70k-90k",TRUE,"$100k+")} -> $10k-30k | Q9: =_xlfn.XMATCH(tbl_Clean[[#This Row],[Income Band]],{"$10k-30k","$40k-60k","$70k-90k","$100k+"}) -> 1 | R9: =IF(tbl_Clean[[#This Row],[Cars]]<=1,"0-1 Cars","2+ Cars") -> 0-1 Cars | S9: =_xlfn.XMATCH(tbl_Clean[[#This Row],[Commute Distance]],{"0-1 Miles","1-2 Miles","2-5 Miles","5-10 Miles","10+ Miles"}) -> 1 | T9: =_xlfn.XMATCH(tbl_Clean[[#This Row],[Education]],{"Partial High School","High School","Partial College","Bachelors","Graduate Degree"}) -> 4 | U9: =IF(tbl_Clean[[#This Row],[Purchased Bike]]="Yes",1,0) -> 1
A10: 13507 | B10: Married | C10: Female | D10: 10000 | E10: 2 | F10: Partial College | G10: Manual | H10: Yes | I10: 0 | J10: 1-2 Miles | K10: Europe | L10: 50 | M10: No | N10: {=_xlfn.IFS(tbl_Clean[[#This Row],[Age]]<=30,"25-30",tbl_Clean[[#This Row],[Age]]<=40,"31-40",tbl_Clean[[#This Row],[Age]]<=50,"41-50",tbl_Clean[[#This Row],[Age]]<=60,"51-60",TRUE,"61+")} -> 41-50 | O10: =_xlfn.XMATCH(tbl_Clean[[#This Row],[Age Band]],{"25-30","31-40","41-50","51-60","61+"}) -> 3 | P10: {=_xlfn.IFS(tbl_Clean[[#This Row],[Income]]<=30000,"$10k-30k",tbl_Clean[[#This Row],[Income]]<=60000,"$40k-60k",tbl_Clean[[#This Row],[Income]]<=90000,"$70k-90k",TRUE,"$100k+")} -> $10k-30k | Q10: =_xlfn.XMATCH(tbl_Clean[[#This Row],[Income Band]],{"$10k-30k","$40k-60k","$70k-90k","$100k+"}) -> 1 | R10: =IF(tbl_Clean[[#This Row],[Cars]]<=1,"0-1 Cars","2+ Cars") -> 0-1 Cars | S10: =_xlfn.XMATCH(tbl_Clean[[#This Row],[Commute Distance]],{"0-1 Miles","1-2 Miles","2-5 Miles","5-10 Miles","10+ Miles"}) -> 2 | T10: =_xlfn.XMATCH(tbl_Clean[[#This Row],[Education]],{"Partial High School","High School","Partial College","Bachelors","Graduate Degree"}) -> 3 | U10: =IF(tbl_Clean[[#This Row],[Purchased Bike]]="Yes",1,0) -> 0
A11: 27974 | B11: Single | C11: Male | D11: 160000 | E11: 2 | F11: High School | G11: Management | H11: Yes | I11: 4 | J11: 0-1 Miles | K11: Pacific | L11: 33 | M11: Yes | N11: {=_xlfn.IFS(tbl_Clean[[#This Row],[Age]]<=30,"25-30",tbl_Clean[[#This Row],[Age]]<=40,"31-40",tbl_Clean[[#This Row],[Age]]<=50,"41-50",tbl_Clean[[#This Row],[Age]]<=60,"51-60",TRUE,"61+")} -> 31-40 | O11: =_xlfn.XMATCH(tbl_Clean[[#This Row],[Age Band]],{"25-30","31-40","41-50","51-60","61+"}) -> 2 | P11: {=_xlfn.IFS(tbl_Clean[[#This Row],[Income]]<=30000,"$10k-30k",tbl_Clean[[#This Row],[Income]]<=60000,"$40k-60k",tbl_Clean[[#This Row],[Income]]<=90000,"$70k-90k",TRUE,"$100k+")} -> $100k+ | Q11: =_xlfn.XMATCH(tbl_Clean[[#This Row],[Income Band]],{"$10k-30k","$40k-60k","$70k-90k","$100k+"}) -> 4 | R11: =IF(tbl_Clean[[#This Row],[Cars]]<=1,"0-1 Cars","2+ Cars") -> 2+ Cars | S11: =_xlfn.XMATCH(tbl_Clean[[#This Row],[Commute Distance]],{"0-1 Miles","1-2 Miles","2-5 Miles","5-10 Miles","10+ Miles"}) -> 1 | T11: =_xlfn.XMATCH(tbl_Clean[[#This Row],[Education]],{"Partial High School","High School","Partial College","Bachelors","Graduate Degree"}) -> 2 | U11: =IF(tbl_Clean[[#This Row],[Purchased Bike]]="Yes",1,0) -> 1
A12: 19364 | B12: Married | C12: Male | D12: 40000 | E12: 1 | F12: Bachelors | G12: Skilled Manual | H12: Yes | I12: 0 | J12: 0-1 Miles | K12: Europe | L12: 43 | M12: Yes | N12: {=_xlfn.IFS(tbl_Clean[[#This Row],[Age]]<=30,"25-30",tbl_Clean[[#This Row],[Age]]<=40,"31-40",tbl_Clean[[#This Row],[Age]]<=50,"41-50",tbl_Clean[[#This Row],[Age]]<=60,"51-60",TRUE,"61+")} -> 41-50 | O12: =_xlfn.XMATCH(tbl_Clean[[#This Row],[Age Band]],{"25-30","31-40","41-50","51-60","61+"}) -> 3 | P12: {=_xlfn.IFS(tbl_Clean[[#This Row],[Income]]<=30000,"$10k-30k",tbl_Clean[[#This Row],[Income]]<=60000,"$40k-60k",tbl_Clean[[#This Row],[Income]]<=90000,"$70k-90k",TRUE,"$100k+")} -> $40k-60k | Q12: =_xlfn.XMATCH(tbl_Clean[[#This Row],[Income Band]],{"$10k-30k","$40k-60k","$70k-90k","$100k+"}) -> 2 | R12: =IF(tbl_Clean[[#This Row],[Cars]]<=1,"0-1 Cars","2+ Cars") -> 0-1 Cars | S12: =_xlfn.XMATCH(tbl_Clean[[#This Row],[Commute Distance]],{"0-1 Miles","1-2 Miles","2-5 Miles","5-10 Miles","10+ Miles"}) -> 1 | T12: =_xlfn.XMATCH(tbl_Clean[[#This Row],[Education]],{"Partial High School","High School","Partial College","Bachelors","Graduate Degree"}) -> 4 | U12: =IF(tbl_Clean[[#This Row],[Purchased Bike]]="Yes",1,0) -> 1
A13: 22155 | B13: Married | C13: Male | D13: 20000 | E13: 2 | F13: Partial High School | G13: Clerical | H13: Yes | I13: 2 | J13: 5-10 Miles | K13: Pacific | L13: 58 | M13: No | N13: {=_xlfn.IFS(tbl_Clean[[#This Row],[Age]]<=30,"25-30",tbl_Clean[[#This Row],[Age]]<=40,"31-40",tbl_Clean[[#This Row],[Age]]<=50,"41-50",tbl_Clean[[#This Row],[Age]]<=60,"51-60",TRUE,"61+")} -> 51-60 | O13: =_xlfn.XMATCH(tbl_Clean[[#This Row],[Age Band]],{"25-30","31-40","41-50","51-60","61+"}) -> 4 | P13: {=_xlfn.IFS(tbl_Clean[[#This Row],[Income]]<=30000,"$10k-30k",tbl_Clean[[#This Row],[Income]]<=60000,"$40k-60k",tbl_Clean[[#This Row],[Income]]<=90000,"$70k-90k",TRUE,"$100k+")} -> $10k-30k | Q13: =_xlfn.XMATCH(tbl_Clean[[#This Row],[Income Band]],{"$10k-30k","$40k-60k","$70k-90k","$100k+"}) -> 1 | R13: =IF(tbl_Clean[[#This Row],[Cars]]<=1,"0-1 Cars","2+ Cars") -> 2+ Cars | S13: =_xlfn.XMATCH(tbl_Clean[[#This Row],[Commute Distance]],{"0-1 Miles","1-2 Miles","2-5 Miles","5-10 Miles","10+ Miles"}) -> 4 | T13: =_xlfn.XMATCH(tbl_Clean[[#This Row],[Education]],{"Partial High School","High School","Partial College","Bachelors","Graduate Degree"}) -> 1 | U13: =IF(tbl_Clean[[#This Row],[Purchased Bike]]="Yes",1,0) -> 0
A14: 19280 | B14: Married | C14: Male | D14: 120000 | E14: 2 | F14: Partial College | G14: Manual | H14: Yes | I14: 1 | J14: 0-1 Miles | K14: Europe | L14: 40 | M14: Yes | N14: {=_xlfn.IFS(tbl_Clean[[#This Row],[Age]]<=30,"25-30",tbl_Clean[[#This Row],[Age]]<=40,"31-40",tbl_Clean[[#This Row],[Age]]<=50,"41-50",tbl_Clean[[#This Row],[Age]]<=60,"51-60",TRUE,"61+")} -> 31-40 | O14: =_xlfn.XMATCH(tbl_Clean[[#This Row],[Age Band]],{"25-30","31-40","41-50","51-60","61+"}) -> 2 | P14: {=_xlfn.IFS(tbl_Clean[[#This Row],[Income]]<=30000,"$10k-30k",tbl_Clean[[#This Row],[Income]]<=60000,"$40k-60k",tbl_Clean[[#This Row],[Income]]<=90000,"$70k-90k",TRUE,"$100k+")} -> $100k+ | Q14: =_xlfn.XMATCH(tbl_Clean[[#This Row],[Income Band]],{"$10k-30k","$40k-60k","$70k-90k","$100k+"}) -> 4 | R14: =IF(tbl_Clean[[#This Row],[Cars]]<=1,"0-1 Cars","2+ Cars") -> 0-1 Cars | S14: =_xlfn.XMATCH(tbl_Clean[[#This Row],[Commute Distance]],{"0-1 Miles","1-2 Miles","2-5 Miles","5-10 Miles","10+ Miles"}) -> 1 | T14: =_xlfn.XMATCH(tbl_Clean[[#This Row],[Education]],{"Partial High School","High School","Partial College","Bachelors","Graduate Degree"}) -> 3 | U14: =IF(tbl_Clean[[#This Row],[Purchased Bike]]="Yes",1,0) -> 1
A15: 22173 | B15: Married | C15: Female | D15: 30000 | E15: 3 | F15: High School | G15: Skilled Manual | H15: No | I15: 2 | J15: 1-2 Miles | K15: Pacific | L15: 54 | M15: Yes | N15: {=_xlfn.IFS(tbl_Clean[[#This Row],[Age]]<=30,"25-30",tbl_Clean[[#This Row],[Age]]<=40,"31-40",tbl_Clean[[#This Row],[Age]]<=50,"41-50",tbl_Clean[[#This Row],[Age]]<=60,"51-60",TRUE,"61+")} -> 51-60 | O15: =_xlfn.XMATCH(tbl_Clean[[#This Row],[Age Band]],{"25-30","31-40","41-50","51-60","61+"}) -> 4 | P15: {=_xlfn.IFS(tbl_Clean[[#This Row],[Income]]<=30000,"$10k-30k",tbl_Clean[[#This Row],[Income]]<=60000,"$40k-60k",tbl_Clean[[#This Row],[Income]]<=90000,"$70k-90k",TRUE,"$100k+")} -> $10k-30k | Q15: =_xlfn.XMATCH(tbl_Clean[[#This Row],[Income Band]],{"$10k-30k","$40k-60k","$70k-90k","$100k+"}) -> 1 | R15: =IF(tbl_Clean[[#This Row],[Cars]]<=1,"0-1 Cars","2+ Cars") -> 2+ Cars | S15: =_xlfn.XMATCH(tbl_Clean[[#This Row],[Commute Distance]],{"0-1 Miles","1-2 Miles","2-5 Miles","5-10 Miles","10+ Miles"}) -> 2 | T15: =_xlfn.XMATCH(tbl_Clean[[#This Row],[Education]],{"Partial High School","High School","Partial College","Bachelors","Graduate Degree"}) -> 2 | U15: =IF(tbl_Clean[[#This Row],[Purchased Bike]]="Yes",1,0) -> 1
A16: 12697 | B16: Single | C16: Female | D16: 90000 | E16: 0 | F16: Bachelors | G16: Professional | H16: No | I16: 4 | J16: 10+ Miles | K16: Pacific | L16: 36 | M16: No | N16: {=_xlfn.IFS(tbl_Clean[[#This Row],[Age]]<=30,"25-30",tbl_Clean[[#This Row],[Age]]<=40,"31-40",tbl_Clean[[#This Row],[Age]]<=50,"41-50",tbl_Clean[[#This Row],[Age]]<=60,"51-60",TRUE,"61+")} -> 31-40 | O16: =_xlfn.XMATCH(tbl_Clean[[#This Row],[Age Band]],{"25-30","31-40","41-50","51-60","61+"}) -> 2 | P16: {=_xlfn.IFS(tbl_Clean[[#This Row],[Income]]<=30000,"$10k-30k",tbl_Clean[[#This Row],[Income]]<=60000,"$40k-60k",tbl_Clean[[#This Row],[Income]]<=90000,"$70k-90k",TRUE,"$100k+")} -> $70k-90k | Q16: =_xlfn.XMATCH(tbl_Clean[[#This Row],[Income Band]],{"$10k-30k","$40k-60k","$70k-90k","$100k+"}) -> 3 | R16: =IF(tbl_Clean[[#This Row],[Cars]]<=1,"0-1 Cars","2+ Cars") -> 2+ Cars | S16: =_xlfn.XMATCH(tbl_Clean[[#This Row],[Commute Distance]],{"0-1 Miles","1-2 Miles","2-5 Miles","5-10 Miles","10+ Miles"}) -> 5 | T16: =_xlfn.XMATCH(tbl_Clean[[#This Row],[Education]],{"Partial High School","High School","Partial College","Bachelors","Graduate Degree"}) -> 4 | U16: =IF(tbl_Clean[[#This Row],[Purchased Bike]]="Yes",1,0) -> 0
... A1004: 12121 | B1004: Single | C1004: Male | D1004: 60000 | E1004: 3 | F1004: High School | G1004: Professional | H1004: Yes | I1004: 2 | J1004: 10+ Miles | K1004: North America | L1004: 53 | M1004: Yes | N1004: {=_xlfn.IFS(tbl_Clean[[#This Row],[Age]]<=30,"25-30",tbl_Clean[[#This Row],[Age]]<=40,"31-40",tbl_Clean[[#This Row],[Age]]<=50,"41-50",tbl_Clean[[#This Row],[Age]]<=60,"51-60",TRUE,"61+")} -> 51-60 | O1004: =_xlfn.XMATCH(tbl_Clean[[#This Row],[Age Band]],{"25-30","31-40","41-50","51-60","61+"}) -> 4 | P1004: {=_xlfn.IFS(tbl_Clean[[#This Row],[Income]]<=30000,"$10k-30k",tbl_Clean[[#This Row],[Income]]<=60000,"$40k-60k",tbl_Clean[[#This Row],[Income]]<=90000,"$70k-90k",TRUE,"$100k+")} -> $40k-60k | Q1004: =_xlfn.XMATCH(tbl_Clean[[#This Row],[Income Band]],{"$10k-30k","$40k-60k","$70k-90k","$100k+"}) -> 2 | R1004: =IF(tbl_Clean[[#This Row],[Cars]]<=1,"0-1 Cars","2+ Cars") -> 2+ Cars | S1004: =_xlfn.XMATCH(tbl_Clean[[#This Row],[Commute Distance]],{"0-1 Miles","1-2 Miles","2-5 Miles","5-10 Miles","10+ Miles"}) -> 5 | T1004: =_xlfn.XMATCH(tbl_Clean[[#This Row],[Education]],{"Partial High School","High School","Partial College","Bachelors","Graduate Degree"}) -> 2 | U1004: =IF(tbl_Clean[[#This Row],[Purchased Bike]]="Yes",1,0) -> 1

Sheet Segment_Analysis
A1: Segment analysis: purchase rate by customer attribute
A2: Purpose: live purchase rate, lift vs the overall average and buyer share for every segment of every factor, ranked by how strongly each factor separates buyers.
A4: Total customers | B4: =ROWS(tbl_Clean[]) -> 1000 | C4: Total buyers | D4: =SUM(tbl_Clean[Purchased Flag]) -> 481 | E4: Overall purchase rate | F4: =D4/B4 -> 0.481
A6: Observations
A7: {=_xlfn.LET(_xlpm.seg,_xlfn.ANCHORARRAY(A34),_xlpm.rt,_xlfn.ANCHORARRAY(D34),_xlpm.hi,MAX(_xlpm.rt),_xlpm.lo,MIN(_xlpm.rt),"Highest-converting age band: "&_xlfn.XLOOKUP(_xlpm.hi,_xlpm.rt,_xlpm.seg)&" at "&TEXT(_xlpm.hi,"0.0%")&" ("&TEXT(_xlpm.hi/Baseline_Rate,"0.00")&"x the average); lowest: "&_xlfn.XLOOKUP(_xlpm.lo,_xlpm.rt,_xlpm.seg)&" at "&TEXT(_xlpm.lo,"0.0%")&" ("&TEXT(_xlpm.lo/Baseline_Rate,"0.00")&"x).")} -> Highest-converting age band: 31-40 at 61.1% (1.27x the average); lowest: 61+ at 30.0% (0.62x).
A8: {=_xlfn.LET(_xlpm.seg,_xlfn.ANCHORARRAY(A13),_xlpm.rt,_xlfn.ANCHORARRAY(D13),_xlpm.hi,MAX(_xlpm.rt),_xlpm.lo,MIN(_xlpm.rt),"Highest-converting car ownership group: "&_xlfn.XLOOKUP(_xlpm.hi,_xlpm.rt,_xlpm.seg)&" at "&TEXT(_xlpm.hi,"0.0%")&" ("&TEXT(_xlpm.hi/Baseline_Rate,"0.00")&"x the average); lowest: "&_xlfn.XLOOKUP(_xlpm.lo,_xlpm.rt,_xlpm.seg)&" at "&TEXT(_xlpm.lo,"0.0%")&" ("&TEXT(_xlpm.lo/Baseline_Rate,"0.00")&"x).")} -> Highest-converting car ownership group: 0-1 Cars at 58.9% (1.23x the average); lowest: 2+ Cars at 36.6% (0.76x).
A9: {=_xlfn.LET(_xlpm.seg,_xlfn.ANCHORARRAY(A26),_xlpm.rt,_xlfn.ANCHORARRAY(D26),_xlpm.hi,MAX(_xlpm.rt),_xlpm.lo,MIN(_xlpm.rt),"Highest-converting commute distance: "&_xlfn.XLOOKUP(_xlpm.hi,_xlpm.rt,_xlpm.seg)&" at "&TEXT(_xlpm.hi,"0.0%")&" ("&TEXT(_xlpm.hi/Baseline_Rate,"0.00")&"x the average); lowest: "&_xlfn.XLOOKUP(_xlpm.lo,_xlpm.rt,_xlpm.seg)&" at "&TEXT(_xlpm.lo,"0.0%")&" ("&TEXT(_xlpm.lo/Baseline_Rate,"0.00")&"x).")} -> Highest-converting commute distance: 2-5 Miles at 58.6% (1.22x the average); lowest: 10+ Miles at 29.7% (0.62x).
A11: Car Ownership | I11: Factor ranking (sorted by spread, highest first)
A12: Segment | B12: Customers | C12: Buyers | D12: Purchase Rate | E12: Lift vs Avg | F12: Share of All Buyers | G12: Sample flag | I12: Factor | J12: Highest segment | K12: Highest rate | L12: Lowest segment | M12: Lowest rate | N12: Spread (pp)
A13: {=_xlfn.LET(_xlpm.s,_xlfn.UNIQUE(tbl_Clean[Car Ownership]),_xlfn.SORTBY(_xlpm.s,COUNTIFS(tbl_Clean[Car Ownership],_xlpm.s,tbl_Clean[Purchased Flag],1)/COUNTIFS(tbl_Clean[Car Ownership],_xlpm.s),-1))} -> 0-1 Cars | B13: {=COUNTIFS(tbl_Clean[Car Ownership],_xlfn.ANCHORARRAY(A13))} -> 514 | C13: {=COUNTIFS(tbl_Clean[Car Ownership],_xlfn.ANCHORARRAY(A13),tbl_Clean[Purchased Flag],1)} -> 303 | D13: {=_xlfn.ANCHORARRAY(C13)/_xlfn.ANCHORARRAY(B13)} -> 0.58949416 | E13: {=_xlfn.ANCHORARRAY(D13)/Baseline_Rate} -> 1.2255596 | F13: {=_xlfn.ANCHORARRAY(C13)/Total_Buyers} -> 0.62993763 | G13: {=IF(_xlfn.ANCHORARRAY(B13)<100,"Small sample","")} | I13: {=_xlfn.SORTBY(I29:N40,N29:N40,-1)} -> Children | J13: 1 | K13: 0.5739645 | L13: 5 | M13: 0.22222222 | N13: 35.174227
A14: 2+ Cars | B14: 486 | C14: 178 | D14: 0.36625514 | E14: 0.76144521 | F14: 0.37006237 | I14: Age Band | J14: 31-40 | K14: 0.61075949 | L14: 61+ | M14: 0.3 | N14: 31.075949
I15: Education | J15: Bachelors | K15: 0.55228758 | L15: Partial High School | M15: 0.26315789 | N15: 28.912969
A16: Cars | I16: Commute Distance | J16: 2-5 Miles | K16: 0.58641975 | L16: 10+ Miles | M16: 0.2972973 | N16: 28.912246
A17: Segment | B17: Customers | C17: Buyers | D17: Purchase Rate | E17: Lift vs Avg | F17: Share of All Buyers | G17: Sample flag | I17: Cars | J17: 0 | K17: 0.61133603 | L17: 4 | M17: 0.3559322 | N17: 25.540383
A18: {=_xlfn._xlws.SORT(_xlfn.UNIQUE(tbl_Clean[Cars]))} -> 0 | B18: {=COUNTIFS(tbl_Clean[Cars],_xlfn.ANCHORARRAY(A18))} -> 247 | C18: {=COUNTIFS(tbl_Clean[Cars],_xlfn.ANCHORARRAY(A18),tbl_Clean[Purchased Flag],1)} -> 151 | D18: {=_xlfn.ANCHORARRAY(C18)/_xlfn.ANCHORARRAY(B18)} -> 0.61133603 | E18: {=_xlfn.ANCHORARRAY(D18)/Baseline_Rate} -> 1.2709689 | F18: {=_xlfn.ANCHORARRAY(C18)/Total_Buyers} -> 0.31392931 | G18: {=IF(_xlfn.ANCHORARRAY(B18)<100,"Small sample","")} | I18: Car Ownership | J18: 0-1 Cars | K18: 0.58949416 | L18: 2+ Cars | M18: 0.36625514 | N18: 22.323902
A19: 1 | B19: 267 | C19: 152 | D19: 0.56928839 | E19: 1.1835517 | F19: 0.31600832 | I19: Region | J19: Pacific | K19: 0.58854167 | L19: North America | M19: 0.43307087 | N19: 15.54708
A20: 2 | B20: 342 | C20: 124 | D20: 0.3625731 | E20: 0.75379023 | F20: 0.25779626 | I20: Income Band | J20: $40k-60k | K20: 0.53203343 | L20: $10k-30k | M20: 0.40070922 | N20: 13.132421
A21: 3 | B21: 85 | C21: 33 | D21: 0.38823529 | E21: 0.80714198 | F21: 0.068607069 | G21: Small sample | I21: Occupation | J21: Professional | K21: 0.54347826 | L21: Management | M21: 0.42196532 | N21: 12.151294
A22: 4 | B22: 59 | C22: 21 | D22: 0.3559322 | E22: 0.73998379 | F22: 0.043659044 | G22: Small sample | I22: Marital Status | J22: Single | K22: 0.54112554 | L22: Married | M22: 0.42936803 | N22: 11.175751
I23: Home Owner | J23: No | K23: 0.49211356 | L23: Yes | M23: 0.47584187 | N23: 1.6271691
A24: Commute Distance | I24: Gender | J24: Female | K24: 0.48875256 | L24: Male | M24: 0.47358121 | N24: 1.5171343
A25: Segment | B25: Customers | C25: Buyers | D25: Purchase Rate | E25: Lift vs Avg | F25: Share of All Buyers | G25: Sample flag
A26: {=_xlfn.LET(_xlpm.u,_xlfn.UNIQUE(_xlfn.HSTACK(tbl_Clean[Commute Distance],tbl_Clean[Commute Sort])),_xlfn.TAKE(_xlfn._xlws.SORT(_xlpm.u,2),,1))} -> 0-1 Miles | B26: {=COUNTIFS(tbl_Clean[Commute Distance],_xlfn.ANCHORARRAY(A26))} -> 366 | C26: {=COUNTIFS(tbl_Clean[Commute Distance],_xlfn.ANCHORARRAY(A26),tbl_Clean[Purchased Flag],1)} -> 200 | D26: {=_xlfn.ANCHORARRAY(C26)/_xlfn.ANCHORARRAY(B26)} -> 0.54644809 | E26: {=_xlfn.ANCHORARRAY(D26)/Baseline_Rate} -> 1.1360667 | F26: {=_xlfn.ANCHORARRAY(C26)/Total_Buyers} -> 0.41580042 | G26: {=IF(_xlfn.ANCHORARRAY(B26)<100,"Small sample","")}
A27: 1-2 Miles | B27: 169 | C27: 77 | D27: 0.4556213 | E27: 0.94723763 | F27: 0.16008316 | I27: Ranking workings (unsorted; feeds the factor ranking above)
A28: 2-5 Miles | B28: 162 | C28: 95 | D28: 0.58641975 | E28: 1.2191679 | F28: 0.1975052 | I28: Factor | J28: Highest segment | K28: Highest rate | L28: Lowest segment | M28: Lowest rate | N28: Spread (pp)
A29: 5-10 Miles | B29: 192 | C29: 76 | D29: 0.39583333 | E29: 0.82293832 | F29: 0.15800416 | I29: Car Ownership | J29: {=_xlfn.XLOOKUP(K29,_xlfn.ANCHORARRAY(D13),_xlfn.ANCHORARRAY(A13))} -> 0-1 Cars | K29: =MAX(_xlfn.ANCHORARRAY(D13)) -> 0.58949416 | L29: {=_xlfn.XLOOKUP(M29,_xlfn.ANCHORARRAY(D13),_xlfn.ANCHORARRAY(A13))} -> 2+ Cars | M29: =MIN(_xlfn.ANCHORARRAY(D13)) -> 0.36625514 | N29: =(K29-M29)*100 -> 22.323902
A30: 10+ Miles | B30: 111 | C30: 33 | D30: 0.2972973 | E30: 0.6180817 | F30: 0.068607069 | I30: Cars | J30: {=_xlfn.XLOOKUP(K30,_xlfn.ANCHORARRAY(D18),_xlfn.ANCHORARRAY(A18))} -> 0 | K30: =MAX(_xlfn.ANCHORARRAY(D18)) -> 0.61133603 | L30: {=_xlfn.XLOOKUP(M30,_xlfn.ANCHORARRAY(D18),_xlfn.ANCHORARRAY(A18))} -> 4 | M30: =MIN(_xlfn.ANCHORARRAY(D18)) -> 0.3559322 | N30: =(K30-M30)*100 -> 25.540383
I31: Commute Distance | J31: {=_xlfn.XLOOKUP(K31,_xlfn.ANCHORARRAY(D26),_xlfn.ANCHORARRAY(A26))} -> 2-5 Miles | K31: =MAX(_xlfn.ANCHORARRAY(D26)) -> 0.58641975 | L31: {=_xlfn.XLOOKUP(M31,_xlfn.ANCHORARRAY(D26),_xlfn.ANCHORARRAY(A26))} -> 10+ Miles | M31: =MIN(_xlfn.ANCHORARRAY(D26)) -> 0.2972973 | N31: =(K31-M31)*100 -> 28.912246
A32: Age Band | I32: Age Band | J32: {=_xlfn.XLOOKUP(K32,_xlfn.ANCHORARRAY(D34),_xlfn.ANCHORARRAY(A34))} -> 31-40 | K32: =MAX(_xlfn.ANCHORARRAY(D34)) -> 0.61075949 | L32: {=_xlfn.XLOOKUP(M32,_xlfn.ANCHORARRAY(D34),_xlfn.ANCHORARRAY(A34))} -> 61+ | M32: =MIN(_xlfn.ANCHORARRAY(D34)) -> 0.3 | N32: =(K32-M32)*100 -> 31.075949
A33: Segment | B33: Customers | C33: Buyers | D33: Purchase Rate | E33: Lift vs Avg | F33: Share of All Buyers | G33: Sample flag | I33: Children | J33: {=_xlfn.XLOOKUP(K33,_xlfn.ANCHORARRAY(D42),_xlfn.ANCHORARRAY(A42))} -> 1 | K33: =MAX(_xlfn.ANCHORARRAY(D42)) -> 0.5739645 | L33: {=_xlfn.XLOOKUP(M33,_xlfn.ANCHORARRAY(D42),_xlfn.ANCHORARRAY(A42))} -> 5 | M33: =MIN(_xlfn.ANCHORARRAY(D42)) -> 0.22222222 | N33: =(K33-M33)*100 -> 35.174227
A34: {=_xlfn.LET(_xlpm.u,_xlfn.UNIQUE(_xlfn.HSTACK(tbl_Clean[Age Band],tbl_Clean[Age Band Sort])),_xlfn.TAKE(_xlfn._xlws.SORT(_xlpm.u,2),,1))} -> 25-30 | B34: {=COUNTIFS(tbl_Clean[Age Band],_xlfn.ANCHORARRAY(A34))} -> 110 | C34: {=COUNTIFS(tbl_Clean[Age Band],_xlfn.ANCHORARRAY(A34),tbl_Clean[Purchased Flag],1)} -> 39 | D34: {=_xlfn.ANCHORARRAY(C34)/_xlfn.ANCHORARRAY(B34)} -> 0.35454545 | E34: {=_xlfn.ANCHORARRAY(D34)/Baseline_Rate} -> 0.73710074 | F34: {=_xlfn.ANCHORARRAY(C34)/Total_Buyers} -> 0.081081081 | G34: {=IF(_xlfn.ANCHORARRAY(B34)<100,"Small sample","")} | I34: Education | J34: {=_xlfn.XLOOKUP(K34,_xlfn.ANCHORARRAY(D51),_xlfn.ANCHORARRAY(A51))} -> Bachelors | K34: =MAX(_xlfn.ANCHORARRAY(D51)) -> 0.55228758 | L34: {=_xlfn.XLOOKUP(M34,_xlfn.ANCHORARRAY(D51),_xlfn.ANCHORARRAY(A51))} -> Partial High School | M34: =MIN(_xlfn.ANCHORARRAY(D51)) -> 0.26315789 | N34: =(K34-M34)*100 -> 28.912969
A35: 31-40 | B35: 316 | C35: 193 | D35: 0.61075949 | E35: 1.2697703 | F35: 0.4012474 | I35: Region | J35: {=_xlfn.XLOOKUP(K35,_xlfn.ANCHORARRAY(D59),_xlfn.ANCHORARRAY(A59))} -> Pacific | K35: =MAX(_xlfn.ANCHORARRAY(D59)) -> 0.58854167 | L35: {=_xlfn.XLOOKUP(M35,_xlfn.ANCHORARRAY(D59),_xlfn.ANCHORARRAY(A59))} -> North America | M35: =MIN(_xlfn.ANCHORARRAY(D59)) -> 0.43307087 | N35: =(K35-M35)*100 -> 15.54708
A36: 41-50 | B36: 298 | C36: 139 | D36: 0.46644295 | E36: 0.96973587 | F36: 0.28898129 | I36: Marital Status | J36: {=_xlfn.XLOOKUP(K36,_xlfn.ANCHORARRAY(D65),_xlfn.ANCHORARRAY(A65))} -> Single | K36: =MAX(_xlfn.ANCHORARRAY(D65)) -> 0.54112554 | L36: {=_xlfn.XLOOKUP(M36,_xlfn.ANCHORARRAY(D65),_xlfn.ANCHORARRAY(A65))} -> Married | M36: =MIN(_xlfn.ANCHORARRAY(D65)) -> 0.42936803 | N36: =(K36-M36)*100 -> 11.175751
A37: 51-60 | B37: 176 | C37: 80 | D37: 0.45454545 | E37: 0.94500095 | F37: 0.16632017 | I37: Income Band | J37: {=_xlfn.XLOOKUP(K37,_xlfn.ANCHORARRAY(D70),_xlfn.ANCHORARRAY(A70))} -> $40k-60k | K37: =MAX(_xlfn.ANCHORARRAY(D70)) -> 0.53203343 | L37: {=_xlfn.XLOOKUP(M37,_xlfn.ANCHORARRAY(D70),_xlfn.ANCHORARRAY(A70))} -> $10k-30k | M37: =MIN(_xlfn.ANCHORARRAY(D70)) -> 0.40070922 | N37: =(K37-M37)*100 -> 13.132421
A38: 61+ | B38: 100 | C38: 30 | D38: 0.3 | E38: 0.62370062 | F38: 0.062370062 | I38: Occupation | J38: {=_xlfn.XLOOKUP(K38,_xlfn.ANCHORARRAY(D77),_xlfn.ANCHORARRAY(A77))} -> Professional | K38: =MAX(_xlfn.ANCHORARRAY(D77)) -> 0.54347826 | L38: {=_xlfn.XLOOKUP(M38,_xlfn.ANCHORARRAY(D77),_xlfn.ANCHORARRAY(A77))} -> Management | M38: =MIN(_xlfn.ANCHORARRAY(D77)) -> 0.42196532 | N38: =(K38-M38)*100 -> 12.151294
I39: Home Owner | J39: {=_xlfn.XLOOKUP(K39,_xlfn.ANCHORARRAY(D85),_xlfn.ANCHORARRAY(A85))} -> No | K39: =MAX(_xlfn.ANCHORARRAY(D85)) -> 0.49211356 | L39: {=_xlfn.XLOOKUP(M39,_xlfn.ANCHORARRAY(D85),_xlfn.ANCHORARRAY(A85))} -> Yes | M39: =MIN(_xlfn.ANCHORARRAY(D85)) -> 0.47584187 | N39: =(K39-M39)*100 -> 1.6271691
A40: Children | I40: Gender | J40: {=_xlfn.XLOOKUP(K40,_xlfn.ANCHORARRAY(D90),_xlfn.ANCHORARRAY(A90))} -> Female | K40: =MAX(_xlfn.ANCHORARRAY(D90)) -> 0.48875256 | L40: {=_xlfn.XLOOKUP(M40,_xlfn.ANCHORARRAY(D90),_xlfn.ANCHORARRAY(A90))} -> Male | M40: =MIN(_xlfn.ANCHORARRAY(D90)) -> 0.47358121 | N40: =(K40-M40)*100 -> 1.5171343
A41: Segment | B41: Customers | C41: Buyers | D41: Purchase Rate | E41: Lift vs Avg | F41: Share of All Buyers | G41: Sample flag
A42: {=_xlfn._xlws.SORT(_xlfn.UNIQUE(tbl_Clean[Children]))} -> 0 | B42: {=COUNTIFS(tbl_Clean[Children],_xlfn.ANCHORARRAY(A42))} -> 281 | C42: {=COUNTIFS(tbl_Clean[Children],_xlfn.ANCHORARRAY(A42),tbl_Clean[Purchased Flag],1)} -> 142 | D42: {=_xlfn.ANCHORARRAY(C42)/_xlfn.ANCHORARRAY(B42)} -> 0.50533808 | E42: {=_xlfn.ANCHORARRAY(D42)/Baseline_Rate} -> 1.0505989 | F42: {=_xlfn.ANCHORARRAY(C42)/Total_Buyers} -> 0.2952183 | G42: {=IF(_xlfn.ANCHORARRAY(B42)<100,"Small sample","")}
A43: 1 | B43: 169 | C43: 97 | D43: 0.5739645 | E43: 1.1932734 | F43: 0.2016632
A44: 2 | B44: 209 | C44: 97 | D44: 0.46411483 | E44: 0.9648957 | F44: 0.2016632
A45: 3 | B45: 134 | C45: 73 | D45: 0.54477612 | E45: 1.1325907 | F45: 0.15176715
A46: 4 | B46: 126 | C46: 54 | D46: 0.42857143 | E46: 0.89100089 | F46: 0.11226611
A47: 5 | B47: 81 | C47: 18 | D47: 0.22222222 | E47: 0.46200046 | F47: 0.037422037 | G47: Small sample
A49: Education
A50: Segment | B50: Customers | C50: Buyers | D50: Purchase Rate | E50: Lift vs Avg | F50: Share of All Buyers | G50: Sample flag
A51: {=_xlfn.LET(_xlpm.u,_xlfn.UNIQUE(_xlfn.HSTACK(tbl_Clean[Education],tbl_Clean[Education Sort])),_xlfn.TAKE(_xlfn._xlws.SORT(_xlpm.u,2),,1))} -> Partial High School | B51: {=COUNTIFS(tbl_Clean[Education],_xlfn.ANCHORARRAY(A51))} -> 76 | C51: {=COUNTIFS(tbl_Clean[Education],_xlfn.ANCHORARRAY(A51),tbl_Clean[Purchased Flag],1)} -> 20 | D51: {=_xlfn.ANCHORARRAY(C51)/_xlfn.ANCHORARRAY(B51)} -> 0.26315789 | E51: {=_xlfn.ANCHORARRAY(D51)/Baseline_Rate} -> 0.54710581 | F51: {=_xlfn.ANCHORARRAY(C51)/Total_Buyers} -> 0.041580042 | G51: {=IF(_xlfn.ANCHORARRAY(B51)<100,"Small sample","")} -> Small sample
A52: High School | B52: 179 | C52: 79 | D52: 0.44134078 | E52: 0.9175484 | F52: 0.16424116
A53: Partial College | B53: 265 | C53: 119 | D53: 0.4490566 | E53: 0.93358961 | F53: 0.24740125
A54: Bachelors | B54: 306 | C54: 169 | D54: 0.55228758 | E54: 1.148207 | F54: 0.35135135
A55: Graduate Degree | B55: 174 | C55: 94 | D55: 0.54022989 | E55: 1.1231391 | F55: 0.1954262
A57: Region
A58: Segment | B58: Customers | C58: Buyers | D58: Purchase Rate | E58: Lift vs Avg | F58: Share of All Buyers | G58: Sample flag
A59: {=_xlfn.LET(_xlpm.s,_xlfn.UNIQUE(tbl_Clean[Region]),_xlfn.SORTBY(_xlpm.s,COUNTIFS(tbl_Clean[Region],_xlpm.s,tbl_Clean[Purchased Flag],1)/COUNTIFS(tbl_Clean[Region],_xlpm.s),-1))} -> Pacific | B59: {=COUNTIFS(tbl_Clean[Region],_xlfn.ANCHORARRAY(A59))} -> 192 | C59: {=COUNTIFS(tbl_Clean[Region],_xlfn.ANCHORARRAY(A59),tbl_Clean[Purchased Flag],1)} -> 113 | D59: {=_xlfn.ANCHORARRAY(C59)/_xlfn.ANCHORARRAY(B59)} -> 0.58854167 | E59: {=_xlfn.ANCHORARRAY(D59)/Baseline_Rate} -> 1.2235793 | F59: {=_xlfn.ANCHORARRAY(C59)/Total_Buyers} -> 0.23492723 | G59: {=IF(_xlfn.ANCHORARRAY(B59)<100,"Small sample","")}
A60: Europe | B60: 300 | C60: 148 | D60: 0.49333333 | E60: 1.025641 | F60: 0.30769231
A61: North America | B61: 508 | C61: 220 | D61: 0.43307087 | E61: 0.90035523 | F61: 0.45738046
A63: Marital Status
A64: Segment | B64: Customers | C64: Buyers | D64: Purchase Rate | E64: Lift vs Avg | F64: Share of All Buyers | G64: Sample flag
A65: {=_xlfn.LET(_xlpm.s,_xlfn.UNIQUE(tbl_Clean[Marital Status]),_xlfn.SORTBY(_xlpm.s,COUNTIFS(tbl_Clean[Marital Status],_xlpm.s,tbl_Clean[Purchased Flag],1)/COUNTIFS(tbl_Clean[Marital Status],_xlpm.s),-1))} -> Single | B65: {=COUNTIFS(tbl_Clean[Marital Status],_xlfn.ANCHORARRAY(A65))} -> 462 | C65: {=COUNTIFS(tbl_Clean[Marital Status],_xlfn.ANCHORARRAY(A65),tbl_Clean[Purchased Flag],1)} -> 250 | D65: {=_xlfn.ANCHORARRAY(C65)/_xlfn.ANCHORARRAY(B65)} -> 0.54112554 | E65: {=_xlfn.ANCHORARRAY(D65)/Baseline_Rate} -> 1.1250011 | F65: {=_xlfn.ANCHORARRAY(C65)/Total_Buyers} -> 0.51975052 | G65: {=IF(_xlfn.ANCHORARRAY(B65)<100,"Small sample","")}
A66: Married | B66: 538 | C66: 231 | D66: 0.42936803 | E66: 0.89265703 | F66: 0.48024948
A68: Income Band
A69: Segment | B69: Customers | C69: Buyers | D69: Purchase Rate | E69: Lift vs Avg | F69: Share of All Buyers | G69: Sample flag
A70: {=_xlfn.LET(_xlpm.u,_xlfn.UNIQUE(_xlfn.HSTACK(tbl_Clean[Income Band],tbl_Clean[Income Band Sort])),_xlfn.TAKE(_xlfn._xlws.SORT(_xlpm.u,2),,1))} -> $10k-30k | B70: {=COUNTIFS(tbl_Clean[Income Band],_xlfn.ANCHORARRAY(A70))} -> 282 | C70: {=COUNTIFS(tbl_Clean[Income Band],_xlfn.ANCHORARRAY(A70),tbl_Clean[Purchased Flag],1)} -> 113 | D70: {=_xlfn.ANCHORARRAY(C70)/_xlfn.ANCHORARRAY(B70)} -> 0.40070922 | E70: {=_xlfn.ANCHORARRAY(D70)/Baseline_Rate} -> 0.8330753 | F70: {=_xlfn.ANCHORARRAY(C70)/Total_Buyers} -> 0.23492723 | G70: {=IF(_xlfn.ANCHORARRAY(B70)<100,"Small sample","")}
A71: $40k-60k | B71: 359 | C71: 191 | D71: 0.53203343 | E71: 1.1060986 | F71: 0.3970894
A72: $70k-90k | B72: 254 | C72: 126 | D72: 0.49606299 | E72: 1.031316 | F72: 0.26195426
A73: $100k+ | B73: 105 | C73: 51 | D73: 0.48571429 | E73: 1.009801 | F73: 0.10602911
A75: Occupation
A76: Segment | B76: Customers | C76: Buyers | D76: Purchase Rate | E76: Lift vs Avg | F76: Share of All Buyers | G76: Sample flag
A77: {=_xlfn.LET(_xlpm.s,_xlfn.UNIQUE(tbl_Clean[Occupation]),_xlfn.SORTBY(_xlpm.s,COUNTIFS(tbl_Clean[Occupation],_xlpm.s,tbl_Clean[Purchased Flag],1)/COUNTIFS(tbl_Clean[Occupation],_xlpm.s),-1))} -> Professional | B77: {=COUNTIFS(tbl_Clean[Occupation],_xlfn.ANCHORARRAY(A77))} -> 276 | C77: {=COUNTIFS(tbl_Clean[Occupation],_xlfn.ANCHORARRAY(A77),tbl_Clean[Purchased Flag],1)} -> 150 | D77: {=_xlfn.ANCHORARRAY(C77)/_xlfn.ANCHORARRAY(B77)} -> 0.54347826 | E77: {=_xlfn.ANCHORARRAY(D77)/Baseline_Rate} -> 1.1298924 | F77: {=_xlfn.ANCHORARRAY(C77)/Total_Buyers} -> 0.31185031 | G77: {=IF(_xlfn.ANCHORARRAY(B77)<100,"Small sample","")}
A78: Clerical | B78: 177 | C78: 88 | D78: 0.49717514 | E78: 1.0336282 | F78: 0.18295218
A79: Manual | B79: 119 | C79: 55 | D79: 0.46218487 | E79: 0.96088331 | F79: 0.11434511
A80: Skilled Manual | B80: 255 | C80: 115 | D80: 0.45098039 | E80: 0.93758917 | F80: 0.23908524
A81: Management | B81: 173 | C81: 73 | D81: 0.42196532 | E81: 0.87726677 | F81: 0.15176715
A83: Home Owner
A84: Segment | B84: Customers | C84: Buyers | D84: Purchase Rate | E84: Lift vs Avg | F84: Share of All Buyers | G84: Sample flag
A85: {=_xlfn.LET(_xlpm.s,_xlfn.UNIQUE(tbl_Clean[Home Owner]),_xlfn.SORTBY(_xlpm.s,COUNTIFS(tbl_Clean[Home Owner],_xlpm.s,tbl_Clean[Purchased Flag],1)/COUNTIFS(tbl_Clean[Home Owner],_xlpm.s),-1))} -> No | B85: {=COUNTIFS(tbl_Clean[Home Owner],_xlfn.ANCHORARRAY(A85))} -> 317 | C85: {=COUNTIFS(tbl_Clean[Home Owner],_xlfn.ANCHORARRAY(A85),tbl_Clean[Purchased Flag],1)} -> 156 | D85: {=_xlfn.ANCHORARRAY(C85)/_xlfn.ANCHORARRAY(B85)} -> 0.49211356 | E85: {=_xlfn.ANCHORARRAY(D85)/Baseline_Rate} -> 1.0231051 | F85: {=_xlfn.ANCHORARRAY(C85)/Total_Buyers} -> 0.32432432 | G85: {=IF(_xlfn.ANCHORARRAY(B85)<100,"Small sample","")}
A86: Yes | B86: 683 | C86: 325 | D86: 0.47584187 | E86: 0.98927625 | F86: 0.67567568
A88: Gender
A89: Segment | B89: Customers | C89: Buyers | D89: Purchase Rate | E89: Lift vs Avg | F89: Share of All Buyers | G89: Sample flag
A90: {=_xlfn.LET(_xlpm.s,_xlfn.UNIQUE(tbl_Clean[Gender]),_xlfn.SORTBY(_xlpm.s,COUNTIFS(tbl_Clean[Gender],_xlpm.s,tbl_Clean[Purchased Flag],1)/COUNTIFS(tbl_Clean[Gender],_xlpm.s),-1))} -> Female | B90: {=COUNTIFS(tbl_Clean[Gender],_xlfn.ANCHORARRAY(A90))} -> 489 | C90: {=COUNTIFS(tbl_Clean[Gender],_xlfn.ANCHORARRAY(A90),tbl_Clean[Purchased Flag],1)} -> 239 | D90: {=_xlfn.ANCHORARRAY(C90)/_xlfn.ANCHORARRAY(B90)} -> 0.48875256 | E90: {=_xlfn.ANCHORARRAY(D90)/Baseline_Rate} -> 1.0161176 | F90: {=_xlfn.ANCHORARRAY(C90)/Total_Buyers} -> 0.4968815 | G90: {=IF(_xlfn.ANCHORARRAY(B90)<100,"Small sample","")}
A91: Male | B91: 511 | C91: 242 | D91: 0.47358121 | E91: 0.98457633 | F91: 0.5031185

Sheet Significance_Tests
A1: Significance tests: which factors really matter?
A2: Purpose: chi-square tests of independence for each factor vs bike purchase, with effect size (Cramér's V), to separate real drivers from chance.
A4: How to read this
A5: • Chi-square test: compares actual buyers per segment with the number expected if the factor had no effect.
A6: • p-value < 0.05 = the difference is statistically significant (unlikely to be chance).
A7: • Cramér's V = strength of the relationship: <0.10 Negligible, 0.10–0.19 Small, 0.20–0.29 Moderate, ≥0.30 Strong.
A9: Results summary (sorted by Cramér's V, strongest first)
A10: Factor | B10: Chi-square | C10: df | D10: p-value | E10: Cramér's V | F10: Strength | G10: Significant? | H10: Valid (min expected ≥5) | I10: Plain-English Verdict
A11: {=INDEX(_xlfn.SORTBY(tbl_SigWorkings[Factor],tbl_SigWorkings[Cramér''s V],-1),ROW()-ROW(tbl_Significance[#Headers]))} -> Cars | B11: =_xlfn.XLOOKUP(tbl_Significance[[#This Row],[Factor]],tbl_SigWorkings[Factor],tbl_SigWorkings[Chi-square]) -> 50.985549 | C11: =_xlfn.XLOOKUP(tbl_Significance[[#This Row],[Factor]],tbl_SigWorkings[Factor],tbl_SigWorkings[df]) -> 4 | D11: =_xlfn.XLOOKUP(tbl_Significance[[#This Row],[Factor]],tbl_SigWorkings[Factor],tbl_SigWorkings[p-value]) -> 2.2477924e-10 | E11: =_xlfn.XLOOKUP(tbl_Significance[[#This Row],[Factor]],tbl_SigWorkings[Factor],tbl_SigWorkings[Cramér''s V]) -> 0.2257998 | F11: {=_xlfn.IFS(tbl_Significance[[#This Row],[Cramér''s V]]<0.1,"Negligible",tbl_Significance[[#This Row],[Cramér''s V]]<0.2,"Small",tbl_Significance[[#This Row],[Cramér''s V]]<0.3,"Moderate",TRUE,"Strong")} -> Moderate | G11: =IF(tbl_Significance[[#This Row],[p-value]]<0.05,"Yes","No") -> Yes | H11: =IF(_xlfn.XLOOKUP(tbl_Significance[[#This Row],[Factor]],tbl_SigWorkings[Factor],tbl_SigWorkings[Min Expected])>=5,"Yes","No") -> Yes | I11: =IF(tbl_Significance[[#This Row],[Significant?]]="Yes","Matters – "&tbl_Significance[[#This Row],[Strength]]&" effect","No evidence it matters")&IF(tbl_Significance[[#This Row],[Valid (min expected ≥5)]]="No"," (caution: small expected counts)","") -> Matters – Moderate effect
A12: {=INDEX(_xlfn.SORTBY(tbl_SigWorkings[Factor],tbl_SigWorkings[Cramér''s V],-1),ROW()-ROW(tbl_Significance[#Headers]))} -> Car Ownership | B12: =_xlfn.XLOOKUP(tbl_Significance[[#This Row],[Factor]],tbl_SigWorkings[Factor],tbl_SigWorkings[Chi-square]) -> 49.868599 | C12: =_xlfn.XLOOKUP(tbl_Significance[[#This Row],[Factor]],tbl_SigWorkings[Factor],tbl_SigWorkings[df]) -> 1 | D12: =_xlfn.XLOOKUP(tbl_Significance[[#This Row],[Factor]],tbl_SigWorkings[Factor],tbl_SigWorkings[p-value]) -> 1.6439466e-12 | E12: =_xlfn.XLOOKUP(tbl_Significance[[#This Row],[Factor]],tbl_SigWorkings[Factor],tbl_SigWorkings[Cramér''s V]) -> 0.22331278 | F12: {=_xlfn.IFS(tbl_Significance[[#This Row],[Cramér''s V]]<0.1,"Negligible",tbl_Significance[[#This Row],[Cramér''s V]]<0.2,"Small",tbl_Significance[[#This Row],[Cramér''s V]]<0.3,"Moderate",TRUE,"Strong")} -> Moderate | G12: =IF(tbl_Significance[[#This Row],[p-value]]<0.05,"Yes","No") -> Yes | H12: =IF(_xlfn.XLOOKUP(tbl_Significance[[#This Row],[Factor]],tbl_SigWorkings[Factor],tbl_SigWorkings[Min Expected])>=5,"Yes","No") -> Yes | I12: =IF(tbl_Significance[[#This Row],[Significant?]]="Yes","Matters – "&tbl_Significance[[#This Row],[Strength]]&" effect","No evidence it matters")&IF(tbl_Significance[[#This Row],[Valid (min expected ≥5)]]="No"," (caution: small expected counts)","") -> Matters – Moderate effect
A13: {=INDEX(_xlfn.SORTBY(tbl_SigWorkings[Factor],tbl_SigWorkings[Cramér''s V],-1),ROW()-ROW(tbl_Significance[#Headers]))} -> Age Band | B13: =_xlfn.XLOOKUP(tbl_Significance[[#This Row],[Factor]],tbl_SigWorkings[Factor],tbl_SigWorkings[Chi-square]) -> 42.229226 | C13: =_xlfn.XLOOKUP(tbl_Significance[[#This Row],[Factor]],tbl_SigWorkings[Factor],tbl_SigWorkings[df]) -> 4 | D13: =_xlfn.XLOOKUP(tbl_Significance[[#This Row],[Factor]],tbl_SigWorkings[Factor],tbl_SigWorkings[p-value]) -> 1.4952691e-08 | E13: =_xlfn.XLOOKUP(tbl_Significance[[#This Row],[Factor]],tbl_SigWorkings[Factor],tbl_SigWorkings[Cramér''s V]) -> 0.20549751 | F13: {=_xlfn.IFS(tbl_Significance[[#This Row],[Cramér''s V]]<0.1,"Negligible",tbl_Significance[[#This Row],[Cramér''s V]]<0.2,"Small",tbl_Significance[[#This Row],[Cramér''s V]]<0.3,"Moderate",TRUE,"Strong")} -> Moderate | G13: =IF(tbl_Significance[[#This Row],[p-value]]<0.05,"Yes","No") -> Yes | H13: =IF(_xlfn.XLOOKUP(tbl_Significance[[#This Row],[Factor]],tbl_SigWorkings[Factor],tbl_SigWorkings[Min Expected])>=5,"Yes","No") -> Yes | I13: =IF(tbl_Significance[[#This Row],[Significant?]]="Yes","Matters – "&tbl_Significance[[#This Row],[Strength]]&" effect","No evidence it matters")&IF(tbl_Significance[[#This Row],[Valid (min expected ≥5)]]="No"," (caution: small expected counts)","") -> Matters – Moderate effect
A14: {=INDEX(_xlfn.SORTBY(tbl_SigWorkings[Factor],tbl_SigWorkings[Cramér''s V],-1),ROW()-ROW(tbl_Significance[#Headers]))} -> Commute Distance | B14: =_xlfn.XLOOKUP(tbl_Significance[[#This Row],[Factor]],tbl_SigWorkings[Factor],tbl_SigWorkings[Chi-square]) -> 34.511749 | C14: =_xlfn.XLOOKUP(tbl_Significance[[#This Row],[Factor]],tbl_SigWorkings[Factor],tbl_SigWorkings[df]) -> 4 | D14: =_xlfn.XLOOKUP(tbl_Significance[[#This Row],[Factor]],tbl_SigWorkings[Factor],tbl_SigWorkings[p-value]) -> 5.8515598e-07 | E14: =_xlfn.XLOOKUP(tbl_Significance[[#This Row],[Factor]],tbl_SigWorkings[Factor],tbl_SigWorkings[Cramér''s V]) -> 0.18577338 | F14: {=_xlfn.IFS(tbl_Significance[[#This Row],[Cramér''s V]]<0.1,"Negligible",tbl_Significance[[#This Row],[Cramér''s V]]<0.2,"Small",tbl_Significance[[#This Row],[Cramér''s V]]<0.3,"Moderate",TRUE,"Strong")} -> Small | G14: =IF(tbl_Significance[[#This Row],[p-value]]<0.05,"Yes","No") -> Yes | H14: =IF(_xlfn.XLOOKUP(tbl_Significance[[#This Row],[Factor]],tbl_SigWorkings[Factor],tbl_SigWorkings[Min Expected])>=5,"Yes","No") -> Yes | I14: =IF(tbl_Significance[[#This Row],[Significant?]]="Yes","Matters – "&tbl_Significance[[#This Row],[Strength]]&" effect","No evidence it matters")&IF(tbl_Significance[[#This Row],[Valid (min expected ≥5)]]="No"," (caution: small expected counts)","") -> Matters – Small effect
A15: {=INDEX(_xlfn.SORTBY(tbl_SigWorkings[Factor],tbl_SigWorkings[Cramér''s V],-1),ROW()-ROW(tbl_Significance[#Headers]))} -> Children | B15: =_xlfn.XLOOKUP(tbl_Significance[[#This Row],[Factor]],tbl_SigWorkings[Factor],tbl_SigWorkings[Chi-square]) -> 32.055151 | C15: =_xlfn.XLOOKUP(tbl_Significance[[#This Row],[Factor]],tbl_SigWorkings[Factor],tbl_SigWorkings[df]) -> 5 | D15: =_xlfn.XLOOKUP(tbl_Significance[[#This Row],[Factor]],tbl_SigWorkings[Factor],tbl_SigWorkings[p-value]) -> 5.7937088e-06 | E15: =_xlfn.XLOOKUP(tbl_Significance[[#This Row],[Factor]],tbl_SigWorkings[Factor],tbl_SigWorkings[Cramér''s V]) -> 0.17903952 | F15: {=_xlfn.IFS(tbl_Significance[[#This Row],[Cramér''s V]]<0.1,"Negligible",tbl_Significance[[#This Row],[Cramér''s V]]<0.2,"Small",tbl_Significance[[#This Row],[Cramér''s V]]<0.3,"Moderate",TRUE,"Strong")} -> Small | G15: =IF(tbl_Significance[[#This Row],[p-value]]<0.05,"Yes","No") -> Yes | H15: =IF(_xlfn.XLOOKUP(tbl_Significance[[#This Row],[Factor]],tbl_SigWorkings[Factor],tbl_SigWorkings[Min Expected])>=5,"Yes","No") -> Yes | I15: =IF(tbl_Significance[[#This Row],[Significant?]]="Yes","Matters – "&tbl_Significance[[#This Row],[Strength]]&" effect","No evidence it matters")&IF(tbl_Significance[[#This Row],[Valid (min expected ≥5)]]="No"," (caution: small expected counts)","") -> Matters – Small effect
A16: {=INDEX(_xlfn.SORTBY(tbl_SigWorkings[Factor],tbl_SigWorkings[Cramér''s V],-1),ROW()-ROW(tbl_Significance[#Headers]))} -> Education | B16: =_xlfn.XLOOKUP(tbl_Significance[[#This Row],[Factor]],tbl_SigWorkings[Factor],tbl_SigWorkings[Chi-square]) -> 25.332685 | C16: =_xlfn.XLOOKUP(tbl_Significance[[#This Row],[Factor]],tbl_SigWorkings[Factor],tbl_SigWorkings[df]) -> 4 | D16: =_xlfn.XLOOKUP(tbl_Significance[[#This Row],[Factor]],tbl_SigWorkings[Factor],tbl_SigWorkings[p-value]) -> 4.3125063e-05 | E16: =_xlfn.XLOOKUP(tbl_Significance[[#This Row],[Factor]],tbl_SigWorkings[Factor],tbl_SigWorkings[Cramér''s V]) -> 0.15916245 | F16: {=_xlfn.IFS(tbl_Significance[[#This Row],[Cramér''s V]]<0.1,"Negligible",tbl_Significance[[#This Row],[Cramér''s V]]<0.2,"Small",tbl_Significance[[#This Row],[Cramér''s V]]<0.3,"Moderate",TRUE,"Strong")} -> Small | G16: =IF(tbl_Significance[[#This Row],[p-value]]<0.05,"Yes","No") -> Yes | H16: =IF(_xlfn.XLOOKUP(tbl_Significance[[#This Row],[Factor]],tbl_SigWorkings[Factor],tbl_SigWorkings[Min Expected])>=5,"Yes","No") -> Yes | I16: =IF(tbl_Significance[[#This Row],[Significant?]]="Yes","Matters – "&tbl_Significance[[#This Row],[Strength]]&" effect","No evidence it matters")&IF(tbl_Significance[[#This Row],[Valid (min expected ≥5)]]="No"," (caution: small expected counts)","") -> Matters – Small effect
A17: {=INDEX(_xlfn.SORTBY(tbl_SigWorkings[Factor],tbl_SigWorkings[Cramér''s V],-1),ROW()-ROW(tbl_Significance[#Headers]))} -> Region | B17: =_xlfn.XLOOKUP(tbl_Significance[[#This Row],[Factor]],tbl_SigWorkings[Factor],tbl_SigWorkings[Chi-square]) -> 13.752387 | C17: =_xlfn.XLOOKUP(tbl_Significance[[#This Row],[Factor]],tbl_SigWorkings[Factor],tbl_SigWorkings[df]) -> 2 | D17: =_xlfn.XLOOKUP(tbl_Significance[[#This Row],[Factor]],tbl_SigWorkings[Factor],tbl_SigWorkings[p-value]) -> 0.001032065 | E17: =_xlfn.XLOOKUP(tbl_Significance[[#This Row],[Factor]],tbl_SigWorkings[Factor],tbl_SigWorkings[Cramér''s V]) -> 0.11727057 | F17: {=_xlfn.IFS(tbl_Significance[[#This Row],[Cramér''s V]]<0.1,"Negligible",tbl_Significance[[#This Row],[Cramér''s V]]<0.2,"Small",tbl_Significance[[#This Row],[Cramér''s V]]<0.3,"Moderate",TRUE,"Strong")} -> Small | G17: =IF(tbl_Significance[[#This Row],[p-value]]<0.05,"Yes","No") -> Yes | H17: =IF(_xlfn.XLOOKUP(tbl_Significance[[#This Row],[Factor]],tbl_SigWorkings[Factor],tbl_SigWorkings[Min Expected])>=5,"Yes","No") -> Yes | I17: =IF(tbl_Significance[[#This Row],[Significant?]]="Yes","Matters – "&tbl_Significance[[#This Row],[Strength]]&" effect","No evidence it matters")&IF(tbl_Significance[[#This Row],[Valid (min expected ≥5)]]="No"," (caution: small expected counts)","") -> Matters – Small effect
A18: {=INDEX(_xlfn.SORTBY(tbl_SigWorkings[Factor],tbl_SigWorkings[Cramér''s V],-1),ROW()-ROW(tbl_Significance[#Headers]))} -> Marital Status | B18: =_xlfn.XLOOKUP(tbl_Significance[[#This Row],[Factor]],tbl_SigWorkings[Factor],tbl_SigWorkings[Chi-square]) -> 12.435558 | C18: =_xlfn.XLOOKUP(tbl_Significance[[#This Row],[Factor]],tbl_SigWorkings[Factor],tbl_SigWorkings[df]) -> 1 | D18: =_xlfn.XLOOKUP(tbl_Significance[[#This Row],[Factor]],tbl_SigWorkings[Factor],tbl_SigWorkings[p-value]) -> 0.00042123655 | E18: =_xlfn.XLOOKUP(tbl_Significance[[#This Row],[Factor]],tbl_SigWorkings[Factor],tbl_SigWorkings[Cramér''s V]) -> 0.11151483 | F18: {=_xlfn.IFS(tbl_Significance[[#This Row],[Cramér''s V]]<0.1,"Negligible",tbl_Significance[[#This Row],[Cramér''s V]]<0.2,"Small",tbl_Significance[[#This Row],[Cramér''s V]]<0.3,"Moderate",TRUE,"Strong")} -> Small | G18: =IF(tbl_Significance[[#This Row],[p-value]]<0.05,"Yes","No") -> Yes | H18: =IF(_xlfn.XLOOKUP(tbl_Significance[[#This Row],[Factor]],tbl_SigWorkings[Factor],tbl_SigWorkings[Min Expected])>=5,"Yes","No") -> Yes | I18: =IF(tbl_Significance[[#This Row],[Significant?]]="Yes","Matters – "&tbl_Significance[[#This Row],[Strength]]&" effect","No evidence it matters")&IF(tbl_Significance[[#This Row],[Valid (min expected ≥5)]]="No"," (caution: small expected counts)","") -> Matters – Small effect
A19: {=INDEX(_xlfn.SORTBY(tbl_SigWorkings[Factor],tbl_SigWorkings[Cramér''s V],-1),ROW()-ROW(tbl_Significance[#Headers]))} -> Income Band | B19: =_xlfn.XLOOKUP(tbl_Significance[[#This Row],[Factor]],tbl_SigWorkings[Factor],tbl_SigWorkings[Chi-square]) -> 11.267838 | C19: =_xlfn.XLOOKUP(tbl_Significance[[#This Row],[Factor]],tbl_SigWorkings[Factor],tbl_SigWorkings[df]) -> 3 | D19: =_xlfn.XLOOKUP(tbl_Significance[[#This Row],[Factor]],tbl_SigWorkings[Factor],tbl_SigWorkings[p-value]) -> 0.010362328 | E19: =_xlfn.XLOOKUP(tbl_Significance[[#This Row],[Factor]],tbl_SigWorkings[Factor],tbl_SigWorkings[Cramér''s V]) -> 0.10615007 | F19: {=_xlfn.IFS(tbl_Significance[[#This Row],[Cramér''s V]]<0.1,"Negligible",tbl_Significance[[#This Row],[Cramér''s V]]<0.2,"Small",tbl_Significance[[#This Row],[Cramér''s V]]<0.3,"Moderate",TRUE,"Strong")} -> Small | G19: =IF(tbl_Significance[[#This Row],[p-value]]<0.05,"Yes","No") -> Yes | H19: =IF(_xlfn.XLOOKUP(tbl_Significance[[#This Row],[Factor]],tbl_SigWorkings[Factor],tbl_SigWorkings[Min Expected])>=5,"Yes","No") -> Yes | I19: =IF(tbl_Significance[[#This Row],[Significant?]]="Yes","Matters – "&tbl_Significance[[#This Row],[Strength]]&" effect","No evidence it matters")&IF(tbl_Significance[[#This Row],[Valid (min expected ≥5)]]="No"," (caution: small expected counts)","") -> Matters – Small effect
A20: {=INDEX(_xlfn.SORTBY(tbl_SigWorkings[Factor],tbl_SigWorkings[Cramér''s V],-1),ROW()-ROW(tbl_Significance[#Headers]))} -> Occupation | B20: =_xlfn.XLOOKUP(tbl_Significance[[#This Row],[Factor]],tbl_SigWorkings[Factor],tbl_SigWorkings[Chi-square]) -> 8.005692 | C20: =_xlfn.XLOOKUP(tbl_Significance[[#This Row],[Factor]],tbl_SigWorkings[Factor],tbl_SigWorkings[df]) -> 4 | D20: =_xlfn.XLOOKUP(tbl_Significance[[#This Row],[Factor]],tbl_SigWorkings[Factor],tbl_SigWorkings[p-value]) -> 0.091369913 | E20: =_xlfn.XLOOKUP(tbl_Significance[[#This Row],[Factor]],tbl_SigWorkings[Factor],tbl_SigWorkings[Cramér''s V]) -> 0.089474532 | F20: {=_xlfn.IFS(tbl_Significance[[#This Row],[Cramér''s V]]<0.1,"Negligible",tbl_Significance[[#This Row],[Cramér''s V]]<0.2,"Small",tbl_Significance[[#This Row],[Cramér''s V]]<0.3,"Moderate",TRUE,"Strong")} -> Negligible | G20: =IF(tbl_Significance[[#This Row],[p-value]]<0.05,"Yes","No") -> No | H20: =IF(_xlfn.XLOOKUP(tbl_Significance[[#This Row],[Factor]],tbl_SigWorkings[Factor],tbl_SigWorkings[Min Expected])>=5,"Yes","No") -> Yes | I20: =IF(tbl_Significance[[#This Row],[Significant?]]="Yes","Matters – "&tbl_Significance[[#This Row],[Strength]]&" effect","No evidence it matters")&IF(tbl_Significance[[#This Row],[Valid (min expected ≥5)]]="No"," (caution: small expected counts)","") -> No evidence it matters
A21: {=INDEX(_xlfn.SORTBY(tbl_SigWorkings[Factor],tbl_SigWorkings[Cramér''s V],-1),ROW()-ROW(tbl_Significance[#Headers]))} -> Gender | B21: =_xlfn.XLOOKUP(tbl_Significance[[#This Row],[Factor]],tbl_SigWorkings[Factor],tbl_SigWorkings[Chi-square]) -> 0.23039093 | C21: =_xlfn.XLOOKUP(tbl_Significance[[#This Row],[Factor]],tbl_SigWorkings[Factor],tbl_SigWorkings[df]) -> 1 | D21: =_xlfn.XLOOKUP(tbl_Significance[[#This Row],[Factor]],tbl_SigWorkings[Factor],tbl_SigWorkings[p-value]) -> 0.63123411 | E21: =_xlfn.XLOOKUP(tbl_Significance[[#This Row],[Factor]],tbl_SigWorkings[Factor],tbl_SigWorkings[Cramér''s V]) -> 0.015178634 | F21: {=_xlfn.IFS(tbl_Significance[[#This Row],[Cramér''s V]]<0.1,"Negligible",tbl_Significance[[#This Row],[Cramér''s V]]<0.2,"Small",tbl_Significance[[#This Row],[Cramér''s V]]<0.3,"Moderate",TRUE,"Strong")} -> Negligible | G21: =IF(tbl_Significance[[#This Row],[p-value]]<0.05,"Yes","No") -> No | H21: =IF(_xlfn.XLOOKUP(tbl_Significance[[#This Row],[Factor]],tbl_SigWorkings[Factor],tbl_SigWorkings[Min Expected])>=5,"Yes","No") -> Yes | I21: =IF(tbl_Significance[[#This Row],[Significant?]]="Yes","Matters – "&tbl_Significance[[#This Row],[Strength]]&" effect","No evidence it matters")&IF(tbl_Significance[[#This Row],[Valid (min expected ≥5)]]="No"," (caution: small expected counts)","") -> No evidence it matters
A22: {=INDEX(_xlfn.SORTBY(tbl_SigWorkings[Factor],tbl_SigWorkings[Cramér''s V],-1),ROW()-ROW(tbl_Significance[#Headers]))} -> Home Owner | B22: =_xlfn.XLOOKUP(tbl_Significance[[#This Row],[Factor]],tbl_SigWorkings[Factor],tbl_SigWorkings[Chi-square]) -> 0.22963225 | C22: =_xlfn.XLOOKUP(tbl_Significance[[#This Row],[Factor]],tbl_SigWorkings[Factor],tbl_SigWorkings[df]) -> 1 | D22: =_xlfn.XLOOKUP(tbl_Significance[[#This Row],[Factor]],tbl_SigWorkings[Factor],tbl_SigWorkings[p-value]) -> 0.63179664 | E22: =_xlfn.XLOOKUP(tbl_Significance[[#This Row],[Factor]],tbl_SigWorkings[Factor],tbl_SigWorkings[Cramér''s V]) -> 0.015153622 | F22: {=_xlfn.IFS(tbl_Significance[[#This Row],[Cramér''s V]]<0.1,"Negligible",tbl_Significance[[#This Row],[Cramér''s V]]<0.2,"Small",tbl_Significance[[#This Row],[Cramér''s V]]<0.3,"Moderate",TRUE,"Strong")} -> Negligible | G22: =IF(tbl_Significance[[#This Row],[p-value]]<0.05,"Yes","No") -> No | H22: =IF(_xlfn.XLOOKUP(tbl_Significance[[#This Row],[Factor]],tbl_SigWorkings[Factor],tbl_SigWorkings[Min Expected])>=5,"Yes","No") -> Yes | I22: =IF(tbl_Significance[[#This Row],[Significant?]]="Yes","Matters – "&tbl_Significance[[#This Row],[Strength]]&" effect","No evidence it matters")&IF(tbl_Significance[[#This Row],[Valid (min expected ≥5)]]="No"," (caution: small expected counts)","") -> No evidence it matters
A24: Test workings (unsorted, in block order; feeds the results summary)
A25: Factor | B25: Chi-square | C25: df | D25: p-value | E25: Cramér's V | F25: Min Expected | G25: p check (CHISQ.DIST.RT)
A26: Car Ownership | B26: =I41 -> 49.868599 | C26: =I42 -> 1 | D26: =I43 -> 1.6439466e-12 | E26: =I44 -> 0.22331278 | F26: =I45 -> 233.766 | G26: =_xlfn.CHISQ.DIST.RT(B26,C26) -> 1.6439466e-12
A27: Cars | B27: =I48 -> 50.985549 | C27: =I49 -> 4 | D27: =I50 -> 2.2477924e-10 | E27: =I51 -> 0.2257998 | F27: =I52 -> 28.379 | G27: =_xlfn.CHISQ.DIST.RT(B27,C27) -> 2.2477924e-10
A28: Commute Distance | B28: =I57 -> 34.511749 | C28: =I58 -> 4 | D28: =I59 -> 5.8515598e-07 | E28: =I60 -> 0.18577338 | F28: =I61 -> 53.391 | G28: =_xlfn.CHISQ.DIST.RT(B28,C28) -> 5.8515598e-07
A29: Age Band | B29: =I66 -> 42.229226 | C29: =I67 -> 4 | D29: =I68 -> 1.4952691e-08 | E29: =I69 -> 0.20549751 | F29: =I70 -> 48.1 | G29: =_xlfn.CHISQ.DIST.RT(B29,C29) -> 1.4952691e-08
A30: Children | B30: =I75 -> 32.055151 | C30: =I76 -> 5 | D30: =I77 -> 5.7937088e-06 | E30: =I78 -> 0.17903952 | F30: =I79 -> 38.961 | G30: =_xlfn.CHISQ.DIST.RT(B30,C30) -> 5.7937088e-06
A31: Education | B31: =I85 -> 25.332685 | C31: =I86 -> 4 | D31: =I87 -> 4.3125063e-05 | E31: =I88 -> 0.15916245 | F31: =I89 -> 36.556 | G31: =_xlfn.CHISQ.DIST.RT(B31,C31) -> 4.3125063e-05
A32: Region | B32: =I94 -> 13.752387 | C32: =I95 -> 2 | D32: =I96 -> 0.001032065 | E32: =I97 -> 0.11727057 | F32: =I98 -> 92.352 | G32: =_xlfn.CHISQ.DIST.RT(B32,C32) -> 0.001032065
A33: Marital Status | B33: =I101 -> 12.435558 | C33: =I102 -> 1 | D33: =I103 -> 0.00042123655 | E33: =I104 -> 0.11151483 | F33: =I105 -> 222.222 | G33: =_xlfn.CHISQ.DIST.RT(B33,C33) -> 0.00042123655
A34: Income Band | B34: =I108 -> 11.267838 | C34: =I109 -> 3 | D34: =I110 -> 0.010362328 | E34: =I111 -> 0.10615007 | F34: =I112 -> 50.505 | G34: =_xlfn.CHISQ.DIST.RT(B34,C34) -> 0.010362328
A35: Occupation | B35: =I116 -> 8.005692 | C35: =I117 -> 4 | D35: =I118 -> 0.091369913 | E35: =I119 -> 0.089474532 | F35: =I120 -> 57.239 | G35: =_xlfn.CHISQ.DIST.RT(B35,C35) -> 0.091369913
A36: Home Owner | B36: =I125 -> 0.22963225 | C36: =I126 -> 1 | D36: =I127 -> 0.63179664 | E36: =I128 -> 0.015153622 | F36: =I129 -> 152.477 | G36: =_xlfn.CHISQ.DIST.RT(B36,C36) -> 0.63179664
A37: Gender | B37: =I132 -> 0.23039093 | C37: =I133 -> 1 | D37: =I134 -> 0.63123411 | E37: =I135 -> 0.015178634 | F37: =I136 -> 235.209 | G37: =_xlfn.CHISQ.DIST.RT(B37,C37) -> 0.63123411
A40: Car Ownership
A41: Segment | B41: Bought | C41: Not bought | D41: Total | E41: Expected bought | F41: Expected not bought | H41: Chi-square statistic | I41: {=SUM((_xlfn.ANCHORARRAY(B42)-_xlfn.ANCHORARRAY(E42))^2/_xlfn.ANCHORARRAY(E42))+SUM((_xlfn.ANCHORARRAY(C42)-_xlfn.ANCHORARRAY(F42))^2/_xlfn.ANCHORARRAY(F42))} -> 49.868599
A42: {=_xlfn.LET(_xlpm.s,_xlfn.UNIQUE(tbl_Clean[Car Ownership]),_xlfn.SORTBY(_xlpm.s,COUNTIFS(tbl_Clean[Car Ownership],_xlpm.s,tbl_Clean[Purchased Flag],1)/COUNTIFS(tbl_Clean[Car Ownership],_xlpm.s),-1))} -> 0-1 Cars | B42: {=COUNTIFS(tbl_Clean[Car Ownership],_xlfn.ANCHORARRAY(A42),tbl_Clean[Purchased Flag],1)} -> 303 | C42: {=COUNTIFS(tbl_Clean[Car Ownership],_xlfn.ANCHORARRAY(A42),tbl_Clean[Purchased Flag],0)} -> 211 | D42: {=_xlfn.ANCHORARRAY(B42)+_xlfn.ANCHORARRAY(C42)} -> 514 | E42: {=_xlfn.ANCHORARRAY(D42)*B44/D44} -> 247.234 | F42: {=_xlfn.ANCHORARRAY(D42)*C44/D44} -> 266.766 | H42: Degrees of freedom | I42: =(ROWS(_xlfn.ANCHORARRAY(A42))-1)*(2-1) -> 1
A43: 2+ Cars | B43: 178 | C43: 308 | D43: 486 | E43: 233.766 | F43: 252.234 | H43: p-value | I43: =_xlfn.CHISQ.TEST(_xlfn.HSTACK(_xlfn.ANCHORARRAY(B42),_xlfn.ANCHORARRAY(C42)),_xlfn.HSTACK(_xlfn.ANCHORARRAY(E42),_xlfn.ANCHORARRAY(F42))) -> 1.6439466e-12
A44: Total | B44: =SUM(_xlfn.ANCHORARRAY(B42)) -> 481 | C44: =SUM(_xlfn.ANCHORARRAY(C42)) -> 519 | D44: =SUM(_xlfn.ANCHORARRAY(D42)) -> 1000 | E44: =SUM(_xlfn.ANCHORARRAY(E42)) -> 481 | F44: =SUM(_xlfn.ANCHORARRAY(F42)) -> 519 | H44: Cramér's V | I44: =SQRT(I41/D44) -> 0.22331278
H45: Min expected count | I45: =MIN(_xlfn.ANCHORARRAY(E42),_xlfn.ANCHORARRAY(F42)) -> 233.766
A47: Cars
A48: Segment | B48: Bought | C48: Not bought | D48: Total | E48: Expected bought | F48: Expected not bought | H48: Chi-square statistic | I48: {=SUM((_xlfn.ANCHORARRAY(B49)-_xlfn.ANCHORARRAY(E49))^2/_xlfn.ANCHORARRAY(E49))+SUM((_xlfn.ANCHORARRAY(C49)-_xlfn.ANCHORARRAY(F49))^2/_xlfn.ANCHORARRAY(F49))} -> 50.985549
A49: {=_xlfn._xlws.SORT(_xlfn.UNIQUE(tbl_Clean[Cars]))} -> 0 | B49: {=COUNTIFS(tbl_Clean[Cars],_xlfn.ANCHORARRAY(A49),tbl_Clean[Purchased Flag],1)} -> 151 | C49: {=COUNTIFS(tbl_Clean[Cars],_xlfn.ANCHORARRAY(A49),tbl_Clean[Purchased Flag],0)} -> 96 | D49: {=_xlfn.ANCHORARRAY(B49)+_xlfn.ANCHORARRAY(C49)} -> 247 | E49: {=_xlfn.ANCHORARRAY(D49)*B54/D54} -> 118.807 | F49: {=_xlfn.ANCHORARRAY(D49)*C54/D54} -> 128.193 | H49: Degrees of freedom | I49: =(ROWS(_xlfn.ANCHORARRAY(A49))-1)*(2-1) -> 4
A50: 1 | B50: 152 | C50: 115 | D50: 267 | E50: 128.427 | F50: 138.573 | H50: p-value | I50: =_xlfn.CHISQ.TEST(_xlfn.HSTACK(_xlfn.ANCHORARRAY(B49),_xlfn.ANCHORARRAY(C49)),_xlfn.HSTACK(_xlfn.ANCHORARRAY(E49),_xlfn.ANCHORARRAY(F49))) -> 2.2477924e-10
A51: 2 | B51: 124 | C51: 218 | D51: 342 | E51: 164.502 | F51: 177.498 | H51: Cramér's V | I51: =SQRT(I48/D54) -> 0.2257998
A52: 3 | B52: 33 | C52: 52 | D52: 85 | E52: 40.885 | F52: 44.115 | H52: Min expected count | I52: =MIN(_xlfn.ANCHORARRAY(E49),_xlfn.ANCHORARRAY(F49)) -> 28.379
A53: 4 | B53: 21 | C53: 38 | D53: 59 | E53: 28.379 | F53: 30.621
A54: Total | B54: =SUM(_xlfn.ANCHORARRAY(B49)) -> 481 | C54: =SUM(_xlfn.ANCHORARRAY(C49)) -> 519 | D54: =SUM(_xlfn.ANCHORARRAY(D49)) -> 1000 | E54: =SUM(_xlfn.ANCHORARRAY(E49)) -> 481 | F54: =SUM(_xlfn.ANCHORARRAY(F49)) -> 519
A56: Commute Distance
A57: Segment | B57: Bought | C57: Not bought | D57: Total | E57: Expected bought | F57: Expected not bought | H57: Chi-square statistic | I57: {=SUM((_xlfn.ANCHORARRAY(B58)-_xlfn.ANCHORARRAY(E58))^2/_xlfn.ANCHORARRAY(E58))+SUM((_xlfn.ANCHORARRAY(C58)-_xlfn.ANCHORARRAY(F58))^2/_xlfn.ANCHORARRAY(F58))} -> 34.511749
A58: {=_xlfn.LET(_xlpm.u,_xlfn.UNIQUE(_xlfn.HSTACK(tbl_Clean[Commute Distance],tbl_Clean[Commute Sort])),_xlfn.TAKE(_xlfn._xlws.SORT(_xlpm.u,2),,1))} -> 0-1 Miles | B58: {=COUNTIFS(tbl_Clean[Commute Distance],_xlfn.ANCHORARRAY(A58),tbl_Clean[Purchased Flag],1)} -> 200 | C58: {=COUNTIFS(tbl_Clean[Commute Distance],_xlfn.ANCHORARRAY(A58),tbl_Clean[Purchased Flag],0)} -> 166 | D58: {=_xlfn.ANCHORARRAY(B58)+_xlfn.ANCHORARRAY(C58)} -> 366 | E58: {=_xlfn.ANCHORARRAY(D58)*B63/D63} -> 176.046 | F58: {=_xlfn.ANCHORARRAY(D58)*C63/D63} -> 189.954 | H58: Degrees of freedom | I58: =(ROWS(_xlfn.ANCHORARRAY(A58))-1)*(2-1) -> 4
A59: 1-2 Miles | B59: 77 | C59: 92 | D59: 169 | E59: 81.289 | F59: 87.711 | H59: p-value | I59: =_xlfn.CHISQ.TEST(_xlfn.HSTACK(_xlfn.ANCHORARRAY(B58),_xlfn.ANCHORARRAY(C58)),_xlfn.HSTACK(_xlfn.ANCHORARRAY(E58),_xlfn.ANCHORARRAY(F58))) -> 5.8515598e-07
A60: 2-5 Miles | B60: 95 | C60: 67 | D60: 162 | E60: 77.922 | F60: 84.078 | H60: Cramér's V | I60: =SQRT(I57/D63) -> 0.18577338
A61: 5-10 Miles | B61: 76 | C61: 116 | D61: 192 | E61: 92.352 | F61: 99.648 | H61: Min expected count | I61: =MIN(_xlfn.ANCHORARRAY(E58),_xlfn.ANCHORARRAY(F58)) -> 53.391
A62: 10+ Miles | B62: 33 | C62: 78 | D62: 111 | E62: 53.391 | F62: 57.609
A63: Total | B63: =SUM(_xlfn.ANCHORARRAY(B58)) -> 481 | C63: =SUM(_xlfn.ANCHORARRAY(C58)) -> 519 | D63: =SUM(_xlfn.ANCHORARRAY(D58)) -> 1000 | E63: =SUM(_xlfn.ANCHORARRAY(E58)) -> 481 | F63: =SUM(_xlfn.ANCHORARRAY(F58)) -> 519
A65: Age Band
A66: Segment | B66: Bought | C66: Not bought | D66: Total | E66: Expected bought | F66: Expected not bought | H66: Chi-square statistic | I66: {=SUM((_xlfn.ANCHORARRAY(B67)-_xlfn.ANCHORARRAY(E67))^2/_xlfn.ANCHORARRAY(E67))+SUM((_xlfn.ANCHORARRAY(C67)-_xlfn.ANCHORARRAY(F67))^2/_xlfn.ANCHORARRAY(F67))} -> 42.229226
A67: {=_xlfn.LET(_xlpm.u,_xlfn.UNIQUE(_xlfn.HSTACK(tbl_Clean[Age Band],tbl_Clean[Age Band Sort])),_xlfn.TAKE(_xlfn._xlws.SORT(_xlpm.u,2),,1))} -> 25-30 | B67: {=COUNTIFS(tbl_Clean[Age Band],_xlfn.ANCHORARRAY(A67),tbl_Clean[Purchased Flag],1)} -> 39 | C67: {=COUNTIFS(tbl_Clean[Age Band],_xlfn.ANCHORARRAY(A67),tbl_Clean[Purchased Flag],0)} -> 71 | D67: {=_xlfn.ANCHORARRAY(B67)+_xlfn.ANCHORARRAY(C67)} -> 110 | E67: {=_xlfn.ANCHORARRAY(D67)*B72/D72} -> 52.91 | F67: {=_xlfn.ANCHORARRAY(D67)*C72/D72} -> 57.09 | H67: Degrees of freedom | I67: =(ROWS(_xlfn.ANCHORARRAY(A67))-1)*(2-1) -> 4
A68: 31-40 | B68: 193 | C68: 123 | D68: 316 | E68: 151.996 | F68: 164.004 | H68: p-value | I68: =_xlfn.CHISQ.TEST(_xlfn.HSTACK(_xlfn.ANCHORARRAY(B67),_xlfn.ANCHORARRAY(C67)),_xlfn.HSTACK(_xlfn.ANCHORARRAY(E67),_xlfn.ANCHORARRAY(F67))) -> 1.4952691e-08
A69: 41-50 | B69: 139 | C69: 159 | D69: 298 | E69: 143.338 | F69: 154.662 | H69: Cramér's V | I69: =SQRT(I66/D72) -> 0.20549751
A70: 51-60 | B70: 80 | C70: 96 | D70: 176 | E70: 84.656 | F70: 91.344 | H70: Min expected count | I70: =MIN(_xlfn.ANCHORARRAY(E67),_xlfn.ANCHORARRAY(F67)) -> 48.1
A71: 61+ | B71: 30 | C71: 70 | D71: 100 | E71: 48.1 | F71: 51.9
A72: Total | B72: =SUM(_xlfn.ANCHORARRAY(B67)) -> 481 | C72: =SUM(_xlfn.ANCHORARRAY(C67)) -> 519 | D72: =SUM(_xlfn.ANCHORARRAY(D67)) -> 1000 | E72: =SUM(_xlfn.ANCHORARRAY(E67)) -> 481 | F72: =SUM(_xlfn.ANCHORARRAY(F67)) -> 519
A74: Children
A75: Segment | B75: Bought | C75: Not bought | D75: Total | E75: Expected bought | F75: Expected not bought | H75: Chi-square statistic | I75: {=SUM((_xlfn.ANCHORARRAY(B76)-_xlfn.ANCHORARRAY(E76))^2/_xlfn.ANCHORARRAY(E76))+SUM((_xlfn.ANCHORARRAY(C76)-_xlfn.ANCHORARRAY(F76))^2/_xlfn.ANCHORARRAY(F76))} -> 32.055151
A76: {=_xlfn._xlws.SORT(_xlfn.UNIQUE(tbl_Clean[Children]))} -> 0 | B76: {=COUNTIFS(tbl_Clean[Children],_xlfn.ANCHORARRAY(A76),tbl_Clean[Purchased Flag],1)} -> 142 | C76: {=COUNTIFS(tbl_Clean[Children],_xlfn.ANCHORARRAY(A76),tbl_Clean[Purchased Flag],0)} -> 139 | D76: {=_xlfn.ANCHORARRAY(B76)+_xlfn.ANCHORARRAY(C76)} -> 281 | E76: {=_xlfn.ANCHORARRAY(D76)*B82/D82} -> 135.161 | F76: {=_xlfn.ANCHORARRAY(D76)*C82/D82} -> 145.839 | H76: Degrees of freedom | I76: =(ROWS(_xlfn.ANCHORARRAY(A76))-1)*(2-1) -> 5
A77: 1 | B77: 97 | C77: 72 | D77: 169 | E77: 81.289 | F77: 87.711 | H77: p-value | I77: =_xlfn.CHISQ.TEST(_xlfn.HSTACK(_xlfn.ANCHORARRAY(B76),_xlfn.ANCHORARRAY(C76)),_xlfn.HSTACK(_xlfn.ANCHORARRAY(E76),_xlfn.ANCHORARRAY(F76))) -> 5.7937088e-06
A78: 2 | B78: 97 | C78: 112 | D78: 209 | E78: 100.529 | F78: 108.471 | H78: Cramér's V | I78: =SQRT(I75/D82) -> 0.17903952
A79: 3 | B79: 73 | C79: 61 | D79: 134 | E79: 64.454 | F79: 69.546 | H79: Min expected count | I79: =MIN(_xlfn.ANCHORARRAY(E76),_xlfn.ANCHORARRAY(F76)) -> 38.961
A80: 4 | B80: 54 | C80: 72 | D80: 126 | E80: 60.606 | F80: 65.394
A81: 5 | B81: 18 | C81: 63 | D81: 81 | E81: 38.961 | F81: 42.039
A82: Total | B82: =SUM(_xlfn.ANCHORARRAY(B76)) -> 481 | C82: =SUM(_xlfn.ANCHORARRAY(C76)) -> 519 | D82: =SUM(_xlfn.ANCHORARRAY(D76)) -> 1000 | E82: =SUM(_xlfn.ANCHORARRAY(E76)) -> 481 | F82: =SUM(_xlfn.ANCHORARRAY(F76)) -> 519
A84: Education
A85: Segment | B85: Bought | C85: Not bought | D85: Total | E85: Expected bought | F85: Expected not bought | H85: Chi-square statistic | I85: {=SUM((_xlfn.ANCHORARRAY(B86)-_xlfn.ANCHORARRAY(E86))^2/_xlfn.ANCHORARRAY(E86))+SUM((_xlfn.ANCHORARRAY(C86)-_xlfn.ANCHORARRAY(F86))^2/_xlfn.ANCHORARRAY(F86))} -> 25.332685
A86: {=_xlfn.LET(_xlpm.u,_xlfn.UNIQUE(_xlfn.HSTACK(tbl_Clean[Education],tbl_Clean[Education Sort])),_xlfn.TAKE(_xlfn._xlws.SORT(_xlpm.u,2),,1))} -> Partial High School | B86: {=COUNTIFS(tbl_Clean[Education],_xlfn.ANCHORARRAY(A86),tbl_Clean[Purchased Flag],1)} -> 20 | C86: {=COUNTIFS(tbl_Clean[Education],_xlfn.ANCHORARRAY(A86),tbl_Clean[Purchased Flag],0)} -> 56 | D86: {=_xlfn.ANCHORARRAY(B86)+_xlfn.ANCHORARRAY(C86)} -> 76 | E86: {=_xlfn.ANCHORARRAY(D86)*B91/D91} -> 36.556 | F86: {=_xlfn.ANCHORARRAY(D86)*C91/D91} -> 39.444 | H86: Degrees of freedom | I86: =(ROWS(_xlfn.ANCHORARRAY(A86))-1)*(2-1) -> 4
A87: High School | B87: 79 | C87: 100 | D87: 179 | E87: 86.099 | F87: 92.901 | H87: p-value | I87: =_xlfn.CHISQ.TEST(_xlfn.HSTACK(_xlfn.ANCHORARRAY(B86),_xlfn.ANCHORARRAY(C86)),_xlfn.HSTACK(_xlfn.ANCHORARRAY(E86),_xlfn.ANCHORARRAY(F86))) -> 4.3125063e-05
A88: Partial College | B88: 119 | C88: 146 | D88: 265 | E88: 127.465 | F88: 137.535 | H88: Cramér's V | I88: =SQRT(I85/D91) -> 0.15916245
A89: Bachelors | B89: 169 | C89: 137 | D89: 306 | E89: 147.186 | F89: 158.814 | H89: Min expected count | I89: =MIN(_xlfn.ANCHORARRAY(E86),_xlfn.ANCHORARRAY(F86)) -> 36.556
A90: Graduate Degree | B90: 94 | C90: 80 | D90: 174 | E90: 83.694 | F90: 90.306
A91: Total | B91: =SUM(_xlfn.ANCHORARRAY(B86)) -> 481 | C91: =SUM(_xlfn.ANCHORARRAY(C86)) -> 519 | D91: =SUM(_xlfn.ANCHORARRAY(D86)) -> 1000 | E91: =SUM(_xlfn.ANCHORARRAY(E86)) -> 481 | F91: =SUM(_xlfn.ANCHORARRAY(F86)) -> 519
A93: Region
A94: Segment | B94: Bought | C94: Not bought | D94: Total | E94: Expected bought | F94: Expected not bought | H94: Chi-square statistic | I94: {=SUM((_xlfn.ANCHORARRAY(B95)-_xlfn.ANCHORARRAY(E95))^2/_xlfn.ANCHORARRAY(E95))+SUM((_xlfn.ANCHORARRAY(C95)-_xlfn.ANCHORARRAY(F95))^2/_xlfn.ANCHORARRAY(F95))} -> 13.752387
A95: {=_xlfn.LET(_xlpm.s,_xlfn.UNIQUE(tbl_Clean[Region]),_xlfn.SORTBY(_xlpm.s,COUNTIFS(tbl_Clean[Region],_xlpm.s,tbl_Clean[Purchased Flag],1)/COUNTIFS(tbl_Clean[Region],_xlpm.s),-1))} -> Pacific | B95: {=COUNTIFS(tbl_Clean[Region],_xlfn.ANCHORARRAY(A95),tbl_Clean[Purchased Flag],1)} -> 113 | C95: {=COUNTIFS(tbl_Clean[Region],_xlfn.ANCHORARRAY(A95),tbl_Clean[Purchased Flag],0)} -> 79 | D95: {=_xlfn.ANCHORARRAY(B95)+_xlfn.ANCHORARRAY(C95)} -> 192 | E95: {=_xlfn.ANCHORARRAY(D95)*B98/D98} -> 92.352 | F95: {=_xlfn.ANCHORARRAY(D95)*C98/D98} -> 99.648 | H95: Degrees of freedom | I95: =(ROWS(_xlfn.ANCHORARRAY(A95))-1)*(2-1) -> 2
A96: Europe | B96: 148 | C96: 152 | D96: 300 | E96: 144.3 | F96: 155.7 | H96: p-value | I96: =_xlfn.CHISQ.TEST(_xlfn.HSTACK(_xlfn.ANCHORARRAY(B95),_xlfn.ANCHORARRAY(C95)),_xlfn.HSTACK(_xlfn.ANCHORARRAY(E95),_xlfn.ANCHORARRAY(F95))) -> 0.001032065
A97: North America | B97: 220 | C97: 288 | D97: 508 | E97: 244.348 | F97: 263.652 | H97: Cramér's V | I97: =SQRT(I94/D98) -> 0.11727057
A98: Total | B98: =SUM(_xlfn.ANCHORARRAY(B95)) -> 481 | C98: =SUM(_xlfn.ANCHORARRAY(C95)) -> 519 | D98: =SUM(_xlfn.ANCHORARRAY(D95)) -> 1000 | E98: =SUM(_xlfn.ANCHORARRAY(E95)) -> 481 | F98: =SUM(_xlfn.ANCHORARRAY(F95)) -> 519 | H98: Min expected count | I98: =MIN(_xlfn.ANCHORARRAY(E95),_xlfn.ANCHORARRAY(F95)) -> 92.352
A100: Marital Status
A101: Segment | B101: Bought | C101: Not bought | D101: Total | E101: Expected bought | F101: Expected not bought | H101: Chi-square statistic | I101: {=SUM((_xlfn.ANCHORARRAY(B102)-_xlfn.ANCHORARRAY(E102))^2/_xlfn.ANCHORARRAY(E102))+SUM((_xlfn.ANCHORARRAY(C102)-_xlfn.ANCHORARRAY(F102))^2/_xlfn.ANCHORARRAY(F102))} -> 12.435558
A102: {=_xlfn.LET(_xlpm.s,_xlfn.UNIQUE(tbl_Clean[Marital Status]),_xlfn.SORTBY(_xlpm.s,COUNTIFS(tbl_Clean[Marital Status],_xlpm.s,tbl_Clean[Purchased Flag],1)/COUNTIFS(tbl_Clean[Marital Status],_xlpm.s),-1))} -> Single | B102: {=COUNTIFS(tbl_Clean[Marital Status],_xlfn.ANCHORARRAY(A102),tbl_Clean[Purchased Flag],1)} -> 250 | C102: {=COUNTIFS(tbl_Clean[Marital Status],_xlfn.ANCHORARRAY(A102),tbl_Clean[Purchased Flag],0)} -> 212 | D102: {=_xlfn.ANCHORARRAY(B102)+_xlfn.ANCHORARRAY(C102)} -> 462 | E102: {=_xlfn.ANCHORARRAY(D102)*B104/D104} -> 222.222 | F102: {=_xlfn.ANCHORARRAY(D102)*C104/D104} -> 239.778 | H102: Degrees of freedom | I102: =(ROWS(_xlfn.ANCHORARRAY(A102))-1)*(2-1) -> 1
A103: Married | B103: 231 | C103: 307 | D103: 538 | E103: 258.778 | F103: 279.222 | H103: p-value | I103: =_xlfn.CHISQ.TEST(_xlfn.HSTACK(_xlfn.ANCHORARRAY(B102),_xlfn.ANCHORARRAY(C102)),_xlfn.HSTACK(_xlfn.ANCHORARRAY(E102),_xlfn.ANCHORARRAY(F102))) -> 0.00042123655
A104: Total | B104: =SUM(_xlfn.ANCHORARRAY(B102)) -> 481 | C104: =SUM(_xlfn.ANCHORARRAY(C102)) -> 519 | D104: =SUM(_xlfn.ANCHORARRAY(D102)) -> 1000 | E104: =SUM(_xlfn.ANCHORARRAY(E102)) -> 481 | F104: =SUM(_xlfn.ANCHORARRAY(F102)) -> 519 | H104: Cramér's V | I104: =SQRT(I101/D104) -> 0.11151483
H105: Min expected count | I105: =MIN(_xlfn.ANCHORARRAY(E102),_xlfn.ANCHORARRAY(F102)) -> 222.222
A107: Income Band
A108: Segment | B108: Bought | C108: Not bought | D108: Total | E108: Expected bought | F108: Expected not bought | H108: Chi-square statistic | I108: {=SUM((_xlfn.ANCHORARRAY(B109)-_xlfn.ANCHORARRAY(E109))^2/_xlfn.ANCHORARRAY(E109))+SUM((_xlfn.ANCHORARRAY(C109)-_xlfn.ANCHORARRAY(F109))^2/_xlfn.ANCHORARRAY(F109))} -> 11.267838
A109: {=_xlfn.LET(_xlpm.u,_xlfn.UNIQUE(_xlfn.HSTACK(tbl_Clean[Income Band],tbl_Clean[Income Band Sort])),_xlfn.TAKE(_xlfn._xlws.SORT(_xlpm.u,2),,1))} -> $10k-30k | B109: {=COUNTIFS(tbl_Clean[Income Band],_xlfn.ANCHORARRAY(A109),tbl_Clean[Purchased Flag],1)} -> 113 | C109: {=COUNTIFS(tbl_Clean[Income Band],_xlfn.ANCHORARRAY(A109),tbl_Clean[Purchased Flag],0)} -> 169 | D109: {=_xlfn.ANCHORARRAY(B109)+_xlfn.ANCHORARRAY(C109)} -> 282 | E109: {=_xlfn.ANCHORARRAY(D109)*B113/D113} -> 135.642 | F109: {=_xlfn.ANCHORARRAY(D109)*C113/D113} -> 146.358 | H109: Degrees of freedom | I109: =(ROWS(_xlfn.ANCHORARRAY(A109))-1)*(2-1) -> 3
A110: $40k-60k | B110: 191 | C110: 168 | D110: 359 | E110: 172.679 | F110: 186.321 | H110: p-value | I110: =_xlfn.CHISQ.TEST(_xlfn.HSTACK(_xlfn.ANCHORARRAY(B109),_xlfn.ANCHORARRAY(C109)),_xlfn.HSTACK(_xlfn.ANCHORARRAY(E109),_xlfn.ANCHORARRAY(F109))) -> 0.010362328
A111: $70k-90k | B111: 126 | C111: 128 | D111: 254 | E111: 122.174 | F111: 131.826 | H111: Cramér's V | I111: =SQRT(I108/D113) -> 0.10615007
A112: $100k+ | B112: 51 | C112: 54 | D112: 105 | E112: 50.505 | F112: 54.495 | H112: Min expected count | I112: =MIN(_xlfn.ANCHORARRAY(E109),_xlfn.ANCHORARRAY(F109)) -> 50.505
A113: Total | B113: =SUM(_xlfn.ANCHORARRAY(B109)) -> 481 | C113: =SUM(_xlfn.ANCHORARRAY(C109)) -> 519 | D113: =SUM(_xlfn.ANCHORARRAY(D109)) -> 1000 | E113: =SUM(_xlfn.ANCHORARRAY(E109)) -> 481 | F113: =SUM(_xlfn.ANCHORARRAY(F109)) -> 519
...

Sheet Lead_Scoring
A1: Lead scoring: ranking every customer by how likely they are to buy
A2: Purpose: score all 1,000 customers from their segments' purchase rates, test how well the score concentrates buyers, and list who to follow up first.
K3: Customer scores (all customers, tbl_Clean order)
A4: Method | K4: ID | L4: Car Ownership | M4: Age Band | N4: Commute Distance | O4: Children | P4: Education | Q4: Region | R4: Marital Status | S4: Income Band | T4: Raw score | U4: Lead score (0-100) | V4: Rank | W4: Decile | X4: Tier | Y4: Purchased Flag
A5: • Score = weighted average of the purchase rates of each customer's segments. | K5: {=tbl_Clean[ID]} -> 12496 | L5: {=tbl_Clean[Car Ownership]} -> 0-1 Cars | M5: {=tbl_Clean[Age Band]} -> 41-50 | N5: {=tbl_Clean[Commute Distance]} -> 0-1 Miles | O5: {=tbl_Clean[Children]} -> 1 | P5: {=tbl_Clean[Education]} -> Bachelors | Q5: {=tbl_Clean[Region]} -> Europe | R5: {=tbl_Clean[Marital Status]} -> Married | S5: {=tbl_Clean[Income Band]} -> $40k-60k | T5: {=_xlfn.LET(_xlpm.seg,_xlfn.HSTACK(_xlfn.ANCHORARRAY(L5),_xlfn.ANCHORARRAY(M5),_xlfn.ANCHORARRAY(N5),_xlfn.ANCHORARRAY(O5),_xlfn.ANCHORARRAY(P5),_xlfn.ANCHORARRAY(Q5),_xlfn.ANCHORARRAY(R5),_xlfn.ANCHORARRAY(S5)),_xlpm.hdr,$L$4:$S$4,_xlpm.w,_xlfn.XLOOKUP(_xlpm.hdr,tbl_Weights[Factor],tbl_Weights[Weight]),_xlpm.rate,_xlfn.XLOOKUP(_xlpm.hdr&"|"&_xlpm.seg,tbl_SegmentRates[Key],tbl_SegmentRates[Purchase Rate]),MMULT(_xlpm.rate,TRANSPOSE(_xlpm.w)))} -> 0.52952886 | U5: {=_xlfn.LET(_xlpm.r,_xlfn.ANCHORARRAY(T5),(_xlpm.r-MIN(_xlpm.r))/(MAX(_xlpm.r)-MIN(_xlpm.r))*100)} -> 82.097557 | V5: {=COUNTIFS(_xlfn.ANCHORARRAY(T5),">"&_xlfn.ANCHORARRAY(T5))+COUNTIFS(_xlfn.ANCHORARRAY(T5),_xlfn.ANCHORARRAY(T5),_xlfn.ANCHORARRAY(K5),"<"&_xlfn.ANCHORARRAY(K5))+1} -> 192 | W5: {=ROUNDUP(_xlfn.ANCHORARRAY(V5)*10/ROWS(_xlfn.ANCHORARRAY(V5)),0)} -> 2 | X5: {=IF(_xlfn.ANCHORARRAY(W5)<=Hot_Cutoff,"Hot",IF(_xlfn.ANCHORARRAY(W5)<=Warm_Cutoff,"Warm","Cold"))} -> Hot | Y5: {=tbl_Clean[Purchased Flag]} -> 0
A6: • Weights = Cramér's V from Significance_Tests, normalised to sum to 1. | K6: 24107 | L6: 0-1 Cars | M6: 41-50 | N6: 0-1 Miles | O6: 3 | P6: Partial College | Q6: Europe | R6: Married | S6: $10k-30k | T6: 0.50188589 | U6: 68.694763 | V6: 359 | W6: 4 | X6: Warm | Y6: 0
A7: • Excluded: Occupation, Home Owner, Gender (not significant); Cars (duplicates Car Ownership). | K7: 14177 | L7: 2+ Cars | M7: 51-60 | N7: 2-5 Miles | O7: 5 | P7: Partial College | Q7: Europe | R7: Married | S7: $70k-90k | T7: 0.43005399 | U7: 33.866816 | V7: 841 | W7: 9 | X7: Cold | Y7: 0
A8: • Limitation: rates and scores come from the same 1,000 customers (in-sample), so results are indicative, not a validated forecast. | K8: 24381 | L8: 0-1 Cars | M8: 41-50 | N8: 5-10 Miles | O8: 0 | P8: Bachelors | Q8: Pacific | R8: Single | S8: $70k-90k | T8: 0.51364222 | U8: 74.394863 | V8: 292 | W8: 3 | X8: Hot | Y8: 1
K9: 25597 | L9: 0-1 Cars | M9: 31-40 | N9: 0-1 Miles | O9: 0 | P9: Bachelors | Q9: Europe | R9: Single | S9: $10k-30k | T9: 0.54187035 | U9: 88.081371 | V9: 97 | W9: 1 | X9: Hot | Y9: 1
A10: =_xlfn.LET(_xlpm.c,INDEX(tbl_TierSummary[Customers],1),_xlpm.cap,INDEX(tbl_TierSummary[Share of All Buyers],1),_xlpm.rt,INDEX(tbl_TierSummary[Purchase Rate],1),_xlpm.lift,INDEX(tbl_TierSummary[Lift vs Avg],1),"Targeting the top "&TEXT(_xlpm.c/ROWS(_xlfn.ANCHORARRAY($K$5)),"0%")&" of customers (Hot tier) reaches "&TEXT(_xlpm.cap,"0.0%")&" of all buyers at a "&TEXT(_xlpm.rt,"0.0%")&" purchase rate, "&TEXT(_xlpm.lift,"0.00")&"x the average.") -> Targeting the top 30% of customers (Hot tier) reaches 43.9% of all buyers at a 70.3% purchase rate, 1.46x the average. | K10: 13507 | L10: 0-1 Cars | M10: 41-50 | N10: 1-2 Miles | O10: 2 | P10: Partial College | Q10: Europe | R10: Married | S10: $10k-30k | T10: 0.47756792 | U10: 56.904112 | V10: 526 | W10: 6 | X10: Warm | Y10: 0
K11: 27974 | L11: 2+ Cars | M11: 31-40 | N11: 0-1 Miles | O11: 2 | P11: High School | Q11: Pacific | R11: Single | S11: $100k+ | T11: 0.49939 | U11: 67.48462 | V11: 379 | W11: 4 | X11: Warm | Y11: 1
K12: 19364 | L12: 0-1 Cars | M12: 41-50 | N12: 0-1 Miles | O12: 1 | P12: Bachelors | Q12: Europe | R12: Married | S12: $40k-60k | T12: 0.52952886 | U12: 82.097557 | V12: 197 | W12: 2 | X12: Hot | Y12: 1
A13: Inputs | K13: 22155 | L13: 2+ Cars | M13: 51-60 | N13: 5-10 Miles | O13: 2 | P13: Partial High School | Q13: Pacific | R13: Married | S13: $10k-30k | T13: 0.41402388 | U13: 26.09456 | V13: 922 | W13: 10 | X13: Cold | Y13: 0
A14: Hot tier: up to decile | B14: 3 | C14: Deciles 1–3 = Hot | K14: 19280 | L14: 0-1 Cars | M14: 31-40 | N14: 0-1 Miles | O14: 2 | P14: Partial College | Q14: Europe | R14: Married | S14: $100k+ | T14: 0.52070862 | U14: 77.821029 | V14: 249 | W14: 3 | X14: Hot | Y14: 1
A15: Warm tier: up to decile | B15: 6 | C15: Deciles 4–6 = Warm; 7–10 = Cold | K15: 22173 | L15: 2+ Cars | M15: 51-60 | N15: 1-2 Miles | O15: 3 | P15: High School | Q15: Pacific | R15: Married | S15: $10k-30k | T15: 0.45588745 | U15: 46.392256 | V15: 685 | W15: 7 | X15: Cold | Y15: 1
A16: Follow-up list size | B16: 25 | C16: Non-buyers shown in the priority follow-up list | K16: 12697 | L16: 2+ Cars | M16: 31-40 | N16: 10+ Miles | O16: 0 | P16: Bachelors | Q16: Pacific | R16: Single | S16: $70k-90k | T16: 0.48374382 | U16: 59.898516 | V16: 484 | W16: 5 | X16: Warm | Y16: 0
K17: 11434 | L17: 0-1 Cars | M17: 51-60 | N17: 0-1 Miles | O17: 5 | P17: Partial College | Q17: Europe | R17: Married | S17: $100k+ | T17: 0.46214785 | U17: 49.427636 | V17: 633 | W17: 7 | X17: Cold | Y17: 0
A18: Model weights | K18: 25323 | L18: 0-1 Cars | M18: 31-40 | N18: 1-2 Miles | O18: 2 | P18: Partial College | Q18: Europe | R18: Married | S18: $40k-60k | T18: 0.51142367 | U18: 73.319191 | V18: 310 | W18: 4 | X18: Warm | Y18: 1
A19: Factor | B19: Cramér's V | C19: Weight | K19: 23542 | L19: 0-1 Cars | M19: 41-50 | N19: 0-1 Miles | O19: 1 | P19: Partial College | Q19: Pacific | R19: Single | S19: $40k-60k | T19: 0.53511801 | U19: 84.807474 | V19: 147 | W19: 2 | X19: Hot | Y19: 1
A20: Car Ownership | B20: =_xlfn.XLOOKUP(tbl_Weights[[#This Row],[Factor]],tbl_Significance[Factor],tbl_Significance[Cramér''s V]) -> 0.22331278 | C20: =tbl_Weights[[#This Row],[Cramér''s V]]/SUM(tbl_Weights[Cramér''s V]) -> 0.17341704 | K20: 20870 | L20: 0-1 Cars | M20: 31-40 | N20: 0-1 Miles | O20: 2 | P20: High School | Q20: Europe | R20: Single | S20: $10k-30k | T20: 0.5224258 | U20: 78.653613 | V20: 238 | W20: 3 | X20: Hot | Y20: 1
A21: Age Band | B21: =_xlfn.XLOOKUP(tbl_Weights[[#This Row],[Factor]],tbl_Significance[Factor],tbl_Significance[Cramér''s V]) -> 0.20549751 | C21: =tbl_Weights[[#This Row],[Cramér''s V]]/SUM(tbl_Weights[Cramér''s V]) -> 0.15958231 | K21: 23316 | L21: 2+ Cars | M21: 51-60 | N21: 1-2 Miles | O21: 3 | P21: Partial College | Q21: Pacific | R21: Single | S21: $10k-30k | T21: 0.46651917 | U21: 51.547083 | V21: 603 | W21: 7 | X21: Cold | Y21: 1
A22: Commute Distance | B22: =_xlfn.XLOOKUP(tbl_Weights[[#This Row],[Factor]],tbl_Significance[Factor],tbl_Significance[Cramér''s V]) -> 0.18577338 | C22: =tbl_Weights[[#This Row],[Cramér''s V]]/SUM(tbl_Weights[Cramér''s V]) -> 0.14426523 | K22: 12610 | L22: 0-1 Cars | M22: 41-50 | N22: 0-1 Miles | O22: 1 | P22: Bachelors | Q22: Europe | R22: Married | S22: $10k-30k | T22: 0.51870348 | U22: 76.848832 | V22: 263 | W22: 3 | X22: Hot | Y22: 0
A23: Children | B23: =_xlfn.XLOOKUP(tbl_Weights[[#This Row],[Factor]],tbl_Significance[Factor],tbl_Significance[Cramér''s V]) -> 0.17903952 | C23: =tbl_Weights[[#This Row],[Cramér''s V]]/SUM(tbl_Weights[Cramér''s V]) -> 0.13903595 | K23: 27183 | L23: 0-1 Cars | M23: 31-40 | N23: 1-2 Miles | O23: 2 | P23: Partial College | Q23: Europe | R23: Single | S23: $40k-60k | T23: 0.52110172 | U23: 78.011625 | V23: 246 | W23: 3 | X23: Hot | Y23: 1
A24: Education | B24: =_xlfn.XLOOKUP(tbl_Weights[[#This Row],[Factor]],tbl_Significance[Factor],tbl_Significance[Cramér''s V]) -> 0.15916245 | C24: =tbl_Weights[[#This Row],[Cramér''s V]]/SUM(tbl_Weights[Cramér''s V]) -> 0.12360009 | K24: 25940 | L24: 2+ Cars | M24: 51-60 | N24: 5-10 Miles | O24: 2 | P24: Partial High School | Q24: Pacific | R24: Single | S24: $10k-30k | T24: 0.42370193 | U24: 30.786993 | V24: 860 | W24: 9 | X24: Cold | Y24: 1
A25: Region | B25: =_xlfn.XLOOKUP(tbl_Weights[[#This Row],[Factor]],tbl_Significance[Factor],tbl_Significance[Cramér''s V]) -> 0.11727057 | C25: =tbl_Weights[[#This Row],[Cramér''s V]]/SUM(tbl_Weights[Cramér''s V]) -> 0.0910683 | K25: 25598 | L25: 0-1 Cars | M25: 31-40 | N25: 0-1 Miles | O25: 0 | P25: Graduate Degree | Q25: Europe | R25: Married | S25: $40k-60k | T25: 0.54152736 | U25: 87.91507 | V25: 105 | W25: 2 | X25: Hot | Y25: 1
A26: Marital Status | B26: =_xlfn.XLOOKUP(tbl_Weights[[#This Row],[Factor]],tbl_Significance[Factor],tbl_Significance[Cramér''s V]) -> 0.11151483 | C26: =tbl_Weights[[#This Row],[Cramér''s V]]/SUM(tbl_Weights[Cramér''s V]) -> 0.086598588 | K26: 21564 | L26: 2+ Cars | M26: 31-40 | N26: 10+ Miles | O26: 0 | P26: Bachelors | Q26: Pacific | R26: Single | S26: $70k-90k | T26: 0.48374382 | U26: 59.898516 | V26: 489 | W26: 5 | X26: Warm | Y26: 0
A27: Income Band | B27: =_xlfn.XLOOKUP(tbl_Weights[[#This Row],[Factor]],tbl_Significance[Factor],tbl_Significance[Cramér''s V]) -> 0.10615007 | C27: =tbl_Weights[[#This Row],[Cramér''s V]]/SUM(tbl_Weights[Cramér''s V]) -> 0.082432502 | K27: 19193 | L27: 0-1 Cars | M27: 31-40 | N27: 1-2 Miles | O27: 2 | P27: Partial College | Q27: Europe | R27: Single | S27: $40k-60k | T27: 0.52110172 | U27: 78.011625 | V27: 245 | W27: 3 | X27: Hot | Y27: 1
A28: Total | B28: =SUBTOTAL(109,tbl_Weights[Cramér''s V]) -> 1.2877211 | C28: =SUBTOTAL(109,tbl_Weights[Weight]) -> 1 | K28: 26412 | L28: 2+ Cars | M28: 51-60 | N28: 5-10 Miles | O28: 5 | P28: High School | Q28: Europe | R28: Married | S28: $70k-90k | T28: 0.40160532 | U28: 20.073378 | V28: 965 | W28: 10 | X28: Cold | Y28: 0
K29: 27184 | L29: 0-1 Cars | M29: 31-40 | N29: 0-1 Miles | O29: 2 | P29: Partial College | Q29: Europe | R29: Single | S29: $40k-60k | T29: 0.53420486 | U29: 84.364731 | V29: 160 | W29: 2 | X29: Hot | Y29: 0
K30: 12590 | L30: 0-1 Cars | M30: 61+ | N30: 0-1 Miles | O30: 1 | P30: Bachelors | Q30: Europe | R30: Single | S30: $10k-30k | T30: 0.50182017 | U30: 68.6629 | V30: 360 | W30: 4 | X30: Warm | Y30: 0
A31: Tier summary | K31: 17841 | L31: 0-1 Cars | M31: 25-30 | N31: 0-1 Miles | O31: 0 | P31: Partial College | Q31: Europe | R31: Single | S31: $10k-30k | T31: 0.48822377 | U31: 62.070634 | V31: 459 | W31: 5 | X31: Warm | Y31: 1
A32: Tier | B32: Customers | C32: Buyers | D32: Purchase Rate | E32: Lift vs Avg | F32: Share of All Buyers | K32: 18283 | L32: 0-1 Cars | M32: 31-40 | N32: 5-10 Miles | O32: 0 | P32: Bachelors | Q32: Pacific | R32: Single | S32: $100k+ | T32: 0.53581952 | U32: 85.147604 | V32: 142 | W32: 2 | X32: Hot | Y32: 0
A33: Hot | B33: =COUNTIFS(_xlfn.ANCHORARRAY($X$5),tbl_TierSummary[[#This Row],[Tier]]) -> 300 | C33: =SUMIFS(_xlfn.ANCHORARRAY($Y$5),_xlfn.ANCHORARRAY($X$5),tbl_TierSummary[[#This Row],[Tier]]) -> 211 | D33: =tbl_TierSummary[[#This Row],[Buyers]]/tbl_TierSummary[[#This Row],[Customers]] -> 0.70333333 | E33: =tbl_TierSummary[[#This Row],[Purchase Rate]]/Baseline_Rate -> 1.4622315 | F33: =tbl_TierSummary[[#This Row],[Buyers]]/Total_Buyers -> 0.43866944 | K33: 18299 | L33: 2+ Cars | M33: 41-50 | N33: 5-10 Miles | O33: 5 | P33: Partial College | Q33: Pacific | R33: Married | S33: $70k-90k | T33: 0.41312809 | U33: 25.660232 | V33: 928 | W33: 10 | X33: Cold | Y33: 0
A34: Warm | B34: =COUNTIFS(_xlfn.ANCHORARRAY($X$5),tbl_TierSummary[[#This Row],[Tier]]) -> 300 | C34: =SUMIFS(_xlfn.ANCHORARRAY($Y$5),_xlfn.ANCHORARRAY($X$5),tbl_TierSummary[[#This Row],[Tier]]) -> 138 | D34: =tbl_TierSummary[[#This Row],[Buyers]]/tbl_TierSummary[[#This Row],[Customers]] -> 0.46 | E34: =tbl_TierSummary[[#This Row],[Purchase Rate]]/Baseline_Rate -> 0.95634096 | F34: =tbl_TierSummary[[#This Row],[Buyers]]/Total_Buyers -> 0.28690229 | K34: 16466 | L34: 2+ Cars | M34: 31-40 | N34: 0-1 Miles | O34: 0 | P34: Partial High School | Q34: Europe | R34: Single | S34: $10k-30k | T34: 0.46742045 | U34: 51.984072 | V34: 597 | W34: 6 | X34: Warm | Y34: 1
A35: Cold | B35: =COUNTIFS(_xlfn.ANCHORARRAY($X$5),tbl_TierSummary[[#This Row],[Tier]]) -> 400 | C35: =SUMIFS(_xlfn.ANCHORARRAY($Y$5),_xlfn.ANCHORARRAY($X$5),tbl_TierSummary[[#This Row],[Tier]]) -> 132 | D35: =tbl_TierSummary[[#This Row],[Buyers]]/tbl_TierSummary[[#This Row],[Customers]] -> 0.33 | E35: =tbl_TierSummary[[#This Row],[Purchase Rate]]/Baseline_Rate -> 0.68607069 | F35: =tbl_TierSummary[[#This Row],[Buyers]]/Total_Buyers -> 0.27442827 | K35: 19273 | L35: 0-1 Cars | M35: 61+ | N35: 0-1 Miles | O35: 2 | P35: Partial College | Q35: Europe | R35: Married | S35: $10k-30k | T35: 0.46410972 | U35: 50.378854 | V35: 617 | W35: 7 | X35: Cold | Y35: 0
K36: 22400 | L36: 0-1 Cars | M36: 25-30 | N36: 0-1 Miles | O36: 0 | P36: Partial College | Q36: Pacific | R36: Married | S36: $10k-30k | T36: 0.48721618 | U36: 61.582105 | V36: 467 | W36: 5 | X36: Warm | Y36: 1
K37: 20942 | L37: 0-1 Cars | M37: 31-40 | N37: 5-10 Miles | O37: 0 | P37: High School | Q37: Europe | R37: Single | S37: $10k-30k | T37: 0.50642885 | U37: 70.897431 | V37: 335 | W37: 4 | X37: Warm | Y37: 0
A38: Gains table (by score decile, 1 = highest scores) | K38: 18484 | L38: 2+ Cars | M38: 41-50 | N38: 1-2 Miles | O38: 2 | P38: High School | Q38: Pacific | R38: Single | S38: $70k-90k | T38: 0.46410955 | U38: 50.378773 | V38: 618 | W38: 7 | X38: Cold | Y38: 1
A39: Decile | B39: Customers | C39: Buyers | D39: Purchase Rate | E39: Lift vs Avg | F39: Cumulative Buyers | G39: % of All Buyers Captured | H39: Score Range (min–max) | K39: 12291 | L39: 2+ Cars | M39: 61+ | N39: 2-5 Miles | O39: 5 | P39: Partial College | Q39: Europe | R39: Single | S39: $70k-90k | T39: 0.41506932 | U39: 26.601442 | V39: 920 | W39: 10 | X39: Cold | Y39: 1
A40: 1 | B40: =COUNTIFS(_xlfn.ANCHORARRAY($W$5),tbl_Gains[[#This Row],[Decile]]) -> 100 | C40: =SUMIFS(_xlfn.ANCHORARRAY($Y$5),_xlfn.ANCHORARRAY($W$5),tbl_Gains[[#This Row],[Decile]]) -> 80 | D40: =tbl_Gains[[#This Row],[Buyers]]/tbl_Gains[[#This Row],[Customers]] -> 0.8 | E40: =tbl_Gains[[#This Row],[Purchase Rate]]/Baseline_Rate -> 1.6632017 | F40: =SUMIFS(_xlfn.ANCHORARRAY($Y$5),_xlfn.ANCHORARRAY($W$5),"<="&tbl_Gains[[#This Row],[Decile]]) -> 80 | G40: =tbl_Gains[[#This Row],[Cumulative Buyers]]/Total_Buyers -> 0.16632017 | H40: =TEXT(_xlfn.MINIFS(_xlfn.ANCHORARRAY($U$5),_xlfn.ANCHORARRAY($W$5),tbl_Gains[[#This Row],[Decile]]),"0.0")&" – "&TEXT(_xlfn.MAXIFS(_xlfn.ANCHORARRAY($U$5),_xlfn.ANCHORARRAY($W$5),tbl_Gains[[#This Row],[Decile]]),"0.0") -> 87.9 – 100.0 | K40: 28380 | L40: 2+ Cars | M40: 41-50 | N40: 0-1 Miles | O40: 5 | P40: Partial High School | Q40: Europe | R40: Single | S40: $10k-30k | T40: 0.4050268 | U40: 21.732292 | V40: 960 | W40: 10 | X40: Cold | Y40: 0
A41: 2 | B41: =COUNTIFS(_xlfn.ANCHORARRAY($W$5),tbl_Gains[[#This Row],[Decile]]) -> 100 | C41: =SUMIFS(_xlfn.ANCHORARRAY($Y$5),_xlfn.ANCHORARRAY($W$5),tbl_Gains[[#This Row],[Decile]]) -> 65 | D41: =tbl_Gains[[#This Row],[Buyers]]/tbl_Gains[[#This Row],[Customers]] -> 0.65 | E41: =tbl_Gains[[#This Row],[Purchase Rate]]/Baseline_Rate -> 1.3513514 | F41: =SUMIFS(_xlfn.ANCHORARRAY($Y$5),_xlfn.ANCHORARRAY($W$5),"<="&tbl_Gains[[#This Row],[Decile]]) -> 145 | G41: =tbl_Gains[[#This Row],[Cumulative Buyers]]/Total_Buyers -> 0.3014553 | H41: =TEXT(_xlfn.MINIFS(_xlfn.ANCHORARRAY($U$5),_xlfn.ANCHORARRAY($W$5),tbl_Gains[[#This Row],[Decile]]),"0.0")&" – "&TEXT(_xlfn.MAXIFS(_xlfn.ANCHORARRAY($U$5),_xlfn.ANCHORARRAY($W$5),tbl_Gains[[#This Row],[Decile]]),"0.0") -> 82.1 – 87.9 | K41: 17891 | L41: 0-1 Cars | M41: 41-50 | N41: 0-1 Miles | O41: 2 | P41: Partial College | Q41: Europe | R41: Married | S41: $10k-30k | T41: 0.49067107 | U41: 63.257219 | V41: 450 | W41: 5 | X41: Warm | Y41: 1
A42: 3 | B42: =COUNTIFS(_xlfn.ANCHORARRAY($W$5),tbl_Gains[[#This Row],[Decile]]) -> 100 | C42: =SUMIFS(_xlfn.ANCHORARRAY($Y$5),_xlfn.ANCHORARRAY($W$5),tbl_Gains[[#This Row],[Decile]]) -> 66 | D42: =tbl_Gains[[#This Row],[Buyers]]/tbl_Gains[[#This Row],[Customers]] -> 0.66 | E42: =tbl_Gains[[#This Row],[Purchase Rate]]/Baseline_Rate -> 1.3721414 | F42: =SUMIFS(_xlfn.ANCHORARRAY($Y$5),_xlfn.ANCHORARRAY($W$5),"<="&tbl_Gains[[#This Row],[Decile]]) -> 211 | G42: =tbl_Gains[[#This Row],[Cumulative Buyers]]/Total_Buyers -> 0.43866944 | H42: =TEXT(_xlfn.MINIFS(_xlfn.ANCHORARRAY($U$5),_xlfn.ANCHORARRAY($W$5),tbl_Gains[[#This Row],[Decile]]),"0.0")&" – "&TEXT(_xlfn.MAXIFS(_xlfn.ANCHORARRAY($U$5),_xlfn.ANCHORARRAY($W$5),tbl_Gains[[#This Row],[Decile]]),"0.0") -> 74.0 – 82.1 | K42: 27832 | L42: 0-1 Cars | M42: 25-30 | N42: 2-5 Miles | O42: 0 | P42: Partial College | Q42: Europe | R42: Single | S42: $10k-30k | T42: 0.49399029 | U42: 64.866552 | V42: 426 | W42: 5 | X42: Warm | Y42: 0
A43: 4 | B43: =COUNTIFS(_xlfn.ANCHORARRAY($W$5),tbl_Gains[[#This Row],[Decile]]) -> 100 | C43: =SUMIFS(_xlfn.ANCHORARRAY($Y$5),_xlfn.ANCHORARRAY($W$5),tbl_Gains[[#This Row],[Decile]]) -> 52 | D43: =tbl_Gains[[#This Row],[Buyers]]/tbl_Gains[[#This Row],[Customers]] -> 0.52 | E43: =tbl_Gains[[#This Row],[Purchase Rate]]/Baseline_Rate -> 1.0810811 | F43: =SUMIFS(_xlfn.ANCHORARRAY($Y$5),_xlfn.ANCHORARRAY($W$5),"<="&tbl_Gains[[#This Row],[Decile]]) -> 263 | G43: =tbl_Gains[[#This Row],[Cumulative Buyers]]/Total_Buyers -> 0.54677755 | H43: =TEXT(_xlfn.MINIFS(_xlfn.ANCHORARRAY($U$5),_xlfn.ANCHORARRAY($W$5),tbl_Gains[[#This Row],[Decile]]),"0.0")&" – "&TEXT(_xlfn.MAXIFS(_xlfn.ANCHORARRAY($U$5),_xlfn.ANCHORARRAY($W$5),tbl_Gains[[#This Row],[Decile]]),"0.0") -> 66.3 – 73.9 | K43: 26863 | L43: 0-1 Cars | M43: 25-30 | N43: 2-5 Miles | O43: 0 | P43: High School | Q43: Europe | R43: Single | S43: $10k-30k | T43: 0.49303661 | U43: 64.404159 | V43: 432 | W43: 5 | X43: Warm | Y43: 0
A44: 5 | B44: =COUNTIFS(_xlfn.ANCHORARRAY($W$5),tbl_Gains[[#This Row],[Decile]]) -> 100 | C44: =SUMIFS(_xlfn.ANCHORARRAY($Y$5),_xlfn.ANCHORARRAY($W$5),tbl_Gains[[#This Row],[Decile]]) -> 51 | D44: =tbl_Gains[[#This Row],[Buyers]]/tbl_Gains[[#This Row],[Customers]] -> 0.51 | E44: =tbl_Gains[[#This Row],[Purchase Rate]]/Baseline_Rate -> 1.0602911 | F44: =SUMIFS(_xlfn.ANCHORARRAY($Y$5),_xlfn.ANCHORARRAY($W$5),"<="&tbl_Gains[[#This Row],[Decile]]) -> 314 | G44: =tbl_Gains[[#This Row],[Cumulative Buyers]]/Total_Buyers -> 0.65280665 | H44: =TEXT(_xlfn.MINIFS(_xlfn.ANCHORARRAY($U$5),_xlfn.ANCHORARRAY($W$5),tbl_Gains[[#This Row],[Decile]]),"0.0")&" – "&TEXT(_xlfn.MAXIFS(_xlfn.ANCHORARRAY($U$5),_xlfn.ANCHORARRAY($W$5),tbl_Gains[[#This Row],[Decile]]),"0.0") -> 58.7 – 66.3 | K44: 16259 | L44: 2+ Cars | M44: 31-40 | N44: 0-1 Miles | O44: 4 | P44: Partial High School | Q44: Europe | R44: Single | S44: $10k-30k | T44: 0.45674712 | U44: 46.809073 | V44: 680 | W44: 7 | X44: Cold | Y44: 1
A45: 6 | B45: =COUNTIFS(_xlfn.ANCHORARRAY($W$5),tbl_Gains[[#This Row],[Decile]]) -> 100 | C45: =SUMIFS(_xlfn.ANCHORARRAY($Y$5),_xlfn.ANCHORARRAY($W$5),tbl_Gains[[#This Row],[Decile]]) -> 35 | D45: =tbl_Gains[[#This Row],[Buyers]]/tbl_Gains[[#This Row],[Customers]] -> 0.35 | E45: =tbl_Gains[[#This Row],[Purchase Rate]]/Baseline_Rate -> 0.72765073 | F45: =SUMIFS(_xlfn.ANCHORARRAY($Y$5),_xlfn.ANCHORARRAY($W$5),"<="&tbl_Gains[[#This Row],[Decile]]) -> 349 | G45: =tbl_Gains[[#This Row],[Cumulative Buyers]]/Total_Buyers -> 0.72557173 | H45: =TEXT(_xlfn.MINIFS(_xlfn.ANCHORARRAY($U$5),_xlfn.ANCHORARRAY($W$5),tbl_Gains[[#This Row],[Decile]]),"0.0")&" – "&TEXT(_xlfn.MAXIFS(_xlfn.ANCHORARRAY($U$5),_xlfn.ANCHORARRAY($W$5),tbl_Gains[[#This Row],[Decile]]),"0.0") -> 51.9 – 58.7 | K45: 27803 | L45: 0-1 Cars | M45: 41-50 | N45: 0-1 Miles | O45: 2 | P45: Partial College | Q45: Europe | R45: Single | S45: $10k-30k | T45: 0.50034911 | U45: 67.949652 | V45: 373 | W45: 4 | X45: Warm | Y45: 0
A46: 7 | B46: =COUNTIFS(_xlfn.ANCHORARRAY($W$5),tbl_Gains[[#This Row],[Decile]]) -> 100 | C46: =SUMIFS(_xlfn.ANCHORARRAY($Y$5),_xlfn.ANCHORARRAY($W$5),tbl_Gains[[#This Row],[Decile]]) -> 39 | D46: =tbl_Gains[[#This Row],[Buyers]]/tbl_Gains[[#This Row],[Customers]] -> 0.39 | E46: =tbl_Gains[[#This Row],[Purchase Rate]]/Baseline_Rate -> 0.81081081 | F46: =SUMIFS(_xlfn.ANCHORARRAY($Y$5),_xlfn.ANCHORARRAY($W$5),"<="&tbl_Gains[[#This Row],[Decile]]) -> 388 | G46: =tbl_Gains[[#This Row],[Cumulative Buyers]]/Total_Buyers -> 0.80665281 | H46: =TEXT(_xlfn.MINIFS(_xlfn.ANCHORARRAY($U$5),_xlfn.ANCHORARRAY($W$5),tbl_Gains[[#This Row],[Decile]]),"0.0")&" – "&TEXT(_xlfn.MAXIFS(_xlfn.ANCHORARRAY($U$5),_xlfn.ANCHORARRAY($W$5),tbl_Gains[[#This Row],[Decile]]),"0.0") -> 45.7 – 51.9 | K46: 14347 | L46: 2+ Cars | M46: 61+ | N46: 5-10 Miles | O46: 2 | P46: Bachelors | Q46: Pacific | R46: Single | S46: $40k-60k | T46: 0.44560104 | U46: 41.404857 | V46: 747 | W46: 8 | X46: Cold | Y46: 1
A47: 8 | B47: =COUNTIFS(_xlfn.ANCHORARRAY($W$5),tbl_Gains[[#This Row],[Decile]]) -> 100 | C47: =SUMIFS(_xlfn.ANCHORARRAY($Y$5),_xlfn.ANCHORARRAY($W$5),tbl_Gains[[#This Row],[Decile]]) -> 53 | D47: =tbl_Gains[[#This Row],[Buyers]]/tbl_Gains[[#This Row],[Customers]] -> 0.53 | E47: =tbl_Gains[[#This Row],[Purchase Rate]]/Baseline_Rate -> 1.1018711 | F47: =SUMIFS(_xlfn.ANCHORARRAY($Y$5),_xlfn.ANCHORARRAY($W$5),"<="&tbl_Gains[[#This Row],[Decile]]) -> 441 | G47: =tbl_Gains[[#This Row],[Cumulative Buyers]]/Total_Buyers -> 0.91683992 | H47: =TEXT(_xlfn.MINIFS(_xlfn.ANCHORARRAY($U$5),_xlfn.ANCHORARRAY($W$5),tbl_Gains[[#This Row],[Decile]]),"0.0")&" – "&TEXT(_xlfn.MAXIFS(_xlfn.ANCHORARRAY($U$5),_xlfn.ANCHORARRAY($W$5),tbl_Gains[[#This Row],[Decile]]),"0.0") -> 36.8 – 45.6 | K47: 17703 | L47: 0-1 Cars | M47: 31-40 | N47: 0-1 Miles | O47: 1 | P47: Graduate Degree | Q47: Europe | R47: Married | S47: $10k-30k | T47: 0.54024352 | U47: 87.292593 | V47: 112 | W47: 2 | X47: Hot | Y47: 0
A48: 9 | B48: =COUNTIFS(_xlfn.ANCHORARRAY($W$5),tbl_Gains[[#This Row],[Decile]]) -> 100 | C48: =SUMIFS(_xlfn.ANCHORARRAY($Y$5),_xlfn.ANCHORARRAY($W$5),tbl_Gains[[#This Row],[Decile]]) -> 21 | D48: =tbl_Gains[[#This Row],[Buyers]]/tbl_Gains[[#This Row],[Customers]] -> 0.21 | E48: =tbl_Gains[[#This Row],[Purchase Rate]]/Baseline_Rate -> 0.43659044 | F48: =SUMIFS(_xlfn.ANCHORARRAY($Y$5),_xlfn.ANCHORARRAY($W$5),"<="&tbl_Gains[[#This Row],[Decile]]) -> 462 | G48: =tbl_Gains[[#This Row],[Cumulative Buyers]]/Total_Buyers -> 0.96049896 | H48: =TEXT(_xlfn.MINIFS(_xlfn.ANCHORARRAY($U$5),_xlfn.ANCHORARRAY($W$5),tbl_Gains[[#This Row],[Decile]]),"0.0")&" – "&TEXT(_xlfn.MAXIFS(_xlfn.ANCHORARRAY($U$5),_xlfn.ANCHORARRAY($W$5),tbl_Gains[[#This Row],[Decile]]),"0.0") -> 28.4 – 36.7 | K48: 17185 | L48: 2+ Cars | M48: 41-50 | N48: 5-10 Miles | O48: 4 | P48: Partial College | Q48: Europe | R48: Married | S48: $100k+ | T48: 0.43229452 | U48: 34.953142 | V48: 824 | W48: 9 | X48: Cold | Y48: 1
A49: 10 | B49: =COUNTIFS(_xlfn.ANCHORARRAY($W$5),tbl_Gains[[#This Row],[Decile]]) -> 100 | C49: =SUMIFS(_xlfn.ANCHORARRAY($Y$5),_xlfn.ANCHORARRAY($W$5),tbl_Gains[[#This Row],[Decile]]) -> 19 | D49: =tbl_Gains[[#This Row],[Buyers]]/tbl_Gains[[#This Row],[Customers]] -> 0.19 | E49: =tbl_Gains[[#This Row],[Purchase Rate]]/Baseline_Rate -> 0.3950104 | F49: =SUMIFS(_xlfn.ANCHORARRAY($Y$5),_xlfn.ANCHORARRAY($W$5),"<="&tbl_Gains[[#This Row],[Decile]]) -> 481 | G49: =tbl_Gains[[#This Row],[Cumulative Buyers]]/Total_Buyers -> 1 | H49: =TEXT(_xlfn.MINIFS(_xlfn.ANCHORARRAY($U$5),_xlfn.ANCHORARRAY($W$5),tbl_Gains[[#This Row],[Decile]]),"0.0")&" – "&TEXT(_xlfn.MAXIFS(_xlfn.ANCHORARRAY($U$5),_xlfn.ANCHORARRAY($W$5),tbl_Gains[[#This Row],[Decile]]),"0.0") -> 0.0 – 28.3 | K49: 29380 | L49: 0-1 Cars | M49: 41-50 | N49: 0-1 Miles | O49: 3 | P49: High School | Q49: Europe | R49: Married | S49: $10k-30k | T49: 0.50093221 | U49: 68.23237 | V49: 367 | W49: 4 | X49: Warm | Y49: 1
K50: 23986 | L50: 0-1 Cars | M50: 61+ | N50: 0-1 Miles | O50: 1 | P50: Bachelors | Q50: Europe | R50: Married | S50: $10k-30k | T50: 0.49214213 | U50: 63.970467 | V50: 446 | W50: 5 | X50: Warm | Y50: 1
K51: 24466 | L51: 0-1 Cars | M51: 41-50 | N51: 5-10 Miles | O51: 1 | P51: Partial College | Q51: Pacific | R51: Married | S51: $40k-60k | T51: 0.50371149 | U51: 69.579914 | V51: 344 | W51: 4 | X51: Warm | Y51: 1
A52: Segment rates (lookup for scoring) | K52: 29097 | L52: 2+ Cars | M52: 51-60 | N52: 5-10 Miles | O52: 2 | P52: Partial College | Q52: Pacific | R52: Single | S52: $40k-60k | T52: 0.45750441 | U52: 47.176244 | V52: 670 | W52: 7 | X52: Cold | Y52: 1
A53: Key | B53: Factor | C53: Segment | D53: Customers | E53: Buyers | F53: Purchase Rate | K53: 19487 | L53: 2+ Cars | M53: 41-50 | N53: 0-1 Miles | O53: 2 | P53: Partial College | Q53: Europe | R53: Married | S53: $10k-30k | T53: 0.45195762 | U53: 44.486866 | V53: 719 | W53: 8 | X53: Cold | Y53: 0
A54: =tbl_SegmentRates[[#This Row],[Factor]]&"|"&tbl_SegmentRates[[#This Row],[Segment]] -> Car Ownership|0-1 Cars | B54: Car Ownership | C54: 0-1 Cars | D54: =COUNTIFS(INDEX(tbl_Clean[],0,MATCH(tbl_SegmentRates[[#This Row],[Factor]],tbl_Clean[#Headers],0)),tbl_SegmentRates[[#This Row],[Segment]]) -> 514 | E54: =COUNTIFS(INDEX(tbl_Clean[],0,MATCH(tbl_SegmentRates[[#This Row],[Factor]],tbl_Clean[#Headers],0)),tbl_SegmentRates[[#This Row],[Segment]],tbl_Clean[Purchased Flag],1) -> 303 | F54: =tbl_SegmentRates[[#This Row],[Buyers]]/tbl_SegmentRates[[#This Row],[Customers]] -> 0.58949416 | K54: 14939 | L54: 0-1 Cars | M54: 31-40 | N54: 0-1 Miles | O54: 0 | P54: Bachelors | Q54: Europe | R54: Single | S54: $40k-60k | T54: 0.55269573 | U54: 93.330096 | V54: 19 | W54: 1 | X54: Hot | Y54: 1
A55: =tbl_SegmentRates[[#This Row],[Factor]]&"|"&tbl_SegmentRates[[#This Row],[Segment]] -> Car Ownership|2+ Cars | B55: Car Ownership | C55: 2+ Cars | D55: =COUNTIFS(INDEX(tbl_Clean[],0,MATCH(tbl_SegmentRates[[#This Row],[Factor]],tbl_Clean[#Headers],0)),tbl_SegmentRates[[#This Row],[Segment]]) -> 486 | E55: =COUNTIFS(INDEX(tbl_Clean[],0,MATCH(tbl_SegmentRates[[#This Row],[Factor]],tbl_Clean[#Headers],0)),tbl_SegmentRates[[#This Row],[Segment]],tbl_Clean[Purchased Flag],1) -> 178 | F55: =tbl_SegmentRates[[#This Row],[Buyers]]/tbl_SegmentRates[[#This Row],[Customers]] -> 0.36625514 | K55: 13826 | L55: 0-1 Cars | M55: 25-30 | N55: 0-1 Miles | O55: 0 | P55: Partial College | Q55: Europe | R55: Single | S55: $10k-30k | T55: 0.48822377 | U55: 62.070634 | V55: 458 | W55: 5 | X55: Warm | Y55: 0
A56: =tbl_SegmentRates[[#This Row],[Factor]]&"|"&tbl_SegmentRates[[#This Row],[Segment]] -> Age Band|25-30 | B56: Age Band | C56: 25-30 | D56: =COUNTIFS(INDEX(tbl_Clean[],0,MATCH(tbl_SegmentRates[[#This Row],[Factor]],tbl_Clean[#Headers],0)),tbl_SegmentRates[[#This Row],[Segment]]) -> 110 | E56: =COUNTIFS(INDEX(tbl_Clean[],0,MATCH(tbl_SegmentRates[[#This Row],[Factor]],tbl_Clean[#Headers],0)),tbl_SegmentRates[[#This Row],[Segment]],tbl_Clean[Purchased Flag],1) -> 39 | F56: =tbl_SegmentRates[[#This Row],[Buyers]]/tbl_SegmentRates[[#This Row],[Customers]] -> 0.35454545 | K56: 20619 | L56: 2+ Cars | M56: 31-40 | N56: 10+ Miles | O56: 0 | P56: Bachelors | Q56: Pacific | R56: Single | S56: $70k-90k | T56: 0.48374382 | U56: 59.898516 | V56: 486 | W56: 5 | X56: Warm | Y56: 0
A57: =tbl_SegmentRates[[#This Row],[Factor]]&"|"&tbl_SegmentRates[[#This Row],[Segment]] -> Age Band|31-40 | B57: Age Band | C57: 31-40 | D57: =COUNTIFS(INDEX(tbl_Clean[],0,MATCH(tbl_SegmentRates[[#This Row],[Factor]],tbl_Clean[#Headers],0)),tbl_SegmentRates[[#This Row],[Segment]]) -> 316 | E57: =COUNTIFS(INDEX(tbl_Clean[],0,MATCH(tbl_SegmentRates[[#This Row],[Factor]],tbl_Clean[#Headers],0)),tbl_SegmentRates[[#This Row],[Segment]],tbl_Clean[Purchased Flag],1) -> 193 | F57: =tbl_SegmentRates[[#This Row],[Buyers]]/tbl_SegmentRates[[#This Row],[Customers]] -> 0.61075949 | K57: 12558 | L57: 0-1 Cars | M57: 61+ | N57: 0-1 Miles | O57: 1 | P57: Bachelors | Q57: Europe | R57: Married | S57: $10k-30k | T57: 0.49214213 | U57: 63.970467 | V57: 441 | W57: 5 | X57: Warm | Y57: 0
A58: =tbl_SegmentRates[[#This Row],[Factor]]&"|"&tbl_SegmentRates[[#This Row],[Segment]] -> Age Band|41-50 | B58: Age Band | C58: 41-50 | D58: =COUNTIFS(INDEX(tbl_Clean[],0,MATCH(tbl_SegmentRates[[#This Row],[Factor]],tbl_Clean[#Headers],0)),tbl_SegmentRates[[#This Row],[Segment]]) -> 298 | E58: =COUNTIFS(INDEX(tbl_Clean[],0,MATCH(tbl_SegmentRates[[#This Row],[Factor]],tbl_Clean[#Headers],0)),tbl_SegmentRates[[#This Row],[Segment]],tbl_Clean[Purchased Flag],1) -> 139 | F58: =tbl_SegmentRates[[#This Row],[Buyers]]/tbl_SegmentRates[[#This Row],[Customers]] -> 0.46644295 | K58: 24871 | L58: 2+ Cars | M58: 51-60 | N58: 5-10 Miles | O58: 4 | P58: High School | Q58: Europe | R58: Single | S58: $70k-90k | T58: 0.43997332 | U58: 38.676238 | V58: 790 | W58: 8 | X58: Cold | Y58: 0
A59: =tbl_SegmentRates[[#This Row],[Factor]]&"|"&tbl_SegmentRates[[#This Row],[Segment]] -> Age Band|51-60 | B59: Age Band | C59: 51-60 | D59: =COUNTIFS(INDEX(tbl_Clean[],0,MATCH(tbl_SegmentRates[[#This Row],[Factor]],tbl_Clean[#Headers],0)),tbl_SegmentRates[[#This Row],[Segment]]) -> 176 | E59: =COUNTIFS(INDEX(tbl_Clean[],0,MATCH(tbl_SegmentRates[[#This Row],[Factor]],tbl_Clean[#Headers],0)),tbl_SegmentRates[[#This Row],[Segment]],tbl_Clean[Purchased Flag],1) -> 80 | F59: =tbl_SegmentRates[[#This Row],[Buyers]]/tbl_SegmentRates[[#This Row],[Customers]] -> 0.45454545 | K59: 17319 | L59: 0-1 Cars | M59: 41-50 | N59: 5-10 Miles | O59: 0 | P59: Bachelors | Q59: Pacific | R59: Single | S59: $70k-90k | T59: 0.51364222 | U59: 74.394863 | V59: 289 | W59: 3 | X59: Hot | Y59: 0
A60: =tbl_SegmentRates[[#This Row],[Factor]]&"|"&tbl_SegmentRates[[#This Row],[Segment]] -> Age Band|61+ | B60: Age Band | C60: 61+ | D60: =COUNTIFS(INDEX(tbl_Clean[],0,MATCH(tbl_SegmentRates[[#This Row],[Factor]],tbl_Clean[#Headers],0)),tbl_SegmentRates[[#This Row],[Segment]]) -> 100 | E60: =COUNTIFS(INDEX(tbl_Clean[],0,MATCH(tbl_SegmentRates[[#This Row],[Factor]],tbl_Clean[#Headers],0)),tbl_SegmentRates[[#This Row],[Segment]],tbl_Clean[Purchased Flag],1) -> 30 | F60: =tbl_SegmentRates[[#This Row],[Buyers]]/tbl_SegmentRates[[#This Row],[Customers]] -> 0.3 | K60: 28906 | L60: 2+ Cars | M60: 51-60 | N60: 10+ Miles | O60: 4 | P60: High School | Q60: Europe | R60: Married | S60: $70k-90k | T60: 0.41607996 | U60: 27.091455 | V60: 917 | W60: 10 | X60: Cold | Y60: 0
A61: =tbl_SegmentRates[[#This Row],[Factor]]&"|"&tbl_SegmentRates[[#This Row],[Segment]] -> Commute Distance|0-1 Miles | B61: Commute Distance | C61: 0-1 Miles | D61: =COUNTIFS(INDEX(tbl_Clean[],0,MATCH(tbl_SegmentRates[[#This Row],[Factor]],tbl_Clean[#Headers],0)),tbl_SegmentRates[[#This Row],[Segment]]) -> 366 | E61: =COUNTIFS(INDEX(tbl_Clean[],0,MATCH(tbl_SegmentRates[[#This Row],[Factor]],tbl_Clean[#Headers],0)),tbl_SegmentRates[[#This Row],[Segment]],tbl_Clean[Purchased Flag],1) -> 200 | F61: =tbl_SegmentRates[[#This Row],[Buyers]]/tbl_SegmentRates[[#This Row],[Customers]] -> 0.54644809 | K61: 12808 | L61: 0-1 Cars | M61: 31-40 | N61: 0-1 Miles | O61: 0 | P61: Bachelors | Q61: Europe | R61: Married | S61: $40k-60k | T61: 0.54301769 | U61: 88.637662 | V61: 82 | W61: 1 | X61: Hot | Y61: 1
A62: =tbl_SegmentRates[[#This Row],[Factor]]&"|"&tbl_SegmentRates[[#This Row],[Segment]] -> Commute Distance|1-2 Miles | B62: Commute Distance | C62: 1-2 Miles | D62: =COUNTIFS(INDEX(tbl_Clean[],0,MATCH(tbl_SegmentRates[[#This Row],[Factor]],tbl_Clean[#Headers],0)),tbl_SegmentRates[[#This Row],[Segment]]) -> 169 | E62: =COUNTIFS(INDEX(tbl_Clean[],0,MATCH(tbl_SegmentRates[[#This Row],[Factor]],tbl_Clean[#Headers],0)),tbl_SegmentRates[[#This Row],[Segment]],tbl_Clean[Purchased Flag],1) -> 77 | F62: =tbl_SegmentRates[[#This Row],[Buyers]]/tbl_SegmentRates[[#This Row],[Customers]] -> 0.4556213 | K62: 20567 | L62: 2+ Cars | M62: 61+ | N62: 5-10 Miles | O62: 4 | P62: Partial College | Q62: Europe | R62: Married | S62: $100k+ | T62: 0.40573317 | U62: 22.074777 | V62: 955 | W62: 10 | X62: Cold | Y62: 1
A63: =tbl_SegmentRates[[#This Row],[Factor]]&"|"&tbl_SegmentRates[[#This Row],[Segment]] -> Commute Distance|2-5 Miles | B63: Commute Distance | C63: 2-5 Miles | D63: =COUNTIFS(INDEX(tbl_Clean[],0,MATCH(tbl_SegmentRates[[#This Row],[Factor]],tbl_Clean[#Headers],0)),tbl_SegmentRates[[#This Row],[Segment]]) -> 162 | E63: =COUNTIFS(INDEX(tbl_Clean[],0,MATCH(tbl_SegmentRates[[#This Row],[Factor]],tbl_Clean[#Headers],0)),tbl_SegmentRates[[#This Row],[Segment]],tbl_Clean[Purchased Flag],1) -> 95 | F63: =tbl_SegmentRates[[#This Row],[Buyers]]/tbl_SegmentRates[[#This Row],[Customers]] -> 0.58641975 | K63: 25502 | L63: 0-1 Cars | M63: 41-50 | N63: 0-1 Miles | O63: 1 | P63: Bachelors | Q63: Europe | R63: Married | S63: $40k-60k | T63: 0.52952886 | U63: 82.097557 | V63: 201 | W63: 3 | X63: Hot | Y63: 1
A64: =tbl_SegmentRates[[#This Row],[Factor]]&"|"&tbl_SegmentRates[[#This Row],[Segment]] -> Commute Distance|5-10 Miles | B64: Commute Distance | C64: 5-10 Miles | D64: =COUNTIFS(INDEX(tbl_Clean[],0,MATCH(tbl_SegmentRates[[#This Row],[Factor]],tbl_Clean[#Headers],0)),tbl_SegmentRates[[#This Row],[Segment]]) -> 192 | E64: =COUNTIFS(INDEX(tbl_Clean[],0,MATCH(tbl_SegmentRates[[#This Row],[Factor]],tbl_Clean[#Headers],0)),tbl_SegmentRates[[#This Row],[Segment]],tbl_Clean[Purchased Flag],1) -> 76 | F64: =tbl_SegmentRates[[#This Row],[Buyers]]/tbl_SegmentRates[[#This Row],[Customers]] -> 0.39583333 | K64: 15580 | L64: 0-1 Cars | M64: 31-40 | N64: 2-5 Miles | O64: 2 | P64: Bachelors | Q64: Pacific | R64: Married | S64: $40k-60k | T64: 0.55172316 | U64: 92.85854 | V64: 30 | W64: 1 | X64: Hot | Y64: 1
A65: =tbl_SegmentRates[[#This Row],[Factor]]&"|"&tbl_SegmentRates[[#This Row],[Segment]] -> Commute Distance|10+ Miles | B65: Commute Distance | C65: 10+ Miles | D65: =COUNTIFS(INDEX(tbl_Clean[],0,MATCH(tbl_SegmentRates[[#This Row],[Factor]],tbl_Clean[#Headers],0)),tbl_SegmentRates[[#This Row],[Segment]]) -> 111 | E65: =COUNTIFS(INDEX(tbl_Clean[],0,MATCH(tbl_SegmentRates[[#This Row],[Factor]],tbl_Clean[#Headers],0)),tbl_SegmentRates[[#This Row],[Segment]],tbl_Clean[Purchased Flag],1) -> 33 | F65: =tbl_SegmentRates[[#This Row],[Buyers]]/tbl_SegmentRates[[#This Row],[Customers]] -> 0.2972973 | K65: 24185 | L65: 0-1 Cars | M65: 41-50 | N65: 1-2 Miles | O65: 1 | P65: High School | Q65: Europe | R65: Single | S65: $10k-30k | T65: 0.50156534 | U65: 68.539345 | V65: 364 | W65: 4 | X65: Warm | Y65: 0
... A85: =tbl_SegmentRates[[#This Row],[Factor]]&"|"&tbl_SegmentRates[[#This Row],[Segment]] -> Income Band|$100k+ | B85: Income Band | C85: $100k+ | D85: =COUNTIFS(INDEX(tbl_Clean[],0,MATCH(tbl_SegmentRates[[#This Row],[Factor]],tbl_Clean[#Headers],0)),tbl_SegmentRates[[#This Row],[Segment]]) -> 105 | E85: =COUNTIFS(INDEX(tbl_Clean[],0,MATCH(tbl_SegmentRates[[#This Row],[Factor]],tbl_Clean[#Headers],0)),tbl_SegmentRates[[#This Row],[Segment]],tbl_Clean[Purchased Flag],1) -> 51 | F85: =tbl_SegmentRates[[#This Row],[Buyers]]/tbl_SegmentRates[[#This Row],[Customers]] -> 0.48571429 | K85: 20828 | L85: 0-1 Cars | M85: 41-50 | N85: 0-1 Miles | O85: 4 | P85: Graduate Degree | Q85: Europe | R85: Married | S85: $10k-30k | T85: 0.49699829 | U85: 66.324991 | V85: 398 | W85: 4 | X85: Warm | Y85: 1
K86: 19461 | L86: 2+ Cars | M86: 31-40 | N86: 0-1 Miles | O86: 4 | P86: Partial High School | Q86: Europe | R86: Single | S86: $10k-30k | T86: 0.45674712 | U86: 46.809073 | V86: 681 | W86: 7 | X86: Cold | Y86: 0
A87: Segment check: | B87: =_xlfn.LET(_xlpm.expected,ROWS(_xlfn.UNIQUE(tbl_Clean[Car Ownership]))+ROWS(_xlfn.UNIQUE(tbl_Clean[Age Band]))+ROWS(_xlfn.UNIQUE(tbl_Clean[Commute Distance]))+ROWS(_xlfn.UNIQUE(tbl_Clean[Children]))+ROWS(_xlfn.UNIQUE(tbl_Clean[Education]))+ROWS(_xlfn.UNIQUE(tbl_Clean[Region]))+ROWS(_xlfn.UNIQUE(tbl_Clean[Marital Status]))+ROWS(_xlfn.UNIQUE(tbl_Clean[Income Band])),_xlpm.listed,ROWS(tbl_SegmentRates[]),_xlpm.covered,SUM(tbl_SegmentRates[Customers])=ROWS(tbl_Weights[])*ROWS(tbl_Clean[]),IF(AND(_xlpm.expected=_xlpm.listed,_xlpm.covered),"OK: "&_xlpm.listed&" segments listed, every customer covered on all "&ROWS(tbl_Weights[])&" factors","WARNING: tbl_Clean has "&_xlpm.expected&" segments but this table lists "&_xlpm.listed&"; update tbl_SegmentRates")) -> OK: 32 segments listed, every customer covered on all 8 factors | K87: 26941 | L87: 0-1 Cars | M87: 41-50 | N87: 0-1 Miles | O87: 0 | P87: Bachelors | Q87: Europe | R87: Married | S87: $10k-30k | T87: 0.50916194 | U87: 72.222583 | V87: 323 | W87: 4 | X87: Warm | Y87: 1
K88: 28412 | L88: 0-1 Cars | M88: 25-30 | N88: 2-5 Miles | O88: 0 | P88: High School | Q88: Europe | R88: Single | S88: $10k-30k | T88: 0.49303661 | U88: 64.404159 | V88: 434 | W88: 5 | X88: Warm | Y88: 0
K89: 24485 | L89: 0-1 Cars | M89: 51-60 | N89: 5-10 Miles | O89: 2 | P89: Bachelors | Q89: Pacific | R89: Single | S89: $40k-60k | T89: 0.50897721 | U89: 72.133017 | V89: 327 | W89: 4 | X89: Warm | Y89: 1
A90: ="Priority follow-up list (top "&FollowUp_Size&" non-buyers by lead score)" -> Priority follow-up list (top 25 non-buyers by lead score) | K90: 16514 | L90: 0-1 Cars | M90: 25-30 | N90: 1-2 Miles | O90: 0 | P90: Partial College | Q90: Pacific | R90: Single | S90: $10k-30k | T90: 0.48379108 | U90: 59.921431 | V90: 479 | W90: 5 | X90: Warm | Y90: 1
A91: ID | B91: Lead score | C91: Tier | D91: Age Band | E91: Car Ownership | F91: Commute Distance | G91: Region | K91: 17191 | L91: 2+ Cars | M91: 51-60 | N91: 0-1 Miles | O91: 3 | P91: Partial College | Q91: Europe | R91: Single | S91: $100k+ | T91: 0.47795903 | U91: 57.093742 | V91: 522 | W91: 6 | X91: Warm | Y91: 1
A92: {=_xlfn.LET(_xlpm.d,_xlfn.HSTACK(_xlfn.ANCHORARRAY(K5),_xlfn.ANCHORARRAY(U5),_xlfn.ANCHORARRAY(X5),_xlfn.ANCHORARRAY(M5),_xlfn.ANCHORARRAY(L5),_xlfn.ANCHORARRAY(N5),_xlfn.ANCHORARRAY(Q5),_xlfn.ANCHORARRAY(V5)),_xlpm.f,_xlfn._xlws.FILTER(_xlpm.d,_xlfn.ANCHORARRAY(Y5)=0),_xlfn.TAKE(_xlfn.DROP(_xlfn.SORTBY(_xlpm.f,_xlfn.TAKE(_xlpm.f,,-1),1),,-1),FollowUp_Size))} -> 11788 | B92: 95.931138 | C92: Hot | D92: 31-40 | E92: 0-1 Cars | F92: 2-5 Miles | G92: North America | K92: 19608 | L92: 2+ Cars | M92: 31-40 | N92: 1-2 Miles | O92: 5 | P92: Bachelors | Q92: Pacific | R92: Married | S92: $70k-90k | T92: 0.45754314 | U92: 47.195026 | V92: 668 | W92: 7 | X92: Cold | Y92: 0
A93: 28858 | B93: 94.686082 | C93: Hot | D93: 31-40 | E93: 0-1 Cars | F93: 2-5 Miles | G93: North America | K93: 24119 | L93: 0-1 Cars | M93: 25-30 | N93: 2-5 Miles | O93: 0 | P93: Partial College | Q93: Europe | R93: Single | S93: $10k-30k | T93: 0.49399029 | U93: 64.866552 | V93: 425 | W93: 5 | X93: Warm | Y93: 0
A94: 27756 | B94: 93.327819 | C94: Hot | D94: 31-40 | E94: 0-1 Cars | F94: 0-1 Miles | G94: North America | K94: 25458 | L94: 0-1 Cars | M94: 31-40 | N94: 1-2 Miles | O94: 1 | P94: High School | Q94: Europe | R94: Married | S94: $10k-30k | T94: 0.51491767 | U94: 75.013266 | V94: 283 | W94: 3 | X94: Hot | Y94: 1
A95: 12993 | B95: 92.85854 | C95: Hot | D95: 31-40 | E95: 0-1 Cars | F95: 2-5 Miles | G95: Pacific | K95: 26886 | L95: 0-1 Cars | M95: 25-30 | N95: 0-1 Miles | O95: 0 | P95: Partial College | Q95: Europe | R95: Single | S95: $10k-30k | T95: 0.48822377 | U95: 62.070634 | V95: 461 | W95: 5 | X95: Warm | Y95: 1
A96: 11801 | B96: 92.67636 | C96: Hot | D96: 31-40 | E96: 0-1 Cars | F96: 2-5 Miles | G96: North America | K96: 28436 | L96: 0-1 Cars | M96: 25-30 | N96: 0-1 Miles | O96: 0 | P96: Partial College | Q96: Europe | R96: Single | S96: $10k-30k | T96: 0.48822377 | U96: 62.070634 | V96: 462 | W96: 5 | X96: Warm | Y96: 1
A97: 12472 | B97: 90.811105 | C97: Hot | D97: 31-40 | E97: 0-1 Cars | F97: 2-5 Miles | G97: Europe | K97: 19562 | L97: 0-1 Cars | M97: 31-40 | N97: 2-5 Miles | O97: 2 | P97: Bachelors | Q97: Pacific | R97: Single | S97: $40k-60k | T97: 0.5614012 | U97: 97.550973 | V97: 5 | W97: 1 | X97: Hot | Y97: 1
A98: 11644 | B98: 90.686193 | C98: Hot | D98: 31-40 | E98: 0-1 Cars | F98: 2-5 Miles | G98: North America | K98: 15608 | L98: 0-1 Cars | M98: 31-40 | N98: 2-5 Miles | O98: 0 | P98: Partial College | Q98: Europe | R98: Single | S98: $10k-30k | T98: 0.53487751 | U98: 84.690869 | V98: 151 | W98: 2 | X98: Hot | Y98: 0
A99: 11641 | B99: 90.603035 | C99: Hot | D99: 31-40 | E99: 0-1 Cars | F99: 0-1 Miles | G99: North America | K99: 16487 | L99: 2+ Cars | M99: 51-60 | N99: 5-10 Miles | O99: 3 | P99: High School | Q99: Pacific | R99: Single | S99: $10k-30k | T99: 0.45694017 | U99: 46.90267 | V99: 678 | W99: 7 | X99: Cold | Y99: 0
A100: 15468 | B100: 90.603035 | C100: Hot | D100: 31-40 | E100: 0-1 Cars | F100: 0-1 Miles | G100: North America | K100: 17197 | L100: 2+ Cars | M100: 61+ | N100: 10+ Miles | O100: 5 | P100: Partial College | Q100: Europe | R100: Single | S100: $70k-90k | T100: 0.373359 | U100: 6.3780477 | V100: 996 | W100: 10 | X100: Cold | Y100: 0
A101: 16217 | B101: 89.946626 | C101: Hot | D101: 31-40 | E101: 0-1 Cars | F101: 0-1 Miles | G101: North America | K101: 12507 | L101: 0-1 Cars | M101: 41-50 | N101: 0-1 Miles | O101: 1 | P101: Partial College | Q101: Europe | R101: Married | S101: $10k-30k | T101: 0.50594412 | U101: 70.662412 | V101: 336 | W101: 4 | X101: Warm | Y101: 0
A102: 21693 | B102: 89.946626 | C102: Hot | D102: 31-40 | E102: 0-1 Cars | F102: 0-1 Miles | G102: North America | K102: 23940 | L102: 0-1 Cars | M102: 41-50 | N102: 0-1 Miles | O102: 1 | P102: Bachelors | Q102: Europe | R102: Married | S102: $40k-60k | T102: 0.52952886 | U102: 82.097557 | V102: 200 | W102: 2 | X102: Hot | Y102: 1
A103: 11783 | B103: 89.880442 | C103: Hot | D103: 31-40 | E103: 0-1 Cars | F103: 0-1 Miles | G103: North America | K103: 19441 | L103: 0-1 Cars | M103: 25-30 | N103: 0-1 Miles | O103: 0 | P103: Graduate Degree | Q103: Europe | R103: Married | S103: $40k-60k | T103: 0.50064013 | U103: 68.090753 | V103: 370 | W103: 4 | X103: Warm | Y103: 1
A104: 14569 | B104: 89.880442 | C104: Hot | D104: 31-40 | E104: 0-1 Cars | F104: 0-1 Miles | G104: North America | K104: 26852 | L104: 2+ Cars | M104: 41-50 | N104: 0-1 Miles | O104: 3 | P104: High School | Q104: Europe | R104: Married | S104: $10k-30k | T104: 0.46221876 | U104: 49.462017 | V104: 626 | W104: 7 | X104: Cold | Y104: 0
... A116: 14785 | B116: 86.354512 | C116: Hot | D116: 31-40 | E116: 0-1 Cars | F116: 1-2 Miles | G116: Europe | K116: 14682 | L116: 0-1 Cars | M116: 31-40 | N116: 5-10 Miles | O116: 0 | P116: Bachelors | Q116: Pacific | R116: Single | S116: $70k-90k | T116: 0.53667259 | U116: 85.561218 | V116: 130 | W116: 2 | X116: Hot | Y116: 0
K117: 17650 | L117: 2+ Cars | M117: 31-40 | N117: 1-2 Miles | O117: 2 | P117: Partial College | Q117: Europe | R117: Single | S117: $40k-60k | T117: 0.48238827 | U117: 59.241272 | V117: 496 | W117: 5 | X117: Warm | Y117: 0
K118: 29191 | L118: 0-1 Cars | M118: 31-40 | N118: 0-1 Miles | O118: 1 | P118: Graduate Degree | Q118: Pacific | R118: Single | S118: $100k+ | T118: 0.5655992 | U118: 99.586386 | V118: 2 | W118: 1 | X118: Hot | Y118: 1
K119: 15030 | L119: 0-1 Cars | M119: 25-30 | N119: 0-1 Miles | O119: 0 | P119: Bachelors | Q119: Pacific | R119: Married | S119: $10k-30k | T119: 0.49997554 | U119: 67.768524 | V119: 374 | W119: 4 | X119: Warm | Y119: 1
K120: 24140 | L120: 0-1 Cars | M120: 25-30 | N120: 0-1 Miles | O120: 0 | P120: Graduate Degree | Q120: Europe | R120: Single | S120: $10k-30k | T120: 0.49949279 | U120: 67.534461 | V120: 378 | W120: 4 | X120: Warm | Y120: 1
K121: 22496 | L121: 2+ Cars | M121: 41-50 | N121: 0-1 Miles | O121: 1 | P121: Bachelors | Q121: Europe | R121: Married | S121: $10k-30k | T121: 0.47999003 | U121: 58.078479 | V121: 516 | W121: 6 | X121: Warm | Y121: 0
K122: 24065 | L122: 0-1 Cars | M122: 31-40 | N122: 0-1 Miles | O122: 0 | P122: High School | Q122: Europe | R122: Single | S122: $10k-30k | T122: 0.52815732 | U122: 81.432557 | V122: 209 | W122: 3 | X122: Hot | Y122: 1
K123: 19914 | L123: 2+ Cars | M123: 61+ | N123: 2-5 Miles | O123: 5 | P123: Bachelors | Q123: Europe | R123: Married | S123: $70k-90k | T123: 0.41815063 | U123: 28.095428 | V123: 906 | W123: 10 | X123: Cold | Y123: 0
K124: 12871 | L124: 0-1 Cars | M124: 25-30 | N124: 2-5 Miles | O124: 0 | P124: Partial College | Q124: Europe | R124: Single | S124: $10k-30k | T124: 0.49399029 | U124: 64.866552 | V124: 420 | W124: 5 | X124: Warm | Y124: 0
K125: 22988 | L125: 2+ Cars | M125: 61+ | N125: 5-10 Miles | O125: 2 | P125: Bachelors | Q125: Pacific | R125: Married | S125: $40k-60k | T125: 0.435923 | U125: 36.712424 | V125: 801 | W125: 9 | X125: Cold | Y125: 1
K126: 15922 | L126: 2+ Cars | M126: 41-50 | N126: 0-1 Miles | O126: 2 | P126: High School | Q126: Europe | R126: Married | S126: $100k+ | T126: 0.45801113 | U126: 47.421929 | V126: 660 | W126: 7 | X126: Cold | Y126: 0
K127: 12344 | L127: 2+ Cars | M127: 31-40 | N127: 10+ Miles | O127: 0 | P127: Bachelors | Q127: Pacific | R127: Single | S127: $70k-90k | T127: 0.48374382 | U127: 59.898516 | V127: 483 | W127: 5 | X127: Warm | Y127: 0
K128: 23627 | L128: 2+ Cars | M128: 51-60 | N128: 5-10 Miles | O128: 3 | P128: Partial College | Q128: Europe | R128: Single | S128: $100k+ | T128: 0.45623056 | U128: 46.558616 | V128: 683 | W128: 7 | X128: Cold | Y128: 0
... K1004: 12121 | L1004: 2+ Cars | M1004: 51-60 | N1004: 10+ Miles | O1004: 3 | P1004: High School | Q1004: North America | R1004: Single | S1004: $40k-60k | T1004: 0.43939176 | U1004: 38.394266 | V1004: 792 | W1004: 8 | X1004: Cold | Y1004: 1

Sheet Profile_Checker
A1: Profile checker: what drives a customer profile's purchase rate
A2: ="Purpose: pick a customer profile and see how each factor pushes its expected purchase rate above or below the "&TEXT(Baseline_Rate,"0.0%")&" average." -> Purpose: pick a customer profile and see how each factor pushes its expected purchase rate above or below the 48.1% average.
A4: Choose a value for each factor (or (Any) to ignore it). Results update instantly.
L5: Dropdown lists (helper, live from tbl_SegmentRates; do not edit)
A6: Inputs | H6: Results
A7: Factor | B7: Selection | H7: Raw score | I7: =Baseline_Rate+tbl_ProfileBreakdown[[#Totals],[Contribution (pp)]]/100 -> 0.52052206 | L7: {=TRANSPOSE($A$8:$A$15)} -> Car Ownership | M7: Age Band | N7: Commute Distance | O7: Children | P7: Education | Q7: Region | R7: Marital Status | S7: Income Band
A8: Car Ownership | B8: 0-1 Cars | H8: Lead score (0-100) | I8: =MAX(0,MIN(100,(I7-I13)/(I14-I13)*100)) -> 77.730574 | L8: {=_xlfn.VSTACK("(Any)",_xlfn._xlws.FILTER(tbl_SegmentRates[Segment],tbl_SegmentRates[Factor]=L$7))} -> (Any) | M8: {=_xlfn.VSTACK("(Any)",_xlfn._xlws.FILTER(tbl_SegmentRates[Segment],tbl_SegmentRates[Factor]=M$7))} -> (Any) | N8: {=_xlfn.VSTACK("(Any)",_xlfn._xlws.FILTER(tbl_SegmentRates[Segment],tbl_SegmentRates[Factor]=N$7))} -> (Any) | O8: {=_xlfn.VSTACK("(Any)",_xlfn._xlws.FILTER(tbl_SegmentRates[Segment],tbl_SegmentRates[Factor]=O$7))} -> (Any) | P8: {=_xlfn.VSTACK("(Any)",_xlfn._xlws.FILTER(tbl_SegmentRates[Segment],tbl_SegmentRates[Factor]=P$7))} -> (Any) | Q8: {=_xlfn.VSTACK("(Any)",_xlfn._xlws.FILTER(tbl_SegmentRates[Segment],tbl_SegmentRates[Factor]=Q$7))} -> (Any) | R8: {=_xlfn.VSTACK("(Any)",_xlfn._xlws.FILTER(tbl_SegmentRates[Segment],tbl_SegmentRates[Factor]=R$7))} -> (Any) | S8: {=_xlfn.VSTACK("(Any)",_xlfn._xlws.FILTER(tbl_SegmentRates[Segment],tbl_SegmentRates[Factor]=S$7))} -> (Any)
A9: Age Band | B9: 31-40 | H9: Tier | I9: =IF(I8>=I15,"Hot",IF(I8>=I16,"Warm","Cold")) -> Hot | L9: 0-1 Cars | M9: 25-30 | N9: 0-1 Miles | O9: 0 | P9: Partial High School | Q9: Pacific | R9: Single | S9: $10k-30k
A10: Commute Distance | B10: (Any) | H10: Estimated purchase likelihood | I10: =_xlfn.XLOOKUP(I9,tbl_TierSummary[Tier],tbl_TierSummary[Purchase Rate]) -> 0.70333333 | L10: 2+ Cars | M10: 31-40 | N10: 1-2 Miles | O10: 1 | P10: High School | Q10: Europe | R10: Married | S10: $40k-60k
A11: Children | B11: (Any) | H11: Lift vs average | I11: =I10/Baseline_Rate -> 1.4622315 | M11: 41-50 | N11: 2-5 Miles | O11: 2 | P11: Partial College | Q11: North America | S11: $70k-90k
A12: Education | B12: (Any) | H12: Workings (live from Lead_Scoring) | M12: 51-60 | N12: 5-10 Miles | O12: 3 | P12: Bachelors | S12: $100k+
A13: Region | B13: (Any) | H13: Raw score min (all customers) | I13: =MIN(_xlfn.ANCHORARRAY(Lead_Scoring!$T$5)) -> 0.36020441 | M13: 61+ | N13: 10+ Miles | O13: 4 | P13: Graduate Degree
A14: Marital Status | B14: (Any) | H14: Raw score max (all customers) | I14: =MAX(_xlfn.ANCHORARRAY(Lead_Scoring!$T$5)) -> 0.56645227 | O14: 5
A15: Income Band | B15: (Any) | H15: ="Hot cut-off: min lead score of decile "&Hot_Cutoff -> Hot cut-off: min lead score of decile 3 | I15: =_xlfn.MINIFS(_xlfn.ANCHORARRAY(Lead_Scoring!$U$5),_xlfn.ANCHORARRAY(Lead_Scoring!$W$5),Hot_Cutoff) -> 73.96118
H16: ="Warm cut-off: min lead score of decile "&Warm_Cutoff -> Warm cut-off: min lead score of decile 6 | I16: =_xlfn.MINIFS(_xlfn.ANCHORARRAY(Lead_Scoring!$U$5),_xlfn.ANCHORARRAY(Lead_Scoring!$W$5),Warm_Cutoff) -> 51.938916
A18: Why this score | H18: Real customers like this
A19: Factor | B19: Selected | C19: Segment Purchase Rate | D19: Lift vs Avg | E19: Weight | F19: Contribution (pp) | H19: Matching customers | I19: {=_xlfn.LET(_xlpm.c,IF(tbl_ProfileBreakdown[Selected]="(Any)","<>",tbl_ProfileBreakdown[Selected]),COUNTIFS(tbl_Clean[Car Ownership],INDEX(_xlpm.c,1),tbl_Clean[Age Band],INDEX(_xlpm.c,2),tbl_Clean[Commute Distance],INDEX(_xlpm.c,3),tbl_Clean[Children],INDEX(_xlpm.c,4),tbl_Clean[Education],INDEX(_xlpm.c,5),tbl_Clean[Region],INDEX(_xlpm.c,6),tbl_Clean[Marital Status],INDEX(_xlpm.c,7),tbl_Clean[Income Band],INDEX(_xlpm.c,8)))} -> 223
A20: Car Ownership | B20: =_xlfn.LET(_xlpm.v,_xlfn.XLOOKUP(tbl_ProfileBreakdown[[#This Row],[Factor]],$A$8:$A$15,Profile_Inputs)&"",IF(_xlpm.v="","(Any)",_xlpm.v)) -> 0-1 Cars | C20: =IF(tbl_ProfileBreakdown[[#This Row],[Selected]]="(Any)",Baseline_Rate,_xlfn.XLOOKUP(tbl_ProfileBreakdown[[#This Row],[Factor]]&"|"&tbl_ProfileBreakdown[[#This Row],[Selected]],tbl_SegmentRates[Key],tbl_SegmentRates[Purchase Rate])) -> 0.58949416 | D20: =tbl_ProfileBreakdown[[#This Row],[Segment Purchase Rate]]/Baseline_Rate -> 1.2255596 | E20: =_xlfn.XLOOKUP(tbl_ProfileBreakdown[[#This Row],[Factor]],tbl_Weights[Factor],tbl_Weights[Weight]) -> 0.17341704 | F20: =tbl_ProfileBreakdown[[#This Row],[Weight]]*(tbl_ProfileBreakdown[[#This Row],[Segment Purchase Rate]]-Baseline_Rate)*100 -> 1.8814736 | H20: Matching buyers | I20: {=_xlfn.LET(_xlpm.c,IF(tbl_ProfileBreakdown[Selected]="(Any)","<>",tbl_ProfileBreakdown[Selected]),COUNTIFS(tbl_Clean[Car Ownership],INDEX(_xlpm.c,1),tbl_Clean[Age Band],INDEX(_xlpm.c,2),tbl_Clean[Commute Distance],INDEX(_xlpm.c,3),tbl_Clean[Children],INDEX(_xlpm.c,4),tbl_Clean[Education],INDEX(_xlpm.c,5),tbl_Clean[Region],INDEX(_xlpm.c,6),tbl_Clean[Marital Status],INDEX(_xlpm.c,7),tbl_Clean[Income Band],INDEX(_xlpm.c,8),tbl_Clean[Purchased Flag],1))} -> 158
A21: Age Band | B21: =_xlfn.LET(_xlpm.v,_xlfn.XLOOKUP(tbl_ProfileBreakdown[[#This Row],[Factor]],$A$8:$A$15,Profile_Inputs)&"",IF(_xlpm.v="","(Any)",_xlpm.v)) -> 31-40 | C21: =IF(tbl_ProfileBreakdown[[#This Row],[Selected]]="(Any)",Baseline_Rate,_xlfn.XLOOKUP(tbl_ProfileBreakdown[[#This Row],[Factor]]&"|"&tbl_ProfileBreakdown[[#This Row],[Selected]],tbl_SegmentRates[Key],tbl_SegmentRates[Purchase Rate])) -> 0.61075949 | D21: =tbl_ProfileBreakdown[[#This Row],[Segment Purchase Rate]]/Baseline_Rate -> 1.2697703 | E21: =_xlfn.XLOOKUP(tbl_ProfileBreakdown[[#This Row],[Factor]],tbl_Weights[Factor],tbl_Weights[Weight]) -> 0.15958231 | F21: =tbl_ProfileBreakdown[[#This Row],[Weight]]*(tbl_ProfileBreakdown[[#This Row],[Segment Purchase Rate]]-Baseline_Rate)*100 -> 2.070732 | H21: Actual purchase rate | I21: =IF(I19=0,"No exact matches. Set some factors to (Any).",I20/I19) -> 0.70852018
A22: Commute Distance | B22: =_xlfn.LET(_xlpm.v,_xlfn.XLOOKUP(tbl_ProfileBreakdown[[#This Row],[Factor]],$A$8:$A$15,Profile_Inputs)&"",IF(_xlpm.v="","(Any)",_xlpm.v)) -> (Any) | C22: =IF(tbl_ProfileBreakdown[[#This Row],[Selected]]="(Any)",Baseline_Rate,_xlfn.XLOOKUP(tbl_ProfileBreakdown[[#This Row],[Factor]]&"|"&tbl_ProfileBreakdown[[#This Row],[Selected]],tbl_SegmentRates[Key],tbl_SegmentRates[Purchase Rate])) -> 0.481 | D22: =tbl_ProfileBreakdown[[#This Row],[Segment Purchase Rate]]/Baseline_Rate -> 1 | E22: =_xlfn.XLOOKUP(tbl_ProfileBreakdown[[#This Row],[Factor]],tbl_Weights[Factor],tbl_Weights[Weight]) -> 0.14426523 | F22: =tbl_ProfileBreakdown[[#This Row],[Weight]]*(tbl_ProfileBreakdown[[#This Row],[Segment Purchase Rate]]-Baseline_Rate)*100 -> 0 | H22: Note | I22: =IF(I19=0,"—",IF(I19<20,"Small sample, read with caution","Sample of "&TEXT(I19,"#,##0")&" customers")) -> Sample of 223 customers
A23: Children | B23: =_xlfn.LET(_xlpm.v,_xlfn.XLOOKUP(tbl_ProfileBreakdown[[#This Row],[Factor]],$A$8:$A$15,Profile_Inputs)&"",IF(_xlpm.v="","(Any)",_xlpm.v)) -> (Any) | C23: =IF(tbl_ProfileBreakdown[[#This Row],[Selected]]="(Any)",Baseline_Rate,_xlfn.XLOOKUP(tbl_ProfileBreakdown[[#This Row],[Factor]]&"|"&tbl_ProfileBreakdown[[#This Row],[Selected]],tbl_SegmentRates[Key],tbl_SegmentRates[Purchase Rate])) -> 0.481 | D23: =tbl_ProfileBreakdown[[#This Row],[Segment Purchase Rate]]/Baseline_Rate -> 1 | E23: =_xlfn.XLOOKUP(tbl_ProfileBreakdown[[#This Row],[Factor]],tbl_Weights[Factor],tbl_Weights[Weight]) -> 0.13903595 | F23: =tbl_ProfileBreakdown[[#This Row],[Weight]]*(tbl_ProfileBreakdown[[#This Row],[Segment Purchase Rate]]-Baseline_Rate)*100 -> 0
A24: Education | B24: =_xlfn.LET(_xlpm.v,_xlfn.XLOOKUP(tbl_ProfileBreakdown[[#This Row],[Factor]],$A$8:$A$15,Profile_Inputs)&"",IF(_xlpm.v="","(Any)",_xlpm.v)) -> (Any) | C24: =IF(tbl_ProfileBreakdown[[#This Row],[Selected]]="(Any)",Baseline_Rate,_xlfn.XLOOKUP(tbl_ProfileBreakdown[[#This Row],[Factor]]&"|"&tbl_ProfileBreakdown[[#This Row],[Selected]],tbl_SegmentRates[Key],tbl_SegmentRates[Purchase Rate])) -> 0.481 | D24: =tbl_ProfileBreakdown[[#This Row],[Segment Purchase Rate]]/Baseline_Rate -> 1 | E24: =_xlfn.XLOOKUP(tbl_ProfileBreakdown[[#This Row],[Factor]],tbl_Weights[Factor],tbl_Weights[Weight]) -> 0.12360009 | F24: =tbl_ProfileBreakdown[[#This Row],[Weight]]*(tbl_ProfileBreakdown[[#This Row],[Segment Purchase Rate]]-Baseline_Rate)*100 -> 0
A25: Region | B25: =_xlfn.LET(_xlpm.v,_xlfn.XLOOKUP(tbl_ProfileBreakdown[[#This Row],[Factor]],$A$8:$A$15,Profile_Inputs)&"",IF(_xlpm.v="","(Any)",_xlpm.v)) -> (Any) | C25: =IF(tbl_ProfileBreakdown[[#This Row],[Selected]]="(Any)",Baseline_Rate,_xlfn.XLOOKUP(tbl_ProfileBreakdown[[#This Row],[Factor]]&"|"&tbl_ProfileBreakdown[[#This Row],[Selected]],tbl_SegmentRates[Key],tbl_SegmentRates[Purchase Rate])) -> 0.481 | D25: =tbl_ProfileBreakdown[[#This Row],[Segment Purchase Rate]]/Baseline_Rate -> 1 | E25: =_xlfn.XLOOKUP(tbl_ProfileBreakdown[[#This Row],[Factor]],tbl_Weights[Factor],tbl_Weights[Weight]) -> 0.0910683 | F25: =tbl_ProfileBreakdown[[#This Row],[Weight]]*(tbl_ProfileBreakdown[[#This Row],[Segment Purchase Rate]]-Baseline_Rate)*100 -> 0
A26: Marital Status | B26: =_xlfn.LET(_xlpm.v,_xlfn.XLOOKUP(tbl_ProfileBreakdown[[#This Row],[Factor]],$A$8:$A$15,Profile_Inputs)&"",IF(_xlpm.v="","(Any)",_xlpm.v)) -> (Any) | C26: =IF(tbl_ProfileBreakdown[[#This Row],[Selected]]="(Any)",Baseline_Rate,_xlfn.XLOOKUP(tbl_ProfileBreakdown[[#This Row],[Factor]]&"|"&tbl_ProfileBreakdown[[#This Row],[Selected]],tbl_SegmentRates[Key],tbl_SegmentRates[Purchase Rate])) -> 0.481 | D26: =tbl_ProfileBreakdown[[#This Row],[Segment Purchase Rate]]/Baseline_Rate -> 1 | E26: =_xlfn.XLOOKUP(tbl_ProfileBreakdown[[#This Row],[Factor]],tbl_Weights[Factor],tbl_Weights[Weight]) -> 0.086598588 | F26: =tbl_ProfileBreakdown[[#This Row],[Weight]]*(tbl_ProfileBreakdown[[#This Row],[Segment Purchase Rate]]-Baseline_Rate)*100 -> 0
A27: Income Band | B27: =_xlfn.LET(_xlpm.v,_xlfn.XLOOKUP(tbl_ProfileBreakdown[[#This Row],[Factor]],$A$8:$A$15,Profile_Inputs)&"",IF(_xlpm.v="","(Any)",_xlpm.v)) -> (Any) | C27: =IF(tbl_ProfileBreakdown[[#This Row],[Selected]]="(Any)",Baseline_Rate,_xlfn.XLOOKUP(tbl_ProfileBreakdown[[#This Row],[Factor]]&"|"&tbl_ProfileBreakdown[[#This Row],[Selected]],tbl_SegmentRates[Key],tbl_SegmentRates[Purchase Rate])) -> 0.481 | D27: =tbl_ProfileBreakdown[[#This Row],[Segment Purchase Rate]]/Baseline_Rate -> 1 | E27: =_xlfn.XLOOKUP(tbl_ProfileBreakdown[[#This Row],[Factor]],tbl_Weights[Factor],tbl_Weights[Weight]) -> 0.082432502 | F27: =tbl_ProfileBreakdown[[#This Row],[Weight]]*(tbl_ProfileBreakdown[[#This Row],[Segment Purchase Rate]]-Baseline_Rate)*100 -> 0
A28: Total | E28: =SUBTOTAL(109,tbl_ProfileBreakdown[Weight]) -> 1 | F28: =SUBTOTAL(109,tbl_ProfileBreakdown[Contribution (pp)]) -> 3.9522056
A30: Verdict
A31: {=_xlfn.LET(_xlpm.f,tbl_ProfileBreakdown[Factor],_xlpm.sel,tbl_ProfileBreakdown[Selected],_xlpm.c,tbl_ProfileBreakdown[Contribution (pp)],_xlpm.mx,MAX(_xlpm.c),_xlpm.mn,MIN(_xlpm.c),_xlpm.pos,IF(_xlpm.mx>0,_xlfn.XLOOKUP(_xlpm.mx,_xlpm.c,_xlpm.f)&" ("&_xlfn.XLOOKUP(_xlpm.mx,_xlpm.c,_xlpm.sel)&")","none"),_xlpm.neg,IF(_xlpm.mn<0,_xlfn.XLOOKUP(_xlpm.mn,_xlpm.c,_xlpm.f)&" ("&_xlfn.XLOOKUP(_xlpm.mn,_xlpm.c,_xlpm.sel)&")","none"),UPPER(I9)&" lead: estimated "&TEXT(I10,"0.0%")&" likelihood to buy ("&TEXT(I11,"0.00")&"x average). Biggest positive driver: "&_xlpm.pos&". Biggest negative driver: "&_xlpm.neg&".")} -> HOT lead: estimated 70.3% likelihood to buy (1.46x average). Biggest positive driver: Age Band (31-40). Biggest negative driver: none.

Sheet Pivot_Analysis
A1: Pivot analysis: PivotTables feeding the Dashboard
A2: Purpose: PivotTables feeding the Dashboard charts, KPI cards and slicers.
A4: KPI totals (all customers) | E4: Takeaway minimum group size | F4: 10
A5: Customers | B5: Buyers | C5: Purchase Rate | E5: The Dashboard takeaways ignore segments smaller than this.
A6: 1000 | B6: 481 | C6: 0.481
E8: Dashboard chart titles (linked)
E9: Age Band | F9: ="Purchase Rate by "&E9&" (overall avg "&TEXT(Baseline_Rate,"0.0%")&")" -> Purchase Rate by Age Band (overall avg 48.1%)
A10: Purchase Rate by Age Band | E10: Commute Distance | F10: ="Purchase Rate by "&E10&" (overall avg "&TEXT(Baseline_Rate,"0.0%")&")" -> Purchase Rate by Commute Distance (overall avg 48.1%)
A11: Age Band | B11: Purchase Rate | E11: Cars Owned | F11: ="Purchase Rate by "&E11&" (overall avg "&TEXT(Baseline_Rate,"0.0%")&")" -> Purchase Rate by Cars Owned (overall avg 48.1%)
A12: 25-30 | B12: 0.35454545 | E12: Number of Children | F12: ="Purchase Rate by "&E12&" (overall avg "&TEXT(Baseline_Rate,"0.0%")&")" -> Purchase Rate by Number of Children (overall avg 48.1%)
A13: 31-40 | B13: 0.61075949
A14: 41-50 | B14: 0.46644295
A15: 51-60 | B15: 0.45454545
A16: 61+ | B16: 0.3
A20: Purchase Rate by Commute Distance
A21: Commute Distance | B21: Purchase Rate
A22: 0-1 Miles | B22: 0.54644809
A23: 1-2 Miles | B23: 0.4556213
A24: 2-5 Miles | B24: 0.58641975
A25: 5-10 Miles | B25: 0.39583333
A26: 10+ Miles | B26: 0.2972973
A30: Purchase Rate by Cars
A31: Cars | B31: Purchase Rate
A32: 0 | B32: 0.61133603
A33: 1 | B33: 0.56928839
A34: 2 | B34: 0.3625731
A35: 3 | B35: 0.38823529
A36: 4 | B36: 0.3559322
A40: Purchase Rate by Children
A41: Children | B41: Purchase Rate
A42: 0 | B42: 0.50533808
A43: 1 | B43: 0.5739645
A44: 2 | B44: 0.46411483
A45: 3 | B45: 0.54477612
A46: 4 | B46: 0.42857143
A47: 5 | B47: 0.22222222
A51: Purchase Rate by Car Ownership
A52: Car Ownership | B52: Purchase Rate
A53: 0-1 Cars | B53: 0.58949416
A54: 2+ Cars | B54: 0.36625514
A58: Customers by Age Band (segment sizes for takeaways)
A59: Age Band | B59: Customers
A60: 25-30 | B60: 110
A61: 31-40 | B61: 316
A62: 41-50 | B62: 298
A63: 51-60 | B63: 176
A64: 61+ | B64: 100
A68: Customers by Commute Distance (segment sizes for takeaways)
A69: Commute Distance | B69: Customers
A70: 0-1 Miles | B70: 366
A71: 1-2 Miles | B71: 169
A72: 2-5 Miles | B72: 162
A73: 5-10 Miles | B73: 192
A74: 10+ Miles | B74: 111
A78: Customers by Car Ownership (segment sizes for takeaways)
A79: Car Ownership | B79: Customers
A80: 0-1 Cars | B80: 514
A81: 2+ Cars | B81: 486

Sheet Recommendations
A1: Recommendations: who to target
A2: Purpose: turns the analysis into actions for the Marketing Manager, with the evidence and limits behind each.
A4: Executive summary
A5: ="Of "&TEXT(Total_Customers,"#,##0")&" customers, "&TEXT(Baseline_Rate,"0.0%")&" bought a bike." -> Of 1,000 customers, 48.1% bought a bike.
A6: ="Targeting the top "&TEXT(_xlfn.XLOOKUP("Hot",tbl_TierSummary[Tier],tbl_TierSummary[Customers])/Total_Customers,"0%")&" by lead score reaches "&TEXT(_xlfn.XLOOKUP("Hot",tbl_TierSummary[Tier],tbl_TierSummary[Share of All Buyers]),"0.0%")&" of all buyers at a "&TEXT(_xlfn.XLOOKUP("Hot",tbl_TierSummary[Tier],tbl_TierSummary[Purchase Rate]),"0.0%")&" purchase rate, "&TEXT(_xlfn.XLOOKUP("Hot",tbl_TierSummary[Tier],tbl_TierSummary[Lift vs Avg]),"0.00")&"x the average." -> Targeting the top 30% by lead score reaches 43.9% of all buyers at a 70.3% purchase rate, 1.46x the average.
A7: =IFERROR(IF(AND(_xlfn.XLOOKUP("Car Ownership",tbl_Significance[Factor],tbl_Significance[Significant?])="Yes",_xlfn.XLOOKUP("Age Band",tbl_Significance[Factor],tbl_Significance[Significant?])="Yes",_xlfn.XLOOKUP("Commute Distance",tbl_Significance[Factor],tbl_Significance[Significant?])="Yes",_xlfn.XLOOKUP("Gender",tbl_Significance[Factor],tbl_Significance[Significant?])="No",_xlfn.XLOOKUP("Home Owner",tbl_Significance[Factor],tbl_Significance[Significant?])="No",_xlfn.XLOOKUP("Occupation",tbl_Significance[Factor],tbl_Significance[Significant?])="No"),"Car ownership, age and commute distance have the biggest effect. Gender, home ownership and occupation make no significant difference.","Factor results have changed. See Significance_Tests for which factors matter."),"See Significance_Tests for which factors matter.") -> Car ownership, age and commute distance have the biggest effect. Gender, home ownership and occupation make no significant difference.
A9: Recommendations
A10: # | B10: Recommendation | C10: Evidence (live) | D10: Source | E10: Priority
A11: 1 | B11: Contact Hot-tier customers first, starting with the priority follow-up list (top 25 non-buyers). | C11: ="Hot tier: "&TEXT(_xlfn.XLOOKUP("Hot",tbl_TierSummary[Tier],tbl_TierSummary[Purchase Rate]),"0.0%")&" purchase rate, "&TEXT(_xlfn.XLOOKUP("Hot",tbl_TierSummary[Tier],tbl_TierSummary[Lift vs Avg]),"0.00")&"x average, "&TEXT(_xlfn.XLOOKUP("Hot",tbl_TierSummary[Tier],tbl_TierSummary[Share of All Buyers]),"0.0%")&" of all buyers from "&TEXT(_xlfn.XLOOKUP("Hot",tbl_TierSummary[Tier],tbl_TierSummary[Customers])/Total_Customers,"0%")&" of customers" -> Hot tier: 70.3% purchase rate, 1.46x average, 43.9% of all buyers from 30% of customers | D11: Lead_Scoring | E11: High
A12: 2 | B12: Pitch bikes as everyday transport to households with 0–1 cars. | C12: =_xlfn.LET(_xlpm.a,_xlfn.XLOOKUP("Car Ownership|0-1 Cars",tbl_SegmentRates[Key],tbl_SegmentRates[Purchase Rate]),_xlpm.b,_xlfn.XLOOKUP("Car Ownership|2+ Cars",tbl_SegmentRates[Key],tbl_SegmentRates[Purchase Rate]),_xlpm.v,_xlfn.XLOOKUP("Car Ownership",tbl_Significance[Factor],tbl_Significance[Cramér''s V]),"0-1 Cars "&TEXT(_xlpm.a,"0.0%")&" vs 2+ Cars "&TEXT(_xlpm.b,"0.0%")&" ("&TEXT((_xlpm.a-_xlpm.b)*100,"+0.0;-0.0;0.0")&" pp); strongest factor used in the model (Cramér's V "&TEXT(_xlpm.v,"0.000")&")") -> 0-1 Cars 58.9% vs 2+ Cars 36.6% (+22.3 pp); strongest factor used in the model (Cramér's V 0.223) | D12: Segment_Analysis, Significance_Tests | E12: High
A13: 3 | B13: Aim ads and channels at customers aged 31–40. | C13: =_xlfn.LET(_xlpm.r,_xlfn.XLOOKUP("Age Band|31-40",tbl_SegmentRates[Key],tbl_SegmentRates[Purchase Rate]),"31-40: "&TEXT(_xlpm.r,"0.0%")&" ("&TEXT(_xlpm.r/Baseline_Rate,"0.00")&"x avg, n = "&TEXT(_xlfn.XLOOKUP("Age Band|31-40",tbl_SegmentRates[Key],tbl_SegmentRates[Customers]),"#,##0")&") vs 61+: "&TEXT(_xlfn.XLOOKUP("Age Band|61+",tbl_SegmentRates[Key],tbl_SegmentRates[Purchase Rate]),"0.0%")&" and 25-30: "&TEXT(_xlfn.XLOOKUP("Age Band|25-30",tbl_SegmentRates[Key],tbl_SegmentRates[Purchase Rate]),"0.0%")) -> 31-40: 61.1% (1.27x avg, n = 316) vs 61+: 30.0% and 25-30: 35.5% | D13: Segment_Analysis | E13: High
A14: 4 | B14: Target people who commute under 5 miles. Spend less on those travelling 10+ miles. | C14: ="0-1 Miles "&TEXT(_xlfn.XLOOKUP("Commute Distance|0-1 Miles",tbl_SegmentRates[Key],tbl_SegmentRates[Purchase Rate]),"0.0%")&", 2-5 Miles "&TEXT(_xlfn.XLOOKUP("Commute Distance|2-5 Miles",tbl_SegmentRates[Key],tbl_SegmentRates[Purchase Rate]),"0.0%")&" vs 10+ Miles "&TEXT(_xlfn.XLOOKUP("Commute Distance|10+ Miles",tbl_SegmentRates[Key],tbl_SegmentRates[Purchase Rate]),"0.0%") -> 0-1 Miles 54.6%, 2-5 Miles 58.6% vs 10+ Miles 29.7% | D14: Segment_Analysis | E14: Medium
A15: 5 | B15: Put the most regional spend into Pacific. In North America, test new messages before cutting budget. | C15: ="Pacific "&TEXT(_xlfn.XLOOKUP("Region|Pacific",tbl_SegmentRates[Key],tbl_SegmentRates[Purchase Rate]),"0.0%")&" vs North America "&TEXT(_xlfn.XLOOKUP("Region|North America",tbl_SegmentRates[Key],tbl_SegmentRates[Purchase Rate]),"0.0%")&" (largest region, n = "&TEXT(_xlfn.XLOOKUP("Region|North America",tbl_SegmentRates[Key],tbl_SegmentRates[Customers]),"#,##0")&")" -> Pacific 58.9% vs North America 43.3% (largest region, n = 508) | D15: Segment_Analysis | E15: Medium
A16: 6 | B16: Don't segment campaigns by gender, home ownership or occupation. | C16: ="p-values "&TEXT(_xlfn.XLOOKUP("Gender",tbl_Significance[Factor],tbl_Significance[p-value]),"0.00")&", "&TEXT(_xlfn.XLOOKUP("Home Owner",tbl_Significance[Factor],tbl_Significance[p-value]),"0.00")&", "&TEXT(_xlfn.XLOOKUP("Occupation",tbl_Significance[Factor],tbl_Significance[p-value]),"0.00")&" (no significant difference)" -> p-values 0.63, 0.63, 0.09 (no significant difference) | D16: Significance_Tests | E16: Medium
A17: 7 | B17: Score new prospects with the Profile Checker before outreach. | C17: =_xlfn.LET(_xlpm.raw,Baseline_Rate+_xlfn.XLOOKUP("Car Ownership",tbl_Weights[Factor],tbl_Weights[Weight])*(_xlfn.XLOOKUP("Car Ownership|0-1 Cars",tbl_SegmentRates[Key],tbl_SegmentRates[Purchase Rate])-Baseline_Rate)+_xlfn.XLOOKUP("Age Band",tbl_Weights[Factor],tbl_Weights[Weight])*(_xlfn.XLOOKUP("Age Band|31-40",tbl_SegmentRates[Key],tbl_SegmentRates[Purchase Rate])-Baseline_Rate),_xlpm.mn,MIN(_xlfn.ANCHORARRAY(Lead_Scoring!$T$5)),_xlpm.mx,MAX(_xlfn.ANCHORARRAY(Lead_Scoring!$T$5)),_xlpm.score,MAX(0,MIN(100,(_xlpm.raw-_xlpm.mn)/(_xlpm.mx-_xlpm.mn)*100)),_xlpm.hot,_xlfn.MINIFS(_xlfn.ANCHORARRAY(Lead_Scoring!$U$5),_xlfn.ANCHORARRAY(Lead_Scoring!$W$5),Hot_Cutoff),_xlpm.warm,_xlfn.MINIFS(_xlfn.ANCHORARRAY(Lead_Scoring!$U$5),_xlfn.ANCHORARRAY(Lead_Scoring!$W$5),Warm_Cutoff),_xlpm.tier,IF(_xlpm.score>=_xlpm.hot,"Hot",IF(_xlpm.score>=_xlpm.warm,"Warm","Cold")),_xlpm.model,_xlfn.XLOOKUP(_xlpm.tier,tbl_TierSummary[Tier],tbl_TierSummary[Purchase Rate]),_xlpm.n,COUNTIFS(tbl_Clean[Car Ownership],"0-1 Cars",tbl_Clean[Age Band],"31-40"),_xlpm.b,COUNTIFS(tbl_Clean[Car Ownership],"0-1 Cars",tbl_Clean[Age Band],"31-40",tbl_Clean[Purchased Flag],1),"Profile 0-1 Cars + 31-40: model "&TEXT(_xlpm.model,"0.0%")&" vs "&TEXT(_xlpm.b/_xlpm.n,"0.0%")&" actual (n = "&TEXT(_xlpm.n,"#,##0")&")") -> Profile 0-1 Cars + 31-40: model 70.3% vs 70.9% actual (n = 223) | D17: Profile_Checker | E17: Low
A19: Limitations
B20: Limitation | C20: Why it matters | D20: Mitigation
B21: ="In-sample model: scores built and evaluated on the same "&TEXT(Total_Customers,"#,##0")&" customers" -> In-sample model: scores built and evaluated on the same 1,000 customers | C21: Real-world lift may be lower | D21: Validate on a hold-out set or the next campaign's results
B22: Correlation, not causation | C22: Car ownership may proxy for income, location or lifestyle | D22: Run an A/B test: Hot-tier targeting vs random
B23: ="Uneven middle deciles (decile 8 converts at "&TEXT(INDEX(tbl_Gains[Purchase Rate],8),"0%")&", above deciles 4–7)" -> Uneven middle deciles (decile 8 converts at 53%, above deciles 4–7) | C23: Scores rank well at the top and bottom, less precisely in the middle | D23: Use tiers (Hot/Warm/Cold), not exact scores
B24: ="Small segments (e.g. 5 children n = "&TEXT(COUNTIFS(tbl_Clean[Children],5),"#,##0")&", Partial High School n = "&TEXT(COUNTIFS(tbl_Clean[Education],"Partial High School"),"#,##0")&"; filtered dashboard groups)" -> Small segments (e.g. 5 children n = 81, Partial High School n = 76; filtered dashboard groups) | C24: Rates from small groups are unstable | D24: Small-group warnings and minimum-n takeaways are built in
B25: No cost or revenue data | C25: Can't calculate campaign ROI | D25: Add cost per contact and margin per bike to estimate return
B26: Public sample dataset (Alex the Analyst) | C26: Not a real company's customers | D26: Treat as a method demonstration
A28: Next steps
A29: • Pilot an A/B test: Hot-tier targeting vs random selection on the next campaign.
A30: • Refit the model with logistic regression on new campaign data.
A31: • Add cost and revenue data to compute campaign ROI.

Sheet Raw_Data
A1: ID | B1: Marital Status | C1: Gender | D1: Income | E1: Children | F1: Education | G1: Occupation | H1: Home Owner | I1: Cars | J1: Commute Distance | K1: Region | L1: Age | M1: Purchased Bike
A2: 12496 | B2: M | C2: F | D2: 40000 | E2: 1 | F2: Bachelors | G2: Skilled Manual | H2: Yes | I2: 0 | J2: 0-1 Miles | K2: Europe | L2: 42 | M2: No
A3: 24107 | B3: M | C3: M | D3: 30000 | E3: 3 | F3: Partial College | G3: Clerical | H3: Yes | I3: 1 | J3: 0-1 Miles | K3: Europe | L3: 43 | M3: No
A4: 14177 | B4: M | C4: M | D4: 80000 | E4: 5 | F4: Partial College | G4: Professional | H4: No | I4: 2 | J4: 2-5 Miles | K4: Europe | L4: 60 | M4: No
A5: 24381 | B5: S | C5: M | D5: 70000 | E5: 0 | F5: Bachelors | G5: Professional | H5: Yes | I5: 1 | J5: 5-10 Miles | K5: Pacific | L5: 41 | M5: Yes
A6: 25597 | B6: S | C6: M | D6: 30000 | E6: 0 | F6: Bachelors | G6: Clerical | H6: No | I6: 0 | J6: 0-1 Miles | K6: Europe | L6: 36 | M6: Yes
A7: 13507 | B7: M | C7: F | D7: 10000 | E7: 2 | F7: Partial College | G7: Manual | H7: Yes | I7: 0 | J7: 1-2 Miles | K7: Europe | L7: 50 | M7: No
A8: 27974 | B8: S | C8: M | D8: 160000 | E8: 2 | F8: High School | G8: Management | H8: Yes | I8: 4 | J8: 0-1 Miles | K8: Pacific | L8: 33 | M8: Yes
A9: 19364 | B9: M | C9: M | D9: 40000 | E9: 1 | F9: Bachelors | G9: Skilled Manual | H9: Yes | I9: 0 | J9: 0-1 Miles | K9: Europe | L9: 43 | M9: Yes
A10: 22155 | B10: M | C10: M | D10: 20000 | E10: 2 | F10: Partial High School | G10: Clerical | H10: Yes | I10: 2 | J10: 5-10 Miles | K10: Pacific | L10: 58 | M10: No
A11: 19280 | B11: M | C11: M | D11: 120000 | E11: 2 | F11: Partial College | G11: Manual | H11: Yes | I11: 1 | J11: 0-1 Miles | K11: Europe | L11: 40 | M11: Yes
A12: 22173 | B12: M | C12: F | D12: 30000 | E12: 3 | F12: High School | G12: Skilled Manual | H12: No | I12: 2 | J12: 1-2 Miles | K12: Pacific | L12: 54 | M12: Yes
A13: 12697 | B13: S | C13: F | D13: 90000 | E13: 0 | F13: Bachelors | G13: Professional | H13: No | I13: 4 | J13: 10+ Miles | K13: Pacific | L13: 36 | M13: No
... A1027: 18484 | B1027: S | C1027: M | D1027: 80000 | E1027: 2 | F1027: High School | G1027: Skilled Manual | H1027: No | I1027: 2 | J1027: 1-2 Miles | K1027: Pacific | L1027: 50 | M1027: Yes
